Workbook
Name sub_7637: 'Форма 807_коды'!#REF!
Name sub_7638: 'Форма 807_коды'!#REF!
Name sub_7639: 'Форма 807_коды'!#REF!
Name sub_7640: 'Форма 807_коды'!#REF!
Name sub_7641: 'Форма 807_коды'!#REF!
Name sub_7642: 'Форма 807_коды'!#REF!
Name sub_7643: 'Форма 807_коды'!#REF!
Name sub_7644: 'Форма 807_коды'!$A$14
Name sub_7645: 'Форма 807_коды'!$A$16
Name sub_7646: 'Форма 807_коды'!$A$17
Name sub_7647: 'Форма 807_коды'!$A$18
Name sub_7648: 'Форма 807_коды'!$A$19
Name sub_7649: 'Форма 807_коды'!$A$20
Name sub_7650: 'Форма 807_коды'!$A$21
Name sub_7651: 'Форма 807_коды'!$A$22
Name sub_7652: 'Форма 807_коды'!$A$23
Name sub_7653: 'Форма 807_коды'!$A$24
Name sub_7654: 'Форма 807_коды'!$A$25
Name sub_7655: 'Форма 807_коды'!$A$26
Name sub_7656: 'Форма 807_коды'!$A$27
Name sub_7657: 'Форма 807_коды'!$A$28
Name sub_7658: 'Форма 807_коды'!$A$29
Name sub_7659: 'Форма 807_коды'!$A$30
Name sub_7660: 'Форма 807_коды'!$A$31
Name sub_7661: 'Форма 807_коды'!$A$32
Name sub_7662: 'Форма 807_коды'!$A$33
Name sub_7663: 'Форма 807_коды'!$A$34
Name sub_7664: 'Форма 807_коды'!$A$35
Name sub_7665: 'Форма 807_коды'!$A$36
Name sub_7666: 'Форма 807_коды'!$A$37
Name sub_7667: 'Форма 807_коды'!$A$39
Name sub_7668: 'Форма 807_коды'!$A$40
Name sub_7669: 'Форма 807_коды'!$A$41
Name sub_7670: 'Форма 807_коды'!$A$42
Name sub_7671: 'Форма 807_коды'!$A$44
Name sub_7672: 'Форма 807_коды'!$A$45
Name sub_7673: 'Форма 807_коды'!$A$46
Name sub_7674: 'Форма 807_коды'!$A$47
Name sub_7675: 'Форма 807_коды'!$A$48
Name sub_7676: 'Форма 807_коды'!$A$49
Name sub_7677: 'Форма 807_коды'!$A$51
Name sub_7678: 'Форма 807_коды'!$A$52
Name sub_7679: 'Форма 807_коды'!$A$53
Name sub_7680: 'Форма 807_коды'!$A$54
Name sub_7681: 'Форма 807_коды'!$A$55
Name sub_7682: 'Форма 807_коды'!$A$57
Name sub_7683: 'Форма 807_коды'!$A$58
Name sub_7684: 'Форма 807_коды'!$A$59
Name sub_7685: 'Форма 807_коды'!$A$60
Name sub_7686: 'Форма 807_коды'!$A$61
Name sub_7687: 'Форма 807_коды'!$A$62
Name sub_7688: 'Форма 807_коды'!$A$63
Name Форма102_2016: #REF!
Name Форма102_2017: #REF!
Name Форма102_2018: #REF!
Name Форма102_2019: #REF!
Name Форма102_2020: #REF!

Sheet Форма 807_коды
A2: Разработочная таблица для составления Отчета о финансовых результатах (публикуемой формы)
A5: Номер | B5: Наименование статьи отчета о финансовых результатах (публикуемой формы) | C5: Символы отчетности по форме 0409102 и их расшифровки в соответствии с отчетностью по форме 04091101
A6: строки
A7: 1 | B7: 2 | C7: 3
A8: Раздел 1. Прибыли и убытки
A9: 1 | B9: Процентные доходы, всего (стр. 1.1 + стр. 1.2 + стр. 1.3 + стр. 1.4), в том числе:
A10: 44197 | B10: от размещения средств в кредитных организациях | C10: 11118 + 11119 + 11215 + 11216 + 11217 + 113 + 114 + 11803 +11807+ 12118 + 12119 + 12215 + 12216 + 12217 + 123 + 13118 + 13119 + 13215 + 13216 + 13217 + 133 + 134 + 13803 + 13807 + S27801/1.1 + S28401/1.1 - 33118 - 33119 - 33215 - 33216 - 33217 - 333 - 334 - 33803 - 33807 - 34118 - 34119 - 34215 - 34216 - 34217 - 34603 - 34607 - 35118 - 35119 - 35215 - 35216 - 35217 - 353 - 354 - 35803 - 35807 + S211/1.1
A11: 44228 | B11: от ссуд, предоставленных клиентам, не являющимся кредитными организациями | C11: 111 (кроме 11118, 11119) + 112 (кроме 11215, 11216, 11217) + 118 (кроме 11803, 11807) + 121 (кроме 12118, 12119) + 122 (кроме 12215, 12216, 12217) + 131 (кроме 13118, 13119) + 132 (кроме 13215, 13216, 13217) + 138 (кроме 13803, 13807) + 28401 + S278/1.2 - S28401/1.1 - 331 (кроме 33118, 33119) - 332 (кроме 33215, 33216, 33217) - 338 (кроме 33803, 33807) - 341 (кроме 34118, 34119) - 342 (кроме 34215, 34216, 34217) - 346 (кроме 34603, 34607) - 351 (кроме 35118, 35119) - 352 (кроме 35215, 35216, 35217) - 358 (кроме 35803, 35807) + S211/1.2
A12: 44256 | B12: от оказания услуг по финансовой аренде (лизингу) | C12: 28303
A13: 44287 | B13: от вложений в ценные бумаги | C13: 115 + 116 + 117 + 135 + 136 + 137 - 335 - 336 - 337 - 343 - 344 - 345 - 355 - 356 - 357
A14: 2 | B14: Процентные расходы, всего (стр. 2.1 + стр. 2.2 + стр. 2.3),
B15: в том числе:
A16: 44198 | B16: по привлеченным средствам кредитных организаций | C16: 311 (кроме 31104, 31105) + 31210 + 31211 + 31315 + 31316 + 31317 + 31415 + 31416 + 31417 + 319 + 321 (кроме 32104, 32105) + 32215 + 32216 + 32217 + 32315 + 32316 + 32317 + 361 (кроме 36104, 36105) + 36210 + 36211 + 36315 + 36316 + 36317 + 36415 + 36416 + 36417 + S47401/2.1 - 141 (кроме 14104, 14105) - 14210 - 14211 - 14315 - 14316 - 14317 - 14415 - 14416 - 14417
A17: 44229 | B17: по привлеченным средствам клиентов, не являющихся кредитными организациями | C17: 31104 + 31105 + 312 (кроме 31210, 31211) + 313 (кроме 31315, 31316, 31317) + 314 (кроме 31415, 31416, 31417) + 315 + 316 + 317 + 32104 + 32105 + 322 (кроме 32215, 32216, 32217) + 323 (кроме 32315, 32316, 32317) + 324 + 325 + 36104 + 36105 + 362 (кроме 36210, 36211) + 363 (кроме 36315, 36316, 36317) + 364 (кроме 36415, 36416, 36417) + 365 + 366 + 367 + 47401 - S47401/2.1 - 14104 - 14105 - 142 (кроме 14210, 14211) - 143 (кроме 14315, 14316, 14317) - 144 (кроме 14415, 14416, 14417) - 145 - 146 - 147
A18: 44257 | B18: по выпущенным ценным бумагам | C18: 318 + 326 + 368 - 148 - 161
A19: 3 | B19: Чистые процентные доходы (отрицательная процентная маржа) (стр. 1 - стр. 2)
A20: 4 | B20: Изменение резерва на возможные потери и оценочного резерва под ожидаемые кредитные убытки по ссудам, ссудной и приравненной к ней задолженности, средствам, размещенным на корреспондентских счетах, а также начисленным процентным доходам, всего, в том числе: | C20: 151 + 152 + 153 + 154 + 155 - S155/16 + 156 - S156/17 + 157 + 171 + 172 + 173 + 174 + 175 + 176 + 177 - S175/16 - S176/17 - 371 - 372 - 373 - 374 - 375 + S375/16 - 376 + S376/17 - 377 - 381 - 382 - 383 - 384 - 385 - 386 - 387 - S385/16 - S386/17 - S/18.1 + S/18.2 + S/4.5 - S/4.6
A21: 44200 | B21: изменение резерва на возможные потери и оценочного резерва под ожидаемые кредитные убытки по начисленным процентным доходам | C21: S/4.1 + S/4.2 - S/4.3 - S/4.4 + S282/4.1 - S473/4.1
A22: 5 | B22: Чистые процентные доходы (отрицательная процентная маржа) после создания резерва на возможные потери (стр. 3 + стр. 4)
A23: 6 | B23: Чистые доходы от операций с финансовыми активами, оцениваемыми по справедливой стоимости через прибыль или убыток | C23: 221 + 222 + 231 + 232 + 251 + 252 + 253 + 254 + 255 + 28104 + S256/6 - 421 - 422 - 431 - 432 - 451 - 452 - 453 - 454 - 455 - S456/6 - 47204
A24: 7 | B24: Чистые доходы от операций с финансовыми обязательствами, оцениваемыми по справедливой стоимости через прибыль или убыток | C24: 28101 + 28102 + 28103 - 47201 - 47202 - 47203
A25: 8 | B25: Чистые доходы от операций с ценными бумагами, оцениваемыми по справедливой стоимости через прочий совокупный доход | C25: 223 + 233 + S256/8 - 423 - 433 - S456/8
A26: 9 | B26: Чистые доходы от операций с ценными бумагами, оцениваемым по амортизированной стоимости | C26: 25611 + 25612 + 25613 + 25614 + 25615 + 224 - S256/6 - S256/8 - 424 - 45611 - 45612 - 45613 - 45614 - 45615 + S456/6 + S456/8
A27: 10 | B27: Чистые доходы от операций с иностранной валютой | C27: 25601 + 25602 + 25603 + 25604 + 25605 + 261 + 262- 45601 - 45602 - 45603 - 45604 - 45605 - 461 - 462
A28: 11 | B28: Чистые доходы от переоценки иностранной валюты | C28: 263 - 463
A29: 12 | B29: Чистые доходы от операций с драгоценными металлами | C29: 25616 + 25617 + 25618 + 25619 + 25620 + 264 + 265 - 45616 - 45617 - 45618 - 45619 - 45620 - 464 - 465
A30: 13 | B30: Доходы от участия в капитале других юридических лиц | C30: 235 + 236 + 237 + 238 + 239 - 435
A31: 14 | B31: Комиссионные доходы | C31: 271 + 272 + 273 + 274 + 275 + 276 + 279
A32: 15 | B32: Комиссионные расходы | C32: 471 (кроме 47108)
A33: 16 | B33: Изменение резерва на возможные потери и оценочного резерва под ожидаемые кредитные убытки по ценным бумагам, оцениваемые по справедливой стоимости через прочий совокупный доход | C33: S155/16 + S175/16 - S375/16 - S385/16
A34: 17 | B34: Изменение резерва на возможные потери и оценочного резерва под ожидаемые кредитные убытки по ценным бумагам, оцениваемым по амортизированной стоимости | C34: S156/17 + S176/17 - S376/17 - S386/17
... A36: 19 | B36: Прочие операционные доходы | C36: 211 + 212 + 213 + 214 + 215 + 216 + 225 + 226 + 241 + 242 + 243 + 244 + 245 + 246 + 247 + 248 + 249 + 25606 + 25607 + 25608 + 25609 + 25610 + 25621 + 25622 + 25623 + 25624 + 25625 + 25626 + 25627 + 277 + 278 + 283 (кроме 28303) + 28402 +285 + 286 + 287 + 288 + 291 + 292 + 294 - S27801/1.1 - S278/1.2 - S211/1.1 - S211/1.2
A37: 20 | B37: Чистые доходы (расходы)
B38: (стр. 5 + стр. 6 + стр. 7 + стр. 8 + стр. 9 + стр.10 + стр. 11 + стр.12 + стр. 13 + стр. 14 - стр. 15 + стр. 16 + стр. 17 + стр.18 + стр. 19)
A39: 21 | B39: Операционные расходы | C39: 411 + 412 + 413 + 414 + 415 + 416 + 425 + 426 + 441 + 442 + 443 + 444 + 445 + 446 + 447 + 448 + 449 + 45606 + 45607 + 45608 + 45609 + 45610 + 45621 + 45622 + 45623 + 45624 + 45625 + 45626 + 45627 + 47108 + 47402 + 475 + 476 + 477 + 47801 + 47802 + 47803 + 481 + 482 + 483 + 484 (кроме 48413) + 486
A40: 22 | B40: Прибыль (убыток) до налогообложения (стр. 20 - стр. 21)
A41: 23 | B41: Возмещение (расход) по налогам | C41: 48413 + 51101 + 51201 - 51202
A42: 24 | B42: Прибыль (убыток) от продолжающейся деятельности
B43: (стр. 22 - стр. 23 - стр. 25)
A44: 25 | B44: Прибыль (убыток) от прекращенной деятельности | C44: 28601 - 47601
A45: 26 | B45: Прибыль (убыток) за отчетный период (стр. 22 - стр. 23)
A46: Раздел 2. Прочий совокупный доход
A47: 1 | B47: Прибыль (убыток) за отчетный период | C47: Статья 26 раздела 1
A48: 2 | B48: Прочий совокупный доход (убыток) | C48: X
A49: 3 | B49: Статьи, которые не переклассифицируются в прибыль или убыток, всего (стр. 3.1 + стр. 3.2),
B50: в том числе:
A51: 44199 | B51: изменение фонда переоценки основных средств и нематериальных активов | C51: 715 - 725
A52: 44230 | B52: изменение фонда переоценки обязательств (требований) по пенсионному обеспечению работников по программам с установленными выплатами | C52: 716 - 726
A53: 4 | B53: Налог на прибыль, относящийся к статьям, которые не могут быть переклассифицированы в прибыль или убыток | C53: 72903 + 72904 + 72905 - 71903 - 71904 - 71905
A54: 5 | B54: Прочий совокупный доход (убыток), который не может быть переклассифицирован в прибыль или убыток, за вычетом налога на прибыль (стр. 3 - стр. 4)
A55: 6 | B55: Статьи, которые могут быть переклассифицированы в прибыль или убыток, всего (стр. 6.1 + стр. 6.2),
B56: в том числе:
A57: 44202 | B57: изменение фонда переоценки финансовых активов, оцениваемых по справедливой стоимости через прочий совокупный доход | C57: 711 + 712 + 713 + 717- 721 - 722 - 723 - 727
A58: 44233 | B58: изменение фонда переоценки финансовых обязательств, оцениваемых по справедливой стоимости через прибыль или убыток | C58: 714 - 724
A59: 44261 | B59: изменение фонда хеджирования денежных потоков | C59: 718 - 728
A60: 7 | B60: Налог на прибыль, относящийся к статьям, которые могут быть переклассифицированы в прибыль или убыток | C60: 72901 + 72902 + 72906 + 72907 + 72908 + 72909 - 71901 - 71902 - 71906 - 71907 - 71908 - 71909
A61: 8 | B61: Прочий совокупный доход (убыток), который может быть переклассифицирован в прибыль или убыток, за вычетом налога на прибыль (стр. 6 - стр. 7)
A62: 9 | B62: Прочий совокупный доход (убыток) за вычетом налога на прибыль (стр. 5 + стр. 8)
A63: 10 | B63: Финансовый результат за отчетный период (стр. 1 + стр. 9)

Sheet Ф_102_2021
A1: Номер п/п | B1: Наименование статей | C1: Символы | D1: Рубли | E1: Ин.валюта | F1: ВСЕГО
B2: Часть 1. Процентные доходы, доходы от корректировок и от восстановления (уменьшения) резервов на возможные потери
B3: Раздел 1. Процентные доходы
B4: 1. По предоставленным кредитам и кредитам, права требования по которым приобретены:
A5: 1. | B5: Минфину России | C5: 11101 | D5: 0 | E5: 0 | F5: 0
A6: 2. | B6: финансовым органам субъектов Российской Федерации и органов местного самоуправления | C6: 11102 | D6: 0 | E6: 0 | F6: 0
A7: 3. | B7: государственным внебюджетным фондам Российской Федерации | C7: 11103 | D7: 0 | E7: 0 | F7: 0
A8: 4. | B8: внебюджетным фондам субъектов Российской Федерации и органов местного самоуправления | C8: 11104 | D8: 0 | E8: 0 | F8: 0
A9: 5. | B9: финансовым организациям, находящимся в федеральной собственности | C9: 11105 | D9: 56209 | E9: 0 | F9: 56209
A10: 6. | B10: коммерческим организациям, находящимся в федеральной собственности | C10: 11106 | D10: 427 | E10: 0 | F10: 427
A11: 7. | B11: некоммерческим организациям, находящимся в федеральной собственности | C11: 11107 | D11: 0 | E11: 0 | F11: 0
A12: 8. | B12: финансовым организациям, находящимся в государственной (кроме федеральной) собственности | C12: 11108 | D12: 3142 | E12: 0 | F12: 3142
A13: 9. | B13: коммерческим организациям, находящимся в государственной (кроме федеральной) собственности | C13: 11109 | D13: 118317 | E13: 0 | F13: 118317
A14: 10. | B14: некоммерческим организациям, находящимся в государственной (кроме федеральной) собственности | C14: 11110 | D14: 0 | E14: 0 | F14: 0
A15: 11. | B15: негосударственным финансовым организациям | C15: 11111 | D15: 570509 | E15: 0 | F15: 570509
A16: 12. | B16: негосударственным коммерческим организациям | C16: 11112 | D16: 6327635 | E16: 157628 | F16: 6485263
... A24: 20. | B24: иностранным государствам | C24: 11120 | D24: 0 | E24: 0 | F24: 0
B25: Итого по символам 11101 - 11120 | D25: 21436032 | E25: 1203708 | F25: 22639740
B26: 2. По прочим размещенным средствам, в том числе по прочим приобретенным правам требования:
A27: 1. | B27: в Минфине России | C27: 11201 | D27: 0 | E27: 0 | F27: 0
A28: 2. | B28: в финансовых органах субъектов Российской Федерации и органов местного самоуправления | C28: 11202 | D28: 0 | E28: 0 | F28: 0
A29: 3. | B29: в государственных внебюджетных фондах Российской Федерации | C29: 11203 | D29: 0 | E29: 0 | F29: 0
A30: 4. | B30: во внебюджетных фондах субъектов Российской Федерации и органов местного самоуправления | C30: 11204 | D30: 0 | E30: 0 | F30: 0
A31: 5. | B31: в финансовых организациях, находящихся в федеральной собственности | C31: 11205 | D31: 0 | E31: 0 | F31: 0
A32: 6. | B32: в коммерческих организациях, находящихся в федеральной собственности | C32: 11206 | D32: 0 | E32: 0 | F32: 0
A33: 7. | B33: в некоммерческих организациях, находящихся в федеральной собственности | C33: 11207 | D33: 0 | E33: 0 | F33: 0
A34: 8. | B34: в финансовых организациях, находящихся в государственной (кроме федеральной) собственности | C34: 11208 | D34: 0 | E34: 0 | F34: 0
A35: 9. | B35: в коммерческих организациях, находящихся в государственной (кроме федеральной) собственности | C35: 11209 | D35: 0 | E35: 0 | F35: 0
A36: 10. | B36: в некоммерческих организациях, находящихся в государственной (кроме федеральной) собственности | C36: 11210 | D36: 0 | E36: 0 | F36: 0
A37: 11. | B37: в негосударственных финансовых организациях | C37: 11211 | D37: 39320 | E37: 0 | F37: 39320
A38: 12. | B38: в негосударственных коммерческих организациях | C38: 11212 | D38: 245858 | E38: 0 | F38: 245858
... A46: 20. | B46: физическим лицам - нерезидентам | C46: 11220 | D46: 0 | E46: 0 | F46: 0
B47: Итого по символам 11201 - 11220 | D47: 2194181 | E47: 2086 | F47: 2196267
B48: 3. По денежным средствам на счетах:
A49: 1. | B49: в Банке России | C49: 11301 | D49: 85243 | E49: 0 | F49: 85243
A50: 2. | B50: в кредитных организациях | C50: 11302 | D50: 2 | E50: 188 | F50: 190
A51: 3. | B51: в банках-нерезидентах | C51: 11303 | D51: 0 | E51: 1510 | F51: 1510
B52: Итого по символам 11301 - 11303 | D52: 85245 | E52: 1698 | F52: 86943
B53: 4. По депозитам размещенным:
A54: 1. | B54: в Банке России | C54: 11401 | D54: 0 | E54: 0 | F54: 0
A55: 2. | B55: в кредитных организациях | C55: 11402 | D55: 0 | E55: 0 | F55: 0
A56: 3. | B56: в банках-нерезидентах | C56: 11403 | D56: 0 | E56: 0 | F56: 0
B57: Итого по символам 11401 - 11403 | D57: 0 | E57: 0 | F57: 0
B58: 5. По вложениям в долговые ценные бумаги, оцениваемые по справедливой стоимости через прибыль или убыток (кроме векселей):
A59: 1. | B59: Российской Федерации | C59: 11501 | D59: 8149 | E59: 0 | F59: 8149
A60: 2. | B60: субъектов Российской Федерации и органов местного самоуправления | C60: 11502 | D60: 0 | E60: 0 | F60: 0
A61: 3. | B61: Банка России | C61: 11503 | D61: 0 | E61: 0 | F61: 0
A62: 4. | B62: кредитных организаций | C62: 11504 | D62: 0 | E62: 0 | F62: 0
A63: 5. | B63: прочих резидентов | C63: 11505 | D63: 204806 | E63: 0 | F63: 204806
A64: 6. | B64: иностранных государств | C64: 11506 | D64: 0 | E64: 0 | F64: 0
A65: 7. | B65: банков-нерезидентов | C65: 11507 | D65: 0 | E65: 0 | F65: 0
A66: 8. | B66: прочих нерезидентов | C66: 11508 | D66: 0 | E66: 0 | F66: 0
B67: Итого по символам 11501 - 11508 | D67: 212955 | E67: 0 | F67: 212955
B68: 6. По вложениям в долговые ценные бумаги, оцениваемые по справедливой стоимости через прочий совокупный доход (кроме векселей):
A69: 1. | B69: Российской Федерации | C69: 11601 | D69: 361746 | E69: 0 | F69: 361746
A70: 2. | B70: субъектов Российской Федерации и органов местного самоуправления | C70: 11602 | D70: 0 | E70: 0 | F70: 0
A71: 3. | B71: Банка России | C71: 11603 | D71: 0 | E71: 0 | F71: 0
A72: 4. | B72: кредитных организаций | C72: 11604 | D72: 39973 | E72: 20923 | F72: 60896
A73: 5. | B73: прочих резидентов | C73: 11605 | D73: 150756 | E73: 0 | F73: 150756
A74: 6. | B74: иностранных государств | C74: 11606 | D74: 0 | E74: 0 | F74: 0
A75: 7. | B75: банков-нерезидентов | C75: 11607 | D75: 0 | E75: 0 | F75: 0
A76: 8. | B76: прочих нерезидентов | C76: 11608 | D76: 15533 | E76: 3116819 | F76: 3132352
B77: Итого по символам 11601 - 11608 | D77: 568008 | E77: 3137742 | F77: 3705750
B78: 7. По вложениям в долговые ценные бумаги, оцениваемые по амортизированной стоимости (кроме векселей):
A79: 1. | B79: Российской Федерации | C79: 11701 | D79: 42651 | E79: 0 | F79: 42651
A80: 2. | B80: субъектов Российской Федерации и органов местного самоуправления | C80: 11702 | D80: 330600 | E80: 0 | F80: 330600
A81: 3. | B81: Банка России | C81: 11703 | D81: 0 | E81: 0 | F81: 0
A82: 4. | B82: кредитных организаций | C82: 11704 | D82: 437859 | E82: 68653 | F82: 506512
A83: 5. | B83: прочих резидентов | C83: 11705 | D83: 5440952 | E83: 0 | F83: 5440952
A84: 6. | B84: иностранных государств | C84: 11706 | D84: 0 | E84: 57562 | F84: 57562
A85: 7. | B85: банков-нерезидентов | C85: 11707 | D85: 0 | E85: 0 | F85: 0
A86: 8. | B86: прочих нерезидентов | C86: 11708 | D86: 680036 | E86: 1435347 | F86: 2115383
B87: Итого по символам 11701 - 11708 | D87: 6932098 | E87: 1561562 | F87: 8493660
B88: 8. По вложениям в учтенные векселя:
A89: 1. | B89: органов федеральной власти | C89: 11801 | D89: 0 | E89: 0 | F89: 0
A90: 2. | B90: органов власти субъектов Российской Федерации и органов местного самоуправления | C90: 11802 | D90: 0 | E90: 0 | F90: 0
A91: 3. | B91: кредитных организаций | C91: 11803 | D91: 0 | E91: 0 | F91: 0
A92: 4. | B92: прочих резидентов | C92: 11804 | D92: 98 | E92: 0 | F92: 98
A93: 5. | B93: органов государственной власти иностранных государств | C93: 11805 | D93: 0 | E93: 0 | F93: 0
A94: 6. | B94: органов местной власти иностранных государств | C94: 11806 | D94: 0 | E94: 0 | F94: 0
A95: 7. | B95: банков-нерезидентов | C95: 11807 | D95: 0 | E95: 0 | F95: 0
A96: 8. | B96: прочих нерезидентов | C96: 11808 | D96: 0 | E96: 0 | F96: 0
B97: Итого по символам 11801 - 11808 | D97: 98 | E97: 0 | F97: 98
B98: Итого по разделу 1 | D98: 31428617 | E98: 5906796 | F98: 37335413
B99: Раздел 2. Комиссионные доходы
B100: 1. По предоставленным кредитам и кредитам, права требования по которым приобретены:
A101: 1. | B101: Минфину России | C101: 12101 | D101: 0 | E101: 0 | F101: 0
A102: 2. | B102: финансовым органам субъектов Российской Федерации и органов местного самоуправления | C102: 12102 | D102: 0 | E102: 0 | F102: 0
A103: 3. | B103: государственным внебюджетным фондам Российской Федерации | C103: 12103 | D103: 0 | E103: 0 | F103: 0
A104: 4. | B104: внебюджетным фондам субъектов Российской Федерации и органов местного самоуправления | C104: 12104 | D104: 0 | E104: 0 | F104: 0
A105: 5. | B105: финансовым организациям, находящимся в федеральной собственности | C105: 12105 | D105: 0 | E105: 0 | F105: 0
A106: 6. | B106: коммерческим организациям, находящимся в федеральной собственности | C106: 12106 | D106: 0 | E106: 0 | F106: 0
A107: 7. | B107: некоммерческим организациям, находящимся в федеральной собственности | C107: 12107 | D107: 0 | E107: 0 | F107: 0
A108: 8. | B108: финансовым организациям, находящимся в государственной (кроме федеральной) собственности | C108: 12108 | D108: 0 | E108: 0 | F108: 0
A109: 9. | B109: коммерческим организациям, находящимся в государственной (кроме федеральной) собственности | C109: 12109 | D109: 34 | E109: 0 | F109: 34
A110: 10. | B110: некоммерческим организациям, находящимся в государственной (кроме федеральной) собственности | C110: 12110 | D110: 0 | E110: 0 | F110: 0
A111: 11. | B111: негосударственным финансовым организациям | C111: 12111 | D111: 0 | E111: 0 | F111: 0
A112: 12. | B112: негосударственным коммерческим организациям | C112: 12112 | D112: 619 | E112: 0 | F112: 619
... A120: 20. | B120: иностранным государствам | C120: 12120 | D120: 0 | E120: 0 | F120: 0
B121: Итого по символам 12101 - 12120 | D121: 35195 | E121: 345702 | F121: 380897
...

Sheet Ф_102_2020
A1: Номер п/п | B1: Наименование статей | C1: Символы | D1: Рубли | E1: Ин.валюта | F1: ВСЕГО
B2: Часть 1. Процентные доходы, доходы от корректировок и от восстановления (уменьшения) резервов на возможные потери
B3: Раздел 1. Процентные доходы
B4: 1. По предоставленным кредитам и кредитам, права требования по которым приобретены:
A5: 1. | B5: Минфину России | C5: 11101 | D5: 0 | E5: 0 | F5: 0
A6: 2. | B6: финансовым органам субъектов Российской Федерации и органов местного самоуправления | C6: 11102 | D6: 0 | E6: 0 | F6: 0
A7: 3. | B7: государственным внебюджетным фондам Российской Федерации | C7: 11103 | D7: 0 | E7: 0 | F7: 0
A8: 4. | B8: внебюджетным фондам субъектов Российской Федерации и органов местного самоуправления | C8: 11104 | D8: 0 | E8: 0 | F8: 0
A9: 5. | B9: финансовым организациям, находящимся в федеральной собственности | C9: 11105 | D9: 81951 | E9: 0 | F9: 81951
A10: 6. | B10: коммерческим организациям, находящимся в федеральной собственности | C10: 11106 | D10: 38509 | E10: 0 | F10: 38509
A11: 7. | B11: некоммерческим организациям, находящимся в федеральной собственности | C11: 11107 | D11: 0 | E11: 0 | F11: 0
A12: 8. | B12: финансовым организациям, находящимся в государственной (кроме федеральной) собственности | C12: 11108 | D12: 12167 | E12: 0 | F12: 12167
A13: 9. | B13: коммерческим организациям, находящимся в государственной (кроме федеральной) собственности | C13: 11109 | D13: 80366 | E13: 0 | F13: 80366
A14: 10. | B14: некоммерческим организациям, находящимся в государственной (кроме федеральной) собственности | C14: 11110 | D14: 0 | E14: 0 | F14: 0
A15: 11. | B15: негосударственным финансовым организациям | C15: 11111 | D15: 829435 | E15: 0 | F15: 829435
A16: 12. | B16: негосударственным коммерческим организациям | C16: 11112 | D16: 7637180 | E16: 17855 | F16: 7655035
... A24: 20. | B24: иностранным государствам | C24: 11120 | D24: 0 | E24: 0 | F24: 0
B25: Итого по символам 11101 - 11120 | D25: 20960733 | E25: 702697 | F25: 21663430
B26: 2. По прочим размещенным средствам, в том числе по прочим приобретенным правам требования:
A27: 1. | B27: в Минфине России | C27: 11201 | D27: 0 | E27: 0 | F27: 0
A28: 2. | B28: в финансовых органах субъектов Российской Федерации и органов местного самоуправления | C28: 11202 | D28: 0 | E28: 0 | F28: 0
A29: 3. | B29: в государственных внебюджетных фондах Российской Федерации | C29: 11203 | D29: 0 | E29: 0 | F29: 0
A30: 4. | B30: во внебюджетных фондах субъектов Российской Федерации и органов местного самоуправления | C30: 11204 | D30: 0 | E30: 0 | F30: 0
A31: 5. | B31: в финансовых организациях, находящихся в федеральной собственности | C31: 11205 | D31: 0 | E31: 0 | F31: 0
A32: 6. | B32: в коммерческих организациях, находящихся в федеральной собственности | C32: 11206 | D32: 0 | E32: 0 | F32: 0
A33: 7. | B33: в некоммерческих организациях, находящихся в федеральной собственности | C33: 11207 | D33: 0 | E33: 0 | F33: 0
A34: 8. | B34: в финансовых организациях, находящихся в государственной (кроме федеральной) собственности | C34: 11208 | D34: 0 | E34: 0 | F34: 0
A35: 9. | B35: в коммерческих организациях, находящихся в государственной (кроме федеральной) собственности | C35: 11209 | D35: 0 | E35: 0 | F35: 0
A36: 10. | B36: в некоммерческих организациях, находящихся в государственной (кроме федеральной) собственности | C36: 11210 | D36: 0 | E36: 0 | F36: 0
A37: 11. | B37: в негосударственных финансовых организациях | C37: 11211 | D37: 440391 | E37: 13623 | F37: 454014
A38: 12. | B38: в негосударственных коммерческих организациях | C38: 11212 | D38: 182605 | E38: 0 | F38: 182605
... A46: 20. | B46: физическим лицам - нерезидентам | C46: 11220 | D46: 0 | E46: 0 | F46: 0
B47: Итого по символам 11201 - 11220 | D47: 2363150 | E47: 18797 | F47: 2381947
B48: 3. По денежным средствам на счетах:
A49: 1. | B49: в Банке России | C49: 11301 | D49: 673154 | E49: 0 | F49: 673154
A50: 2. | B50: в кредитных организациях | C50: 11302 | D50: 5 | E50: 120 | F50: 125
A51: 3. | B51: в банках-нерезидентах | C51: 11303 | D51: 0 | E51: 1920 | F51: 1920
B52: Итого по символам 11301 - 11303 | D52: 673159 | E52: 2040 | F52: 675199
B53: 4. По депозитам размещенным:
A54: 1. | B54: в Банке России | C54: 11401 | D54: 0 | E54: 0 | F54: 0
A55: 2. | B55: в кредитных организациях | C55: 11402 | D55: 0 | E55: 0 | F55: 0
A56: 3. | B56: в банках-нерезидентах | C56: 11403 | D56: 0 | E56: 1146 | F56: 1146
B57: Итого по символам 11401 - 11403 | D57: 0 | E57: 1146 | F57: 1146
B58: 5. По вложениям в долговые ценные бумаги, оцениваемые по справедливой стоимости через прибыль или убыток (кроме векселей):
A59: 1. | B59: Российской Федерации | C59: 11501 | D59: 4578 | E59: 0 | F59: 4578
A60: 2. | B60: субъектов Российской Федерации и органов местного самоуправления | C60: 11502 | D60: 0 | E60: 0 | F60: 0
A61: 3. | B61: Банка России | C61: 11503 | D61: 0 | E61: 0 | F61: 0
A62: 4. | B62: кредитных организаций | C62: 11504 | D62: 0 | E62: 0 | F62: 0
A63: 5. | B63: прочих резидентов | C63: 11505 | D63: 26304 | E63: 0 | F63: 26304
A64: 6. | B64: иностранных государств | C64: 11506 | D64: 0 | E64: 0 | F64: 0
A65: 7. | B65: банков-нерезидентов | C65: 11507 | D65: 0 | E65: 0 | F65: 0
A66: 8. | B66: прочих нерезидентов | C66: 11508 | D66: 0 | E66: 0 | F66: 0
B67: Итого по символам 11501 - 11508 | D67: 30882 | E67: 0 | F67: 30882
B68: 6. По вложениям в долговые ценные бумаги, оцениваемые по справедливой стоимости через прочий совокупный доход (кроме векселей):
A69: 1. | B69: Российской Федерации | C69: 11601 | D69: 500652 | E69: 0 | F69: 500652
A70: 2. | B70: субъектов Российской Федерации и органов местного самоуправления | C70: 11602 | D70: 0 | E70: 0 | F70: 0
A71: 3. | B71: Банка России | C71: 11603 | D71: 0 | E71: 0 | F71: 0
A72: 4. | B72: кредитных организаций | C72: 11604 | D72: 64734 | E72: 17482 | F72: 82216
A73: 5. | B73: прочих резидентов | C73: 11605 | D73: 211185 | E73: 0 | F73: 211185
A74: 6. | B74: иностранных государств | C74: 11606 | D74: 0 | E74: 23646 | F74: 23646
A75: 7. | B75: банков-нерезидентов | C75: 11607 | D75: 6611 | E75: 0 | F75: 6611
A76: 8. | B76: прочих нерезидентов | C76: 11608 | D76: 26179 | E76: 2968620 | F76: 2994799
B77: Итого по символам 11601 - 11608 | D77: 809361 | E77: 3009748 | F77: 3819109
B78: 7. По вложениям в долговые ценные бумаги, оцениваемые по амортизированной стоимости (кроме векселей):
A79: 1. | B79: Российской Федерации | C79: 11701 | D79: 115185 | E79: 0 | F79: 115185
A80: 2. | B80: субъектов Российской Федерации и органов местного самоуправления | C80: 11702 | D80: 0 | E80: 0 | F80: 0
A81: 3. | B81: Банка России | C81: 11703 | D81: 0 | E81: 0 | F81: 0
A82: 4. | B82: кредитных организаций | C82: 11704 | D82: 204211 | E82: 51126 | F82: 255337
A83: 5. | B83: прочих резидентов | C83: 11705 | D83: 6339722 | E83: 0 | F83: 6339722
A84: 6. | B84: иностранных государств | C84: 11706 | D84: 0 | E84: 44239 | F84: 44239
A85: 7. | B85: банков-нерезидентов | C85: 11707 | D85: 0 | E85: 10372 | F85: 10372
A86: 8. | B86: прочих нерезидентов | C86: 11708 | D86: 229587 | E86: 1186266 | F86: 1415853
B87: Итого по символам 11701 - 11708 | D87: 6888705 | E87: 1292003 | F87: 8180708
B88: 8. По вложениям в учтенные векселя:
A89: 1. | B89: органов федеральной власти | C89: 11801 | D89: 0 | E89: 0 | F89: 0
A90: 2. | B90: органов власти субъектов Российской Федерации и органов местного самоуправления | C90: 11802 | D90: 0 | E90: 0 | F90: 0
A91: 3. | B91: кредитных организаций | C91: 11803 | D91: 20 | E91: 0 | F91: 20
A92: 4. | B92: прочих резидентов | C92: 11804 | D92: 25109 | E92: 0 | F92: 25109
A93: 5. | B93: органов государственной власти иностранных государств | C93: 11805 | D93: 0 | E93: 0 | F93: 0
A94: 6. | B94: органов местной власти иностранных государств | C94: 11806 | D94: 0 | E94: 0 | F94: 0
A95: 7. | B95: банков-нерезидентов | C95: 11807 | D95: 0 | E95: 0 | F95: 0
A96: 8. | B96: прочих нерезидентов | C96: 11808 | D96: 0 | E96: 0 | F96: 0
B97: Итого по символам 11801 - 11808 | D97: 25129 | E97: 0 | F97: 25129
B98: Итого по разделу 1 | D98: 31751119 | E98: 5026431 | F98: 36777550
B99: Раздел 2. Комиссионные доходы
B100: 1. По предоставленным кредитам и кредитам, права требования по которым приобретены:
A101: 1. | B101: Минфину России | C101: 12101 | D101: 0 | E101: 0 | F101: 0
A102: 2. | B102: финансовым органам субъектов Российской Федерации и органов местного самоуправления | C102: 12102 | D102: 0 | E102: 0 | F102: 0
A103: 3. | B103: государственным внебюджетным фондам Российской Федерации | C103: 12103 | D103: 0 | E103: 0 | F103: 0
A104: 4. | B104: внебюджетным фондам субъектов Российской Федерации и органов местного самоуправления | C104: 12104 | D104: 0 | E104: 0 | F104: 0
A105: 5. | B105: финансовым организациям, находящимся в федеральной собственности | C105: 12105 | D105: 0 | E105: 0 | F105: 0
A106: 6. | B106: коммерческим организациям, находящимся в федеральной собственности | C106: 12106 | D106: 0 | E106: 0 | F106: 0
A107: 7. | B107: некоммерческим организациям, находящимся в федеральной собственности | C107: 12107 | D107: 0 | E107: 0 | F107: 0
A108: 8. | B108: финансовым организациям, находящимся в государственной (кроме федеральной) собственности | C108: 12108 | D108: 0 | E108: 0 | F108: 0
A109: 9. | B109: коммерческим организациям, находящимся в государственной (кроме федеральной) собственности | C109: 12109 | D109: 0 | E109: 0 | F109: 0
A110: 10. | B110: некоммерческим организациям, находящимся в государственной (кроме федеральной) собственности | C110: 12110 | D110: 0 | E110: 0 | F110: 0
A111: 11. | B111: негосударственным финансовым организациям | C111: 12111 | D111: 0 | E111: 0 | F111: 0
A112: 12. | B112: негосударственным коммерческим организациям | C112: 12112 | D112: 865 | E112: 0 | F112: 865
... A120: 20. | B120: иностранным государствам | C120: 12120 | D120: 0 | E120: 0 | F120: 0
B121: Итого по символам 12101 - 12120 | D121: 953 | E121: 154137 | F121: 155090
...

Sheet Ф_102_2019
A1: Номер п/п | B1: Наименование статей | C1: Символы | D1: Рубли | E1: Ин.валюта | F1: ВСЕГО
B2: Часть 1. Процентные доходы, доходы от корректировок и от восстановления (уменьшения) резервов на возможные потери
B3: Раздел 1. Процентные доходы
B4: 1. По предоставленным кредитам и кредитам, права требования по которым приобретены:
A5: 1. | B5: Минфину России | C5: 11101 | D5: 0 | E5: 0 | F5: 0
A6: 2. | B6: финансовым органам субъектов Российской Федерации и органов местного самоуправления | C6: 11102 | D6: 2669 | E6: 0 | F6: 2669
A7: 3. | B7: государственным внебюджетным фондам Российской Федерации | C7: 11103 | D7: 0 | E7: 0 | F7: 0
A8: 4. | B8: внебюджетным фондам субъектов Российской Федерации и органов местного самоуправления | C8: 11104 | D8: 0 | E8: 0 | F8: 0
A9: 5. | B9: финансовым организациям, находящимся в федеральной собственности | C9: 11105 | D9: 107800 | E9: 0 | F9: 107800
A10: 6. | B10: коммерческим организациям, находящимся в федеральной собственности | C10: 11106 | D10: 17462 | E10: 0 | F10: 17462
A11: 7. | B11: некоммерческим организациям, находящимся в федеральной собственности | C11: 11107 | D11: 0 | E11: 0 | F11: 0
A12: 8. | B12: финансовым организациям, находящимся в государственной (кроме федеральной) собственности | C12: 11108 | D12: 0 | E12: 0 | F12: 0
A13: 9. | B13: коммерческим организациям, находящимся в государственной (кроме федеральной) собственности | C13: 11109 | D13: 50561 | E13: 0 | F13: 50561
A14: 10. | B14: некоммерческим организациям, находящимся в государственной (кроме федеральной) собственности | C14: 11110 | D14: 269597 | E14: 0 | F14: 269597
A15: 11. | B15: негосударственным финансовым организациям | C15: 11111 | D15: 854130 | E15: 22240 | F15: 876370
A16: 12. | B16: негосударственным коммерческим организациям | C16: 11112 | D16: 8797995 | E16: 178885 | F16: 8976880
... A24: 20. | B24: иностранным государствам | C24: 11120 | D24: 0 | E24: 0 | F24: 0
B25: Итого по символам 11101 - 11120 | D25: 22622853 | E25: 919307 | F25: 23542160
B26: 2. По прочим размещенным средствам, в том числе по прочим приобретенным правам требования:
A27: 1. | B27: в Минфине России | C27: 11201 | D27: 0 | E27: 0 | F27: 0
A28: 2. | B28: в финансовых органах субъектов Российской Федерации и органов местного самоуправления | C28: 11202 | D28: 0 | E28: 0 | F28: 0
A29: 3. | B29: в государственных внебюджетных фондах Российской Федерации | C29: 11203 | D29: 0 | E29: 0 | F29: 0
A30: 4. | B30: во внебюджетных фондах субъектов Российской Федерации и органов местного самоуправления | C30: 11204 | D30: 0 | E30: 0 | F30: 0
A31: 5. | B31: в финансовых организациях, находящихся в федеральной собственности | C31: 11205 | D31: 0 | E31: 0 | F31: 0
A32: 6. | B32: в коммерческих организациях, находящихся в федеральной собственности | C32: 11206 | D32: 0 | E32: 0 | F32: 0
A33: 7. | B33: в некоммерческих организациях, находящихся в федеральной собственности | C33: 11207 | D33: 0 | E33: 0 | F33: 0
A34: 8. | B34: в финансовых организациях, находящихся в государственной (кроме федеральной) собственности | C34: 11208 | D34: 0 | E34: 0 | F34: 0
A35: 9. | B35: в коммерческих организациях, находящихся в государственной (кроме федеральной) собственности | C35: 11209 | D35: 0 | E35: 0 | F35: 0
A36: 10. | B36: в некоммерческих организациях, находящихся в государственной (кроме федеральной) собственности | C36: 11210 | D36: 0 | E36: 0 | F36: 0
A37: 11. | B37: в негосударственных финансовых организациях | C37: 11211 | D37: 488327 | E37: 0 | F37: 488327
A38: 12. | B38: в негосударственных коммерческих организациях | C38: 11212 | D38: 155783 | E38: 0 | F38: 155783
... A46: 20. | B46: физическим лицам - нерезидентам | C46: 11220 | D46: 0 | E46: 0 | F46: 0
B47: Итого по символам 11201 - 11220 | D47: 3172713 | E47: 243 | F47: 3172956
B48: 3. По денежным средствам на счетах:
A49: 1. | B49: в Банке России | C49: 11301 | D49: 2679550 | E49: 0 | F49: 2679550
A50: 2. | B50: в кредитных организациях | C50: 11302 | D50: 6 | E50: 144 | F50: 150
A51: 3. | B51: в банках-нерезидентах | C51: 11303 | D51: 0 | E51: 2892 | F51: 2892
B52: Итого по символам 11301 - 11303 | D52: 2679556 | E52: 3036 | F52: 2682592
B53: 4. По депозитам размещенным:
A54: 1. | B54: в Банке России | C54: 11401 | D54: 0 | E54: 0 | F54: 0
A55: 2. | B55: в кредитных организациях | C55: 11402 | D55: 0 | E55: 0 | F55: 0
A56: 3. | B56: в банках-нерезидентах | C56: 11403 | D56: 0 | E56: 6713 | F56: 6713
B57: Итого по символам 11401 - 11403 | D57: 0 | E57: 6713 | F57: 6713
B58: 5. По вложениям в долговые ценные бумаги, оцениваемые по справедливой стоимости через прибыль или убыток (кроме векселей):
A59: 1. | B59: Российской Федерации | C59: 11501 | D59: 84716 | E59: 0 | F59: 84716
A60: 2. | B60: субъектов Российской Федерации и органов местного самоуправления | C60: 11502 | D60: 0 | E60: 0 | F60: 0
A61: 3. | B61: Банка России | C61: 11503 | D61: 0 | E61: 0 | F61: 0
A62: 4. | B62: кредитных организаций | C62: 11504 | D62: 0 | E62: 0 | F62: 0
A63: 5. | B63: прочих резидентов | C63: 11505 | D63: 7395 | E63: 0 | F63: 7395
A64: 6. | B64: иностранных государств | C64: 11506 | D64: 0 | E64: 0 | F64: 0
A65: 7. | B65: банков-нерезидентов | C65: 11507 | D65: 0 | E65: 0 | F65: 0
A66: 8. | B66: прочих нерезидентов | C66: 11508 | D66: 0 | E66: 0 | F66: 0
B67: Итого по символам 11501 - 11508 | D67: 92111 | E67: 0 | F67: 92111
B68: 6. По вложениям в долговые ценные бумаги, оцениваемые по справедливой стоимости через прочий совокупный доход (кроме векселей):
A69: 1. | B69: Российской Федерации | C69: 11601 | D69: 345800 | E69: 0 | F69: 345800
A70: 2. | B70: субъектов Российской Федерации и органов местного самоуправления | C70: 11602 | D70: 21 | E70: 0 | F70: 21
A71: 3. | B71: Банка России | C71: 11603 | D71: 0 | E71: 0 | F71: 0
A72: 4. | B72: кредитных организаций | C72: 11604 | D72: 45901 | E72: 0 | F72: 45901
A73: 5. | B73: прочих резидентов | C73: 11605 | D73: 296939 | E73: 0 | F73: 296939
A74: 6. | B74: иностранных государств | C74: 11606 | D74: 13888 | E74: 0 | F74: 13888
A75: 7. | B75: банков-нерезидентов | C75: 11607 | D75: 546 | E75: 0 | F75: 546
A76: 8. | B76: прочих нерезидентов | C76: 11608 | D76: 2788891 | E76: 0 | F76: 2788891
B77: Итого по символам 11601 - 11608 | D77: 3491986 | E77: 0 | F77: 3491986
B78: 7. По вложениям в долговые ценные бумаги, оцениваемые по амортизированной стоимости (кроме векселей):
A79: 1. | B79: Российской Федерации | C79: 11701 | D79: 450114 | E79: 0 | F79: 450114
A80: 2. | B80: субъектов Российской Федерации и органов местного самоуправления | C80: 11702 | D80: 75718 | E80: 0 | F80: 75718
A81: 3. | B81: Банка России | C81: 11703 | D81: 0 | E81: 0 | F81: 0
A82: 4. | B82: кредитных организаций | C82: 11704 | D82: 94210 | E82: 0 | F82: 94210
A83: 5. | B83: прочих резидентов | C83: 11705 | D83: 2813502 | E83: 0 | F83: 2813502
A84: 6. | B84: иностранных государств | C84: 11706 | D84: 40451 | E84: 0 | F84: 40451
A85: 7. | B85: банков-нерезидентов | C85: 11707 | D85: 0 | E85: 0 | F85: 0
A86: 8. | B86: прочих нерезидентов | C86: 11708 | D86: 727525 | E86: 0 | F86: 727525
B87: Итого по символам 11701 - 11708 | D87: 4201520 | E87: 0 | F87: 4201520
B88: 8. По вложениям в учтенные векселя:
A89: 1. | B89: органов федеральной власти | C89: 11801 | D89: 0 | E89: 0 | F89: 0
A90: 2. | B90: органов власти субъектов Российской Федерации и органов местного самоуправления | C90: 11802 | D90: 0 | E90: 0 | F90: 0
A91: 3. | B91: кредитных организаций | C91: 11803 | D91: 284 | E91: 0 | F91: 284
A92: 4. | B92: прочих резидентов | C92: 11804 | D92: 58876 | E92: 0 | F92: 58876
A93: 5. | B93: органов государственной власти иностранных государств | C93: 11805 | D93: 0 | E93: 0 | F93: 0
A94: 6. | B94: органов местной власти иностранных государств | C94: 11806 | D94: 0 | E94: 0 | F94: 0
A95: 7. | B95: банков-нерезидентов | C95: 11807 | D95: 0 | E95: 0 | F95: 0
A96: 8. | B96: прочих нерезидентов | C96: 11808 | D96: 0 | E96: 0 | F96: 0
B97: Итого по символам 11801 - 11808 | D97: 59160 | E97: 0 | F97: 59160
B98: Итого по разделу 1 | D98: 36319899 | E98: 929299 | F98: 37249198
B99: Раздел 2. Комиссионные доходы
B100: 1. По предоставленным кредитам и кредитам, права требования по которым приобретены:
A101: 1. | B101: Минфину России | C101: 12101 | D101: 0 | E101: 0 | F101: 0
A102: 2. | B102: финансовым органам субъектов Российской Федерации и органов местного самоуправления | C102: 12102 | D102: 0 | E102: 0 | F102: 0
A103: 3. | B103: государственным внебюджетным фондам Российской Федерации | C103: 12103 | D103: 0 | E103: 0 | F103: 0
A104: 4. | B104: внебюджетным фондам субъектов Российской Федерации и органов местного самоуправления | C104: 12104 | D104: 0 | E104: 0 | F104: 0
A105: 5. | B105: финансовым организациям, находящимся в федеральной собственности | C105: 12105 | D105: 0 | E105: 0 | F105: 0
A106: 6. | B106: коммерческим организациям, находящимся в федеральной собственности | C106: 12106 | D106: 0 | E106: 0 | F106: 0
A107: 7. | B107: некоммерческим организациям, находящимся в федеральной собственности | C107: 12107 | D107: 0 | E107: 0 | F107: 0
A108: 8. | B108: финансовым организациям, находящимся в государственной (кроме федеральной) собственности | C108: 12108 | D108: 0 | E108: 0 | F108: 0
A109: 9. | B109: коммерческим организациям, находящимся в государственной (кроме федеральной) собственности | C109: 12109 | D109: 0 | E109: 0 | F109: 0
A110: 10. | B110: некоммерческим организациям, находящимся в государственной (кроме федеральной) собственности | C110: 12110 | D110: 0 | E110: 0 | F110: 0
A111: 11. | B111: негосударственным финансовым организациям | C111: 12111 | D111: 0 | E111: 0 | F111: 0
A112: 12. | B112: негосударственным коммерческим организациям | C112: 12112 | D112: 1573 | E112: 0 | F112: 1573
... A120: 20. | B120: иностранным государствам | C120: 12120 | D120: 0 | E120: 0 | F120: 0
B121: Итого по символам 12101 - 12120 | D121: 1767 | E121: 36151 | F121: 37918
...

Sheet Ф_102_2018
A1: Номер п/п | B1: Наименование статей | C1: Символы | D1: Рубли | E1: Ин.валюта | F1: ВСЕГО
B2: Часть 1. Процентные доходы, доходы от корректировок и от восстановления (уменьшения) резервов на возможные потери
B3: Раздел 1. Процентные доходы
B4: 1. По предоставленным кредитам и кредитам, права требования по которым приобретены:
A5: 1. | B5: Минфину России | C5: 11101 | D5: 0 | E5: 0 | F5: 0
A6: 2. | B6: финансовым органам субъектов Российской Федерации и органов местного самоуправления | C6: 11102 | D6: 0 | E6: 0 | F6: 0
A7: 3. | B7: государственным внебюджетным фондам Российской Федерации | C7: 11103 | D7: 0 | E7: 0 | F7: 0
A8: 4. | B8: внебюджетным фондам субъектов Российской Федерации и органов местного самоуправления | C8: 11104 | D8: 0 | E8: 0 | F8: 0
A9: 5. | B9: финансовым организациям, находящимся в федеральной собственности | C9: 11105 | D9: 75608 | E9: 0 | F9: 75608
A10: 6. | B10: коммерческим организациям, находящимся в федеральной собственности | C10: 11106 | D10: 0 | E10: 0 | F10: 0
A11: 7. | B11: некоммерческим организациям, находящимся в федеральной собственности | C11: 11107 | D11: 0 | E11: 0 | F11: 0
A12: 8. | B12: финансовым организациям, находящимся в государственной (кроме федеральной) собственности | C12: 11108 | D12: 0 | E12: 0 | F12: 0
A13: 9. | B13: коммерческим организациям, находящимся в государственной (кроме федеральной) собственности | C13: 11109 | D13: 8179 | E13: 0 | F13: 8179
A14: 10. | B14: некоммерческим организациям, находящимся в государственной (кроме федеральной) собственности | C14: 11110 | D14: 542172 | E14: 0 | F14: 542172
A15: 11. | B15: негосударственным финансовым организациям | C15: 11111 | D15: 965109 | E15: 27696 | F15: 992805
A16: 12. | B16: негосударственным коммерческим организациям | C16: 11112 | D16: 9017855 | E16: 130545 | F16: 9148400
... A24: 20. | B24: иностранным государствам | C24: 11120 | D24: 0 | E24: 0 | F24: 0
B25: Итого по символам 11101 - 11120 | D25: 20020535 | E25: 185959 | F25: 20206494
B26: 2. По прочим размещенным средствам, в том числе по прочим приобретенным правам требования:
A27: 1. | B27: в Минфине России | C27: 11201 | D27: 0 | E27: 0 | F27: 0
A28: 2. | B28: в финансовых органах субъектов Российской Федерации и органов местного самоуправления | C28: 11202 | D28: 0 | E28: 0 | F28: 0
A29: 3. | B29: в государственных внебюджетных фондах Российской Федерации | C29: 11203 | D29: 0 | E29: 0 | F29: 0
A30: 4. | B30: во внебюджетных фондах субъектов Российской Федерации и органов местного самоуправления | C30: 11204 | D30: 0 | E30: 0 | F30: 0
A31: 5. | B31: в финансовых организациях, находящихся в федеральной собственности | C31: 11205 | D31: 0 | E31: 0 | F31: 0
A32: 6. | B32: в коммерческих организациях, находящихся в федеральной собственности | C32: 11206 | D32: 0 | E32: 0 | F32: 0
A33: 7. | B33: в некоммерческих организациях, находящихся в федеральной собственности | C33: 11207 | D33: 0 | E33: 0 | F33: 0
A34: 8. | B34: в финансовых организациях, находящихся в государственной (кроме федеральной) собственности | C34: 11208 | D34: 0 | E34: 0 | F34: 0
A35: 9. | B35: в коммерческих организациях, находящихся в государственной (кроме федеральной) собственности | C35: 11209 | D35: 0 | E35: 0 | F35: 0
A36: 10. | B36: в некоммерческих организациях, находящихся в государственной (кроме федеральной) собственности | C36: 11210 | D36: 0 | E36: 0 | F36: 0
A37: 11. | B37: в негосударственных финансовых организациях | C37: 11211 | D37: 69025 | E37: 0 | F37: 69025
A38: 12. | B38: в негосударственных коммерческих организациях | C38: 11212 | D38: 218153 | E38: 0 | F38: 218153
... A46: 20. | B46: физическим лицам - нерезидентам | C46: 11220 | D46: 0 | E46: 0 | F46: 0
B47: Итого по символам 11201 - 11220 | D47: 1781816 | E47: 153695 | F47: 1935511
B48: 3. По денежным средствам на счетах:
A49: 1. | B49: в Банке России | C49: 11301 | D49: 2607824 | E49: 0 | F49: 2607824
A50: 2. | B50: в кредитных организациях | C50: 11302 | D50: 5 | E50: 111 | F50: 116
A51: 3. | B51: в банках-нерезидентах | C51: 11303 | D51: 0 | E51: 2630 | F51: 2630
B52: Итого по символам 11301 - 11303 | D52: 2607829 | E52: 2741 | F52: 2610570
B53: 4. По депозитам размещенным:
A54: 1. | B54: в Банке России | C54: 11401 | D54: 0 | E54: 0 | F54: 0
A55: 2. | B55: в кредитных организациях | C55: 11402 | D55: 0 | E55: 0 | F55: 0
A56: 3. | B56: в банках-нерезидентах | C56: 11403 | D56: 0 | E56: 5474 | F56: 5474
B57: Итого по символам 11401 - 11403 | D57: 0 | E57: 5474 | F57: 5474
B58: 5. По вложениям в долговые ценные бумаги, оцениваемые по справедливой стоимости через прибыль или убыток (кроме векселей):
A59: 1. | B59: Российской Федерации | C59: 11501 | D59: 0 | E59: 0 | F59: 0
A60: 2. | B60: субъектов Российской Федерации и органов местного самоуправления | C60: 11502 | D60: 0 | E60: 0 | F60: 0
A61: 3. | B61: Банка России | C61: 11503 | D61: 0 | E61: 0 | F61: 0
A62: 4. | B62: кредитных организаций | C62: 11504 | D62: 0 | E62: 0 | F62: 0
A63: 5. | B63: прочих резидентов | C63: 11505 | D63: 0 | E63: 0 | F63: 0
A64: 6. | B64: иностранных государств | C64: 11506 | D64: 0 | E64: 0 | F64: 0
A65: 7. | B65: банков-нерезидентов | C65: 11507 | D65: 0 | E65: 0 | F65: 0
A66: 8. | B66: прочих нерезидентов | C66: 11508 | D66: 0 | E66: 0 | F66: 0
B67: Итого по символам 11501 - 11508 | D67: 0 | E67: 0 | F67: 0
B68: 6. По вложениям в долговые ценные бумаги, имеющиеся в наличии для продажи (кроме векселей):
A69: 1. | B69: Российской Федерации | C69: 11601 | D69: 1324768 | E69: 0 | F69: 1324768
A70: 2. | B70: субъектов Российской Федерации и органов местного самоуправления | C70: 11602 | D70: 57716 | E70: 0 | F70: 57716
A71: 3. | B71: Банка России | C71: 11603 | D71: 3418 | E71: 0 | F71: 3418
A72: 4. | B72: кредитных организаций | C72: 11604 | D72: 86241 | E72: 0 | F72: 86241
A73: 5. | B73: прочих резидентов | C73: 11605 | D73: 938484 | E73: 0 | F73: 938484
A74: 6. | B74: иностранных государств | C74: 11606 | D74: 0 | E74: 0 | F74: 0
A75: 7. | B75: банков-нерезидентов | C75: 11607 | D75: 0 | E75: 0 | F75: 0
A76: 8. | B76: прочих нерезидентов | C76: 11608 | D76: 3822596 | E76: 0 | F76: 3822596
B77: Итого по символам 11601 - 11608 | D77: 6233223 | E77: 0 | F77: 6233223
B78: 7. По вложениям в долговые ценные бумаги, удерживаемые до погашения (кроме векселей):
A79: 1. | B79: Российской Федерации | C79: 11701 | D79: 588080 | E79: 0 | F79: 588080
A80: 2. | B80: субъектов Российской Федерации и органов местного самоуправления | C80: 11702 | D80: 33820 | E80: 0 | F80: 33820
A81: 3. | B81: Банка России | C81: 11703 | D81: 0 | E81: 0 | F81: 0
A82: 4. | B82: кредитных организаций | C82: 11704 | D82: 128051 | E82: 0 | F82: 128051
A83: 5. | B83: прочих резидентов | C83: 11705 | D83: 321947 | E83: 0 | F83: 321947
A84: 6. | B84: иностранных государств | C84: 11706 | D84: 0 | E84: 0 | F84: 0
A85: 7. | B85: банков-нерезидентов | C85: 11707 | D85: 0 | E85: 0 | F85: 0
A86: 8. | B86: прочих нерезидентов | C86: 11708 | D86: 277962 | E86: 0 | F86: 277962
B87: Итого по символам 11701 - 11708 | D87: 1349860 | E87: 0 | F87: 1349860
B88: 8. По вложениям в учтенные векселя:
A89: 1. | B89: органов федеральной власти | C89: 11801 | D89: 0 | E89: 0 | F89: 0
A90: 2. | B90: органов власти субъектов Российской Федерации и органов местного самоуправления | C90: 11802 | D90: 0 | E90: 0 | F90: 0
A91: 3. | B91: кредитных организаций | C91: 11803 | D91: 508 | E91: 0 | F91: 508
A92: 4. | B92: прочих резидентов | C92: 11804 | D92: 49917 | E92: 0 | F92: 49917
A93: 5. | B93: органов государственной власти иностранных государств | C93: 11805 | D93: 0 | E93: 0 | F93: 0
A94: 6. | B94: органов местной власти иностранных государств | C94: 11806 | D94: 0 | E94: 0 | F94: 0
A95: 7. | B95: банков-нерезидентов | C95: 11807 | D95: 0 | E95: 0 | F95: 0
A96: 8. | B96: прочих нерезидентов | C96: 11808 | D96: 0 | E96: 0 | F96: 0
B97: Итого по символам 11801 - 11808 | D97: 50425 | E97: 0 | F97: 50425
B98: Итого по разделу 1 | D98: 32043688 | E98: 347869 | F98: 32391557
B99: Раздел 2. Комиссионные доходы
B100: 1. По предоставленным кредитам и кредитам, права требования по которым приобретены:
A101: 1. | B101: Минфину России | C101: 12101 | D101: 0 | E101: 0 | F101: 0
A102: 2. | B102: финансовым органам субъектов Российской Федерации и органов местного самоуправления | C102: 12102 | D102: 0 | E102: 0 | F102: 0
A103: 3. | B103: государственным внебюджетным фондам Российской Федерации | C103: 12103 | D103: 0 | E103: 0 | F103: 0
A104: 4. | B104: внебюджетным фондам субъектов Российской Федерации и органов местного самоуправления | C104: 12104 | D104: 0 | E104: 0 | F104: 0
A105: 5. | B105: финансовым организациям, находящимся в федеральной собственности | C105: 12105 | D105: 0 | E105: 0 | F105: 0
A106: 6. | B106: коммерческим организациям, находящимся в федеральной собственности | C106: 12106 | D106: 0 | E106: 0 | F106: 0
A107: 7. | B107: некоммерческим организациям, находящимся в федеральной собственности | C107: 12107 | D107: 0 | E107: 0 | F107: 0
A108: 8. | B108: финансовым организациям, находящимся в государственной (кроме федеральной) собственности | C108: 12108 | D108: 0 | E108: 0 | F108: 0
A109: 9. | B109: коммерческим организациям, находящимся в государственной (кроме федеральной) собственности | C109: 12109 | D109: 0 | E109: 0 | F109: 0
A110: 10. | B110: некоммерческим организациям, находящимся в государственной (кроме федеральной) собственности | C110: 12110 | D110: 0 | E110: 0 | F110: 0
A111: 11. | B111: негосударственным финансовым организациям | C111: 12111 | D111: 0 | E111: 0 | F111: 0
A112: 12. | B112: негосударственным коммерческим организациям | C112: 12112 | D112: 325 | E112: 0 | F112: 325
... A120: 20. | B120: иностранным государствам | C120: 12120 | D120: 0 | E120: 0 | F120: 0
B121: Итого по символам 12101 - 12120 | D121: 552 | E121: 61936 | F121: 62488
...

Sheet Ф_102_2017
A1: Номер п/п | B1: Наименование статей | C1: Символы | D1: Рубли | E1: Ин.валюта | F1: ВСЕГО
B2: Часть 1. Процентные доходы, доходы от корректировок и от восстановления (уменьшения) резервов на возможные потери
B3: Раздел 1. Процентные доходы
B4: 1. По предоставленным кредитам и кредитам, права требования по которым приобретены:
A5: 1. | B5: Минфину России | C5: 11101 | D5: 0 | E5: 0 | F5: 0
A6: 2. | B6: финансовым органам субъектов Российской Федерации и органов местного самоуправления | C6: 11102 | D6: 0 | E6: 0 | F6: 0
A7: 3. | B7: государственным внебюджетным фондам Российской Федерации | C7: 11103 | D7: 0 | E7: 0 | F7: 0
A8: 4. | B8: внебюджетным фондам субъектов Российской Федерации и органов местного самоуправления | C8: 11104 | D8: 0 | E8: 0 | F8: 0
A9: 5. | B9: финансовым организациям, находящимся в федеральной собственности | C9: 11105 | D9: 0 | E9: 0 | F9: 0
A10: 6. | B10: коммерческим организациям, находящимся в федеральной собственности | C10: 11106 | D10: 0 | E10: 0 | F10: 0
A11: 7. | B11: некоммерческим организациям, находящимся в федеральной собственности | C11: 11107 | D11: 48 | E11: 0 | F11: 48
A12: 8. | B12: финансовым организациям, находящимся в государственной (кроме федеральной) собственности | C12: 11108 | D12: 68492 | E12: 0 | F12: 68492
A13: 9. | B13: коммерческим организациям, находящимся в государственной (кроме федеральной) собственности | C13: 11109 | D13: 4388 | E13: 0 | F13: 4388
A14: 10. | B14: некоммерческим организациям, находящимся в государственной (кроме федеральной) собственности | C14: 11110 | D14: 900000 | E14: 0 | F14: 900000
A15: 11. | B15: негосударственным финансовым организациям | C15: 11111 | D15: 1035271 | E15: 34675 | F15: 1069946
A16: 12. | B16: негосударственным коммерческим организациям | C16: 11112 | D16: 12067177 | E16: 45307 | F16: 12112484
... A24: 20. | B24: иностранным государствам | C24: 11120 | D24: 0 | E24: 0 | F24: 0
B25: Итого по символам 11101 - 11120 | D25: 23159466 | E25: 82863 | F25: 23242329
B26: 2. По прочим размещенным средствам, в том числе по прочим приобретенным правам
A27: 1. | B27: в Минфине России | C27: 11201 | D27: 0 | E27: 0 | F27: 0
A28: 2. | B28: в финансовых органах субъектов Российской Федерации и органов местного самоуправления | C28: 11202 | D28: 0 | E28: 0 | F28: 0
A29: 3. | B29: в государственных внебюджетных фондах Российской Федерации | C29: 11203 | D29: 0 | E29: 0 | F29: 0
A30: 4. | B30: во внебюджетных фондах субъектов Российской Федерации и органов местного самоуправления | C30: 11204 | D30: 0 | E30: 0 | F30: 0
A31: 5. | B31: в финансовых организациях, находящихся в федеральной собственности | C31: 11205 | D31: 0 | E31: 0 | F31: 0
A32: 6. | B32: в коммерческих организациях, находящихся в федеральной собственности | C32: 11206 | D32: 0 | E32: 0 | F32: 0
A33: 7. | B33: в некоммерческих организациях, находящихся в федеральной собственности | C33: 11207 | D33: 0 | E33: 0 | F33: 0
A34: 8. | B34: в финансовых организациях, находящихся в государственной (кроме федеральной) собственности | C34: 11208 | D34: 0 | E34: 0 | F34: 0
A35: 9. | B35: в коммерческих организациях, находящихся в государственной (кроме федеральной) собственности | C35: 11209 | D35: 0 | E35: 0 | F35: 0
A36: 10. | B36: в некоммерческих организациях, находящихся в государственной (кроме федеральной) собственности | C36: 11210 | D36: 0 | E36: 0 | F36: 0
A37: 11. | B37: в негосударственных финансовых организациях | C37: 11211 | D37: 17 | E37: 0 | F37: 17
A38: 12. | B38: в негосударственных коммерческих организациях | C38: 11212 | D38: 121218 | E38: 0 | F38: 121218
... A46: 20. | B46: физическим лицам - нерезидентам | C46: 11220 | D46: 0 | E46: 0 | F46: 0
B47: Итого по символам 11201 - 11220 | D47: 1271542 | E47: 116533 | F47: 1388075
B48: 3. По денежным средствам на счетах:
A49: 1. | B49: в Банке России | C49: 11301 | D49: 507630 | E49: 0 | F49: 507630
A50: 2. | B50: в кредитных организациях | C50: 11302 | D50: 121 | E50: 74 | F50: 195
A51: 3. | B51: в банках-нерезидентах | C51: 11303 | D51: 0 | E51: 2103 | F51: 2103
B52: Итого по символам 11301 - 11303 | D52: 507751 | E52: 2177 | F52: 509928
B53: 4. По депозитам размещенным:
A54: 1. | B54: в Банке России | C54: 11401 | D54: 0 | E54: 0 | F54: 0
A55: 2. | B55: в кредитных организациях | C55: 11402 | D55: 0 | E55: 0 | F55: 0
A56: 3. | B56: в банках-нерезидентах | C56: 11403 | D56: 0 | E56: 7 | F56: 7
B57: Итого по символам 11401 - 11403 | D57: 0 | E57: 7 | F57: 7
B58: 5. По вложениям в долговые ценные бумаги, оцениваемые по справедливой стоимости через прибыль или убыток (кроме векселей):
A59: 1. | B59: Российской Федерации | C59: 11501 | D59: 0 | E59: 0 | F59: 0
A60: 2. | B60: субъектов Российской Федерации и органов местного самоуправления | C60: 11502 | D60: 0 | E60: 0 | F60: 0
A61: 3. | B61: Банка России | C61: 11503 | D61: 0 | E61: 0 | F61: 0
A62: 4. | B62: кредитных организаций | C62: 11504 | D62: 0 | E62: 0 | F62: 0
A63: 5. | B63: прочих резидентов | C63: 11505 | D63: 0 | E63: 0 | F63: 0
A64: 6. | B64: иностранных государств | C64: 11506 | D64: 0 | E64: 0 | F64: 0
A65: 7. | B65: банков-нерезидентов | C65: 11507 | D65: 0 | E65: 0 | F65: 0
A66: 8. | B66: прочих нерезидентов | C66: 11508 | D66: 0 | E66: 0 | F66: 0
B67: Итого по символам 11501 - 11508 | D67: 0 | E67: 0 | F67: 0
B68: 6. По вложениям в долговые ценные бумаги, имеющиеся в наличии для продажи (кроме векселей):
A69: 1. | B69: Российской Федерации | C69: 11601 | D69: 667264 | E69: 0 | F69: 667264
A70: 2. | B70: субъектов Российской Федерации и органов местного самоуправления | C70: 11602 | D70: 12534 | E70: 0 | F70: 12534
A71: 3. | B71: Банка России | C71: 11603 | D71: 11882 | E71: 0 | F71: 11882
A72: 4. | B72: кредитных организаций | C72: 11604 | D72: 132703 | E72: 0 | F72: 132703
A73: 5. | B73: прочих резидентов | C73: 11605 | D73: 794117 | E73: 0 | F73: 794117
A74: 6. | B74: иностранных государств | C74: 11606 | D74: 0 | E74: 0 | F74: 0
A75: 7. | B75: банков-нерезидентов | C75: 11607 | D75: 0 | E75: 0 | F75: 0
A76: 8. | B76: прочих нерезидентов | C76: 11608 | D76: 3971682 | E76: 0 | F76: 3971682
B77: Итого по символам 11601 - 11608 | D77: 5590182 | E77: 0 | F77: 5590182
B78: 7. По вложениям в долговые ценные бумаги, удерживаемые до погашения (кроме векселей):
A79: 1. | B79: Российской Федерации | C79: 11701 | D79: 1255796 | E79: 0 | F79: 1255796
A80: 2. | B80: субъектов Российской Федерации и органов местного самоуправления | C80: 11702 | D80: 0 | E80: 0 | F80: 0
A81: 3. | B81: Банка России | C81: 11703 | D81: 0 | E81: 0 | F81: 0
A82: 4. | B82: кредитных организаций | C82: 11704 | D82: 0 | E82: 0 | F82: 0
A83: 5. | B83: прочих резидентов | C83: 11705 | D83: 205011 | E83: 0 | F83: 205011
A84: 6. | B84: иностранных государств | C84: 11706 | D84: 0 | E84: 0 | F84: 0
A85: 7. | B85: банков-нерезидентов | C85: 11707 | D85: 0 | E85: 0 | F85: 0
A86: 8. | B86: прочих нерезидентов | C86: 11708 | D86: 23068 | E86: 0 | F86: 23068
B87: Итого по символам 11701 - 11708 | D87: 1483875 | E87: 0 | F87: 1483875
B88: 8. По вложениям в учтенные векселя:
A89: 1. | B89: органов федеральной власти | C89: 11801 | D89: 0 | E89: 0 | F89: 0
A90: 2. | B90: органов власти субъектов Российской Федерации и органов местного самоуправления | C90: 11802 | D90: 0 | E90: 0 | F90: 0
A91: 3. | B91: кредитных организаций | C91: 11803 | D91: 48 | E91: 0 | F91: 48
A92: 4. | B92: прочих резидентов | C92: 11804 | D92: 410832 | E92: 0 | F92: 410832
A93: 5. | B93: органов государственной власти иностранных государств | C93: 11805 | D93: 0 | E93: 0 | F93: 0
A94: 6. | B94: органов местной власти иностранных государств | C94: 11806 | D94: 0 | E94: 0 | F94: 0
A95: 7. | B95: банков-нерезидентов | C95: 11807 | D95: 0 | E95: 0 | F95: 0
A96: 8. | B96: прочих нерезидентов | C96: 11808 | D96: 0 | E96: 0 | F96: 0
B97: Итого по символам 11801 - 11808 | D97: 410880 | E97: 0 | F97: 410880
B98: Итого по разделу 1 | D98: 32423696 | E98: 201580 | F98: 32625276
B99: Раздел 2. Комиссионные доходы
B100: 1. По предоставленным кредитам и кредитам, права требования по которым приобретены:
A101: 1. | B101: Минфину России | C101: 12101 | D101: 0 | E101: 0 | F101: 0
A102: 2. | B102: финансовым органам субъектов Российской Федерации и органов местного самоуправления | C102: 12102 | D102: 0 | E102: 0 | F102: 0
A103: 3. | B103: государственным внебюджетным фондам Российской Федерации | C103: 12103 | D103: 0 | E103: 0 | F103: 0
A104: 4. | B104: внебюджетным фондам субъектов Российской Федерации и органов местного самоуправления | C104: 12104 | D104: 0 | E104: 0 | F104: 0
A105: 5. | B105: финансовым организациям, находящимся в федеральной собственности | C105: 12105 | D105: 0 | E105: 0 | F105: 0
A106: 6. | B106: коммерческим организациям, находящимся в федеральной собственности | C106: 12106 | D106: 0 | E106: 0 | F106: 0
A107: 7. | B107: некоммерческим организациям, находящимся в федеральной собственности | C107: 12107 | D107: 0 | E107: 0 | F107: 0
A108: 8. | B108: финансовым организациям, находящимся в государственной (кроме федеральной) собственности | C108: 12108 | D108: 0 | E108: 0 | F108: 0
A109: 9. | B109: коммерческим организациям, находящимся в государственной (кроме федеральной) собственности | C109: 12109 | D109: 0 | E109: 0 | F109: 0
A110: 10. | B110: некоммерческим организациям, находящимся в государственной (кроме федеральной) собственности | C110: 12110 | D110: 0 | E110: 0 | F110: 0
A111: 11. | B111: негосударственным финансовым организациям | C111: 12111 | D111: 0 | E111: 0 | F111: 0
A112: 12. | B112: негосударственным коммерческим организациям | C112: 12112 | D112: 464 | E112: 0 | F112: 464
... A120: 20. | B120: иностранным государствам | C120: 12120 | D120: 0 | E120: 0 | F120: 0
B121: Итого по символам 12101 - 12120 | D121: 826 | E121: 20710 | F121: 21536
...

Sheet Ф_102_2016
A1: Номер п/п | B1: Наименование статей | C1: Символы | D1: Рубли | E1: Ин.валюта | F1: ВСЕГО
B2: Часть 1. Процентные доходы, доходы от корректировок и от восстановления (уменьшения) резервов на возможные потери
B3: Раздел 1. Процентные доходы
B4: 1. По предоставленным кредитам и кредитам, права требования по которым приобретены:
A5: 1. | B5: Минфину России | C5: 11101 | D5: 0 | E5: 0 | F5: 0
A6: 2. | B6: финансовым органам субъектов Российской Федерации и органов местного самоуправления | C6: 11102 | D6: 0 | E6: 0 | F6: 0
A7: 3. | B7: государственным внебюджетным фондам Российской Федерации | C7: 11103 | D7: 0 | E7: 0 | F7: 0
A8: 4. | B8: внебюджетным фондам субъектов Российской Федерации и органов местного самоуправления | C8: 11104 | D8: 0 | E8: 0 | F8: 0
A9: 5. | B9: финансовым организациям, находящимся в федеральной собственности | C9: 11105 | D9: 0 | E9: 0 | F9: 0
A10: 6. | B10: коммерческим организациям, находящимся в федеральной собственности | C10: 11106 | D10: 0 | E10: 0 | F10: 0
A11: 7. | B11: некоммерческим организациям, находящимся в федеральной собственности | C11: 11107 | D11: 660 | E11: 0 | F11: 660
A12: 8. | B12: финансовым организациям, находящимся в государственной (кроме федеральной) собственности | C12: 11108 | D12: 0 | E12: 0 | F12: 0
A13: 9. | B13: коммерческим организациям, находящимся в государственной (кроме федеральной) собственности | C13: 11109 | D13: 8358 | E13: 0 | F13: 8358
A14: 10. | B14: некоммерческим организациям, находящимся в государственной (кроме федеральной) собственности | C14: 11110 | D14: 1107650 | E14: 0 | F14: 1107650
A15: 11. | B15: негосударственным финансовым организациям | C15: 11111 | D15: 1523303 | E15: 3617 | F15: 1526920
A16: 12. | B16: негосударственным коммерческим организациям | C16: 11112 | D16: 18211937 | E16: 1093684 | F16: 19305621
... A24: 20. | B24: иностранным государствам | C24: 11120 | D24: 0 | E24: 0 | F24: 0
B25: Итого по символам 11101 - 11120 | D25: 28741417 | E25: 1112886 | F25: 29854303
B26: 2. По прочим размещенным средствам, в том числе по прочим приобретенным правам
A27: 1. | B27: в Минфине России | C27: 11201 | D27: 0 | E27: 0 | F27: 0
A28: 2. | B28: в финансовых органах субъектов Российской Федерации и органов местного самоуправления | C28: 11202 | D28: 0 | E28: 0 | F28: 0
A29: 3. | B29: в государственных внебюджетных фондах Российской Федерации | C29: 11203 | D29: 0 | E29: 0 | F29: 0
A30: 4. | B30: во внебюджетных фондах субъектов Российской Федерации и органов местного самоуправления | C30: 11204 | D30: 0 | E30: 0 | F30: 0
A31: 5. | B31: в финансовых организациях, находящихся в федеральной собственности | C31: 11205 | D31: 0 | E31: 0 | F31: 0
A32: 6. | B32: в коммерческих организациях, находящихся в федеральной собственности | C32: 11206 | D32: 0 | E32: 0 | F32: 0
A33: 7. | B33: в некоммерческих организациях, находящихся в федеральной собственности | C33: 11207 | D33: 0 | E33: 0 | F33: 0
A34: 8. | B34: в финансовых организациях, находящихся в государственной (кроме федеральной) собственности | C34: 11208 | D34: 0 | E34: 0 | F34: 0
A35: 9. | B35: в коммерческих организациях, находящихся в государственной (кроме федеральной) собственности | C35: 11209 | D35: 0 | E35: 0 | F35: 0
A36: 10. | B36: в некоммерческих организациях, находящихся в государственной (кроме федеральной) собственности | C36: 11210 | D36: 72302 | E36: 0 | F36: 72302
A37: 11. | B37: в негосударственных финансовых организациях | C37: 11211 | D37: 61492 | E37: 2181 | F37: 63673
A38: 12. | B38: в негосударственных коммерческих организациях | C38: 11212 | D38: 752699 | E38: 375875 | F38: 1128574
... A46: 20. | B46: физическим лицам - нерезидентам | C46: 11220 | D46: 0 | E46: 0 | F46: 0
B47: Итого по символам 11201 - 11220 | D47: 1760029 | E47: 722849 | F47: 2482878
B48: 3. По денежным средствам на счетах:
A49: 1. | B49: в Банке России | C49: 11301 | D49: 1133 | E49: 0 | F49: 1133
A50: 2. | B50: в кредитных организациях | C50: 11302 | D50: 422 | E50: 217 | F50: 639
A51: 3. | B51: в банках-нерезидентах | C51: 11303 | D51: 0 | E51: 4532 | F51: 4532
B52: Итого по символам 11301 - 11303 | D52: 1555 | E52: 4749 | F52: 6304
B53: 4. По депозитам размещенным:
A54: 1. | B54: в Банке России | C54: 11401 | D54: 0 | E54: 0 | F54: 0
A55: 2. | B55: в кредитных организациях | C55: 11402 | D55: 0 | E55: 0 | F55: 0
A56: 3. | B56: в банках-нерезидентах | C56: 11403 | D56: 0 | E56: 4 | F56: 4
B57: Итого по символам 11401 - 11403 | D57: 0 | E57: 4 | F57: 4
B58: 5. По вложениям в долговые ценные бумаги, оцениваемые по справедливой стоимости через прибыль или убыток (кроме векселей):
A59: 1. | B59: Российской Федерации | C59: 11501 | D59: 0 | E59: 0 | F59: 0
A60: 2. | B60: субъектов Российской Федерации и органов местного самоуправления | C60: 11502 | D60: 0 | E60: 0 | F60: 0
A61: 3. | B61: Банка России | C61: 11503 | D61: 0 | E61: 0 | F61: 0
A62: 4. | B62: кредитных организаций | C62: 11504 | D62: 0 | E62: 0 | F62: 0
A63: 5. | B63: прочих резидентов | C63: 11505 | D63: 0 | E63: 0 | F63: 0
A64: 6. | B64: иностранных государств | C64: 11506 | D64: 0 | E64: 0 | F64: 0
A65: 7. | B65: банков-нерезидентов | C65: 11507 | D65: 0 | E65: 0 | F65: 0
A66: 8. | B66: прочих нерезидентов | C66: 11508 | D66: 0 | E66: 0 | F66: 0
B67: Итого по символам 11501 - 11508 | D67: 0 | E67: 0 | F67: 0
B68: 6. По вложениям в долговые ценные бумаги, имеющиеся в наличии для продажи (кроме векселей):
A69: 1. | B69: Российской Федерации | C69: 11601 | D69: 400010 | E69: 0 | F69: 400010
A70: 2. | B70: субъектов Российской Федерации и органов местного самоуправления | C70: 11602 | D70: 31834 | E70: 0 | F70: 31834
A71: 3. | B71: Банка России | C71: 11603 | D71: 0 | E71: 0 | F71: 0
A72: 4. | B72: кредитных организаций | C72: 11604 | D72: 286317 | E72: 0 | F72: 286317
A73: 5. | B73: прочих резидентов | C73: 11605 | D73: 1558995 | E73: 0 | F73: 1558995
A74: 6. | B74: иностранных государств | C74: 11606 | D74: 0 | E74: 0 | F74: 0
A75: 7. | B75: банков-нерезидентов | C75: 11607 | D75: 0 | E75: 0 | F75: 0
A76: 8. | B76: прочих нерезидентов | C76: 11608 | D76: 1923192 | E76: 0 | F76: 1923192
B77: Итого по символам 11601 - 11608 | D77: 4200348 | E77: 0 | F77: 4200348
B78: 7. По вложениям в долговые ценные бумаги, удерживаемые до погашения (кроме векселей):
A79: 1. | B79: Российской Федерации | C79: 11701 | D79: 1892312 | E79: 0 | F79: 1892312
A80: 2. | B80: субъектов Российской Федерации и органов местного самоуправления | C80: 11702 | D80: 0 | E80: 0 | F80: 0
A81: 3. | B81: Банка России | C81: 11703 | D81: 0 | E81: 0 | F81: 0
A82: 4. | B82: кредитных организаций | C82: 11704 | D82: 0 | E82: 0 | F82: 0
A83: 5. | B83: прочих резидентов | C83: 11705 | D83: 261530 | E83: 0 | F83: 261530
A84: 6. | B84: иностранных государств | C84: 11706 | D84: 0 | E84: 0 | F84: 0
A85: 7. | B85: банков-нерезидентов | C85: 11707 | D85: 0 | E85: 0 | F85: 0
A86: 8. | B86: прочих нерезидентов | C86: 11708 | D86: 35232 | E86: 0 | F86: 35232
B87: Итого по символам 11701 - 11708 | D87: 2189074 | E87: 0 | F87: 2189074
B88: 8. По вложениям в учтенные векселя:
A89: 1. | B89: органов федеральной власти | C89: 11801 | D89: 0 | E89: 0 | F89: 0
A90: 2. | B90: органов власти субъектов Российской Федерации и органов местного самоуправления | C90: 11802 | D90: 0 | E90: 0 | F90: 0
A91: 3. | B91: кредитных организаций | C91: 11803 | D91: 0 | E91: 0 | F91: 0
A92: 4. | B92: прочих резидентов | C92: 11804 | D92: 329634 | E92: 0 | F92: 329634
A93: 5. | B93: органов государственной власти иностранных государств | C93: 11805 | D93: 0 | E93: 0 | F93: 0
A94: 6. | B94: органов местной власти иностранных государств | C94: 11806 | D94: 0 | E94: 0 | F94: 0
A95: 7. | B95: банков-нерезидентов | C95: 11807 | D95: 0 | E95: 0 | F95: 0
A96: 8. | B96: прочих нерезидентов | C96: 11808 | D96: 0 | E96: 0 | F96: 0
B97: Итого по символам 11801 - 11808 | D97: 329634 | E97: 0 | F97: 329634
B98: Итого по разделу 1 | D98: 37222057 | E98: 1840488 | F98: 39062545
B99: Раздел 2. Комиссионные доходы
B100: 1. По предоставленным кредитам и кредитам, права требования по которым приобретены:
A101: 1. | B101: Минфину России | C101: 12101 | D101: 1 | E101: 0 | F101: 1
A102: 2. | B102: финансовым органам субъектов Российской Федерации и органов местного самоуправления | C102: 12102 | D102: 0 | E102: 0 | F102: 0
A103: 3. | B103: государственным внебюджетным фондам Российской Федерации | C103: 12103 | D103: 0 | E103: 0 | F103: 0
A104: 4. | B104: внебюджетным фондам субъектов Российской Федерации и органов местного самоуправления | C104: 12104 | D104: 0 | E104: 0 | F104: 0
A105: 5. | B105: финансовым организациям, находящимся в федеральной собственности | C105: 12105 | D105: 0 | E105: 0 | F105: 0
A106: 6. | B106: коммерческим организациям, находящимся в федеральной собственности | C106: 12106 | D106: 85 | E106: 0 | F106: 85
A107: 7. | B107: некоммерческим организациям, находящимся в федеральной собственности | C107: 12107 | D107: 0 | E107: 0 | F107: 0
A108: 8. | B108: финансовым организациям, находящимся в государственной (кроме федеральной) собственности | C108: 12108 | D108: 0 | E108: 0 | F108: 0
A109: 9. | B109: коммерческим организациям, находящимся в государственной (кроме федеральной) собственности | C109: 12109 | D109: 0 | E109: 0 | F109: 0
A110: 10. | B110: некоммерческим организациям, находящимся в государственной (кроме федеральной) собственности | C110: 12110 | D110: 0 | E110: 0 | F110: 0
A111: 11. | B111: негосударственным финансовым организациям | C111: 12111 | D111: 254 | E111: 0 | F111: 254
A112: 12. | B112: негосударственным коммерческим организациям | C112: 12112 | D112: 34480 | E112: 0 | F112: 34480
... A120: 20. | B120: иностранным государствам | C120: 12120 | D120: 0 | E120: 0 | F120: 0
B121: Итого по символам 12101 - 12120 | D121: 41043 | E121: 10016 | F121: 51059
...

Sheet МСФО_ввод
D2: Наименование банка | E2: ОАО "Банк Москвы"
D3: Стандарт составления отчетности | E3: МСФО
D4: Тип отчетности | E4: Консолидированная
D6: Отчет о финансовом положении | E6: На 31.12'
D7: млрд руб. | E7: 2009 | F7: 2010 | G7: 2011 | H7: 2012 | I7: 2013 | J7: 2014 | K7: 2015
D8: Активы
D9: Денежные средства и краткосрочные активы | E9: 75.164 | F9: 71.53 | G9: 62.851 | H9: 70.22 | I9: 89.767 | J9: 79.3 | K9: 77.6
D10: Обязательные резервы в центральных банках | E10: 4.748 | F10: 5.588 | G10: 9.753 | H10: 7.006 | I10: 6.669 | J10: 7.9 | K10: 5.2
D11: Финансовые активы, предназначенные для торговли | E11: 90.441 | F11: 86.609 | G11: 33.434 | H11: 32.851 | I11: 58.606 | J11: 25.6 | K11: 14.1
D12: Финансовые активы, заложенные по договорам "репо" | E12: 4.936 | F12: 38.175 | G12: 185.247 | H12: 263.098 | I12: 273.145 | J12: 281.5 | K12: 126.7
D13: Средства в банках | E13: 50.703 | F13: 79.485 | G13: 158.825 | H13: 167.503 | I13: 162.86 | J13: 508.9 | K13: 177.2
D14: Кредиты и авансы клиентам | E14: 558.165 | F14: 505.72 | G14: 533.735 | H14: 649.994 | I14: 909.061 | J14: 1096.3 | K14: 954.4
D15: Финансовые активы, имеющиеся в наличии для продажи | E15: 15.032 | F15: 14.723 | G15: 18.258 | H15: 25.792 | I15: 28.828 | J15: 10.8 | K15: 25.8
D16: Инвестиционные ценные бумаги, удерживаемые для погашения | E16: 0.265 | F16: 0.418 | G16: 0.324 | H16: 0.132 | I16: 0.004 | J16: 0 | K16: 16
D17: Инвестиции в ассоциированные компании | E17: 3.82 | F17: 3.247 | G17: 3.121 | H17: 0.756 | I17: 1.008 | J17: 1.8 | K17: 2.4
D18: Основные средства и нематериальные активы | E18: 17.284 | F18: 15.965 | G18: 20.457 | H18: 33.881 | I18: 40.747 | J18: 66.4 | K18: 52.3
D19: Инвестиционная недвижимость | E19: 0 | F19: 3.638 | G19: 3.785 | H19: 5.076 | I19: 14.034 | J19: 19.1 | K19: 28
D20: Активы, предназначенные для продажи | E20: 0 | F20: 0 | G20: 10.33 | H20: 15.234 | I20: 24.412 | J20: 0.3 | K20: 8.4
... D23: Прочие активы | E23: 3.822 | F23: 5.842 | G23: 5.076 | H23: 9.457 | I23: 12.102 | J23: 13.2 | K23: 6.4
D24: Итого активы | E24: =SUM(E9:E23) -> 825.206 | F24: =SUM(F9:F23) -> 849.476 | G24: =SUM(G9:G23) -> 1060.002 | H24: =SUM(H9:H23) -> 1293.015 | I24: =SUM(I9:I23) -> 1628.653 | J24: =SUM(J9:J23) -> 2129.1 | K24: =SUM(K9:K23) -> 1509.2
D25: Обязательства
D26: Средства банков | E26: 137.76 | F26: 145.198 | G26: 44.001 | H26: 101.678 | I26: 205.027 | J26: 543.7 | K26: 68.9
D27: Средства, привлеченные от ЦБ РФ | E27: 73.845 | F27: 0 | G27: 159.745 | H27: 264.685 | I27: 272.445 | J27: 406.1 | K27: 211.1
D28: Финансовые обязательства, предназначенные для торговли | G28: 3.156 | H28: 2.528 | I28: 1.697 | J28: 0.3 | K28: 0
D29: Средства клиентов | E29: 428.028 | F29: 543.14 | G29: 418.688 | H29: 464.022 | I29: 615.622 | J29: 631.8 | K29: 686.9
D30: Выпущенные долговые ценные бумаги | E30: 56.862 | F30: 81.103 | G30: 73.616 | H30: 66.971 | I30: 69.963 | J30: 101.5 | K30: 52.3
D31: Средства, привлеченные от ГК "АСВ" | E31: 0 | F31: 0 | G31: 144.386 | H31: 153.426 | I31: 159.041 | J31: 67.7 | K31: 73.7
D32: Обязательства, связанные с активами, предназначенными для продажи | E32: 0 | F32: 0 | G32: 8.502 | H32: 6.06 | I32: 19.775 | J32: 0.3 | K32: 7.6
D33: Текущие налоговые обязательства | E33: 0.089 | F33: 0.039 | G33: 0.224 | H33: 0.531 | I33: 0.894 | J33: 0.9 | K33: 1
D34: Отложенные налоговые обязательства | E34: 1.631 | F34: 0.135 | G34: 0.613 | H34: 1.095 | I34: 1.093 | J34: 6.1 | K34: 1.7
D35: Прочие обязательства | E35: 6.918 | F35: 8.738 | G35: 8.377 | H35: 8.528 | I35: 30.579 | J35: 115.6 | K35: 73.8
D36: Субординированная задолженность | E36: 35.346 | F36: 34.173 | G36: 35.821 | H36: 34.514 | I36: 36.448 | J36: 67.5 | K36: 138.4
D37: Итого обязательства | E37: =SUM(E26:E36) -> 740.479 | F37: =SUM(F26:F36) -> 812.526 | G37: =SUM(G26:G36) -> 897.129 | H37: =SUM(H26:H36) -> 1104.038 | I37: =SUM(I26:I36) -> 1412.584 | J37: =SUM(J26:J36) -> 1941.5 | K37: =SUM(K26:K36) -> 1315.4
D38: Собственные средства
D39: Уставный капитал | E39: 18.313 | F39: 20.476 | G39: 29.651 | H39: 29.651 | I39: 29.651 | J39: 29.7 | K39: 29.7
D40: Эмиссионный доход | E40: 34.09 | F40: 53.624 | G40: 146.449 | H40: 146.449 | I40: 146.449 | J40: 146.4 | K40: 146.4
D41: Собственные средства, выкупленные у акционеров | H41: 0 | I41: -0.0037 | J41: 0 | K41: 0
D42: Фонд переоценки финансовых активов, имеющихся в наличии для продажи | E42: 0.064 | F42: 0.105 | G42: 0.142 | H42: 1.615 | I42: 1.048 | J42: -4.8 | K42: -0.9
D43: Фонд переоценки основных средств | E43: 3.882 | F43: 3.882 | G43: 3.882 | H43: 6.238 | I43: 6.08 | J43: 5.8 | K43: 6.7
D44: Фонд накопленных курсовых разниц | E44: -0.039 | F44: 0.013 | G44: -0.528 | H44: -0.011 | I44: -0.022 | J44: -0.1 | K44: 0.1
D45: Нераспределенная прибыль | E45: 28.172 | F45: -41.577 | G45: -16.951 | H45: 4.88 | I45: 32.161 | J45: 9.6 | K45: 10.8
D46: Собственные средства, принадлежащие акционерам | E46: =SUM(E39:E45) -> 84.482 | F46: =SUM(F39:F45) -> 36.523 | G46: =SUM(G39:G45) -> 162.645 | H46: =SUM(H39:H45) -> 188.822 | I46: =SUM(I39:I45) -> 215.3633 | J46: =SUM(J39:J45) -> 186.6 | K46: =SUM(K39:K45) -> 192.8
D47: Неконтрольные доли участия | E47: 0.245 | F47: 0.429 | G47: 0.243 | H47: 0.156 | I47: 0.708 | J47: 1 | K47: 1
D48: Итого собственные средства | E48: =SUM(E46:E47) -> 84.727 | F48: =SUM(F46:F47) -> 36.952 | G48: =SUM(G46:G47) -> 162.888 | H48: =SUM(H46:H47) -> 188.978 | I48: =SUM(I46:I47) -> 216.0713 | J48: =SUM(J46:J47) -> 187.6 | K48: =SUM(K46:K47) -> 193.8
D49: Итого обязательства и собственные средства | E49: =E37+E48 -> 825.206 | F49: =F37+F48 -> 849.478 | G49: =G37+G48 -> 1060.017 | H49: =H37+H48 -> 1293.016 | I49: =I37+I48 -> 1628.6553 | J49: =J37+J48 -> 2129.1 | K49: =K37+K48 -> 1509.2
D50: Проверка баланса | E50: =E24-E49 -> 0 | F50: =F24-F49 -> -0.002 | G50: =G24-G49 -> -0.015 | H50: =H24-H49 -> -0.001 | I50: =I24-I49 -> -0.0023 | J50: =J24-J49 -> 0 | K50: =K24-K49 -> 0
D54: Отчет о прибылях и убытках | E54: За год, закончившийся 31.12'
D55: млрд руб. | E55: =E7 -> 2009 | F55: =F7 -> 2010 | G55: =G7 -> 2011 | H55: =H7 -> 2012 | I55: =I7 -> 2013 | J55: =J7 -> 2014 | K55: =K7 -> 2015
D56: Процентные доходы | E56: 82.264 | F56: 77.193 | G56: 58.913 | H56: 90.148 | I56: 124.774 | J56: 166.8 | K56: 176.4
D57: Процентные расходы | E57: -50.988 | F57: -37.569 | G57: -35.095 | H57: -50.623 | I57: -64.6 | J57: -104.4 | K57: -130.4
D58: Чистые процентные доходы | E58: =SUM(E56:E57) -> 31.276 | F58: =SUM(F56:F57) -> 39.624 | G58: =SUM(G56:G57) -> 23.818 | H58: =SUM(H56:H57) -> 39.525 | I58: =SUM(I56:I57) -> 60.174 | J58: =SUM(J56:J57) -> 62.4 | K58: =SUM(K56:K57) -> 46
D59: Создание резерва под обесценение средств в банках и кредитов и авансов клиентам | E59: -30.751 | F59: -105.513 | G59: -120.737 | H59: 15.043 | I59: 7.125 | J59: -37.6 | K59: -35.5
D60: Чистые процентные доходы после создания резервов под обесценение | E60: =SUM(E58:E59) -> 0.525 | F60: =SUM(F58:F59) -> -65.889 | G60: =SUM(G58:G59) -> -96.919 | H60: =SUM(H58:H59) -> 54.568 | I60: =SUM(I58:I59) -> 67.299 | J60: =SUM(J58:J59) -> 24.8 | K60: =SUM(K58:K59) -> 10.5
D61: Комиссионные доходы | E61: 6.966 | F61: 7.135 | G61: 7.83 | H61: 8.225 | I61: 10.4 | J61: 14.6 | K61: 17.5
D62: Комиссионные расходы | E62: -1.486 | F62: -1.675 | G62: -1.942 | H62: -1.918 | I62: -2.1 | J62: -2.5 | K62: -2.7
D63: Расходы за вычетом доходов от досрочного погашения обязательств | F63: 0 | G63: -1.111 | H63: -4.876 | I63: -3.8 | J63: -0.3 | K63: -1.5
D64: Прибыль/ (убыток) от первоначального признания и реструктуризации финансовых обязательств | F64: 1.112 | G64: 152.002 | H64: -0.837 | I64: 0 | J64: 99.1 | K64: -0.6
D65: Доходы за вычетом расходов от операций с финансовыми инструментами, предназначенными для торговли | E65: =9.595-1.141 -> 8.454 | F65: 3.793 | G65: 0.048 | H65: 1.558 | I65: 0.1 | J65: 6.5 | K65: 0.3
D66: Доходы за вычетом расходов от реализации финансовых активов, имеющихся в наличии для продажи | E66: 0.935 | F66: -5.017 | G66: - | H66: 0.954 | I66: 1 | J66: 0.1 | K66: 0
A67: * | D67: Обесценение финансовых активов, имеющихся в наличии для продажи | E67: -0.233 | G67: -10.565 | H67: -1.321 | I67: -1.3 | J67: 0 | K67: 0
D68: Доходы за вычетом расходов по операциям с иностранной валютой и драгметаллами | E68: 0.638 | F68: 2.255 | G68: 5.883 | H68: 9.67 | I68: -0.2 | J68: 4.9 | K68: 6.5
D69: Расходы за вычетом доходов от переоценки валютных статей | E69: -0.497 | F69: -2.196 | G69: -2.635 | H69: -5.527 | I69: 2.2 | J69: -15.5 | K69: -19.6
D70: Доходы за вычетом расходов от переоценки инвестиционной недвижимости | H70: -1.179 | I70: 0.5 | J70: 1.4 | K70: 0.9
D71: Прочие доходы/ (расходы) от восстановления/ (создания) резервов | E71: =-0.6-0.004-0.205 -> -0.809 | F71: -2.989 | G71: -1.114 | H71: -0.845 | I71: -0.4 | J71: -88.2 | K71: 28.2
D72: Заработанные страховые премии, нетто | I72: 0 | J72: 9.3 | K72: 7.1
D73: Состоявшиеся страховые выплаты, нетто, и изменение обязательств перед страхователями | I73: 0 | J73: -9.8 | K73: -8
D74: Доходы от небанковской деятельности | G74: -0.233 | H74: 7.518 | I74: 8.7 | J74: 10.2 | K74: 11.3
D75: Расходы от небанковской деятельности | H75: -7.742 | I75: -11 | J75: -12.5 | K75: -13.3
D76: Прочие доходы за вычетом расходов | E76: =0.019+1.856 -> 1.875 | F76: 1.903 | G76: 0.592 | H76: 1.658 | I76: 0.9 | J76: 1.6 | K76: 0.7
D77: Убыток от обесценения групп выбытия, классифицрованных как предназначенные для продажи | E77: 0 | F77: 0 | G77: 0 | H77: 0 | I77: 0 | J77: 0 | K77: -0.5
D78: Чистые непроцентные доходы | E78: =SUM(E61:E77) -> 15.843 | F78: =SUM(F61:F77) -> 4.321 | G78: =SUM(G61:G77) -> 148.755 | H78: =SUM(H61:H77) -> 5.338 | I78: =SUM(I61:I77) -> 5 | J78: =SUM(J61:J77) -> 18.9 | K78: =SUM(K61:K77) -> 26.3
D79: Операционные доходы | E79: =E60+E78 -> 16.368 | F79: =F60+F78 -> -61.568 | G79: =G60+G78 -> 51.836 | H79: =H60+H78 -> 59.906 | I79: =I60+I78 -> 72.299 | J79: =J60+J78 -> 43.7 | K79: =K60+K78 -> 36.8
D80: Общие и административные расходы | E80: =-14.317-0.633 -> -14.95 | F80: -8.352 | G80: -9.204 | H80: -10.239 | I80: -12.1 | J80: -13.5 | K80: -15.4
D81: Расходы на содержание персонала | F81: -9.499 | G81: -9.807 | H81: -13.667 | I81: -18.4 | J81: -22.3 | K81: -19.6
D82: Доля в чистой прибыли ассоциированных компаний | E82: -0.129 | F82: -3.091 | G82: -0.757 | H82: -0.829 | I82: 0.2 | J82: 0.1 | K82: 0.1
D83: Чистая прибыль/ (убыток) от приобретения и выбытия дочерних и ассоциированных компаний | E83: =-0.001-0.031 -> -0.032 | F83: -2.756 | G83: 0.306 | H83: -0.004 | I83: 3.1 | J83: -6.9 | K83: 0.1
D84: Убыток по чистой монетарной позиции | E84: 0 | F84: 0 | G84: -0.952 | H84: -0.28 | I84: -0.2 | J84: -0.2 | K84: 0
D85: Прибыль до налогообложения | E85: =SUM(E79:E84) -> 1.257 | F85: =SUM(F79:F84) -> -85.266 | G85: =SUM(G79:G84) -> 31.422 | H85: =SUM(H79:H84) -> 34.887 | I85: =SUM(I79:I84) -> 44.899 | J85: =SUM(J79:J84) -> 0.9 | K85: =SUM(K79:K84) -> 2
D86: (Расходы)/ Экономия по налогу на прибыль | E86: -0.535 | F86: 15.524 | G86: -6.805 | H86: -6.568 | I86: -7.6 | J86: 0.3 | K86: -0.3
D87: Чистая прибыль после налогообложения | E87: =SUM(E85:E86) -> 0.722 | F87: =SUM(F85:F86) -> -69.742 | G87: =SUM(G85:G86) -> 24.617 | H87: =SUM(H85:H86) -> 28.319 | I87: =SUM(I85:I86) -> 37.299 | J87: =SUM(J85:J86) -> 1.2 | K87: =SUM(K85:K86) -> 1.7
D88: Прибыль/ (убыток) после налогообложения от дочерних компаний, приобретенных исключительно для продажи | I88: 0.4 | J88: 1.2 | K88: -0.5
D89: Чистая прибыль | E89: =SUM(E87:E88) -> 0.722 | F89: =SUM(F87:F88) -> -69.742 | G89: =SUM(G87:G88) -> 24.617 | H89: =SUM(H87:H88) -> 28.319 | I89: =SUM(I87:I88) -> 37.699 | J89: =SUM(J87:J88) -> 2.4 | K89: =SUM(K87:K88) -> 1.2
D90: Чистая прибыль, приходящаяся на:
C91: - | D91: Акционеров банка | F91: -69.75 | G91: 24.6128 | H91: 28.383 | I91: 37.8 | J91: 2.3 | K91: 1.2
C92: - | D92: Неконтрольные доли участия | F92: 0.008 | G92: 0.0037 | H92: -0.064 | I92: -0.1 | J92: 0.1 | K92: 0
D93: Прибыль на акцию: базовая и с учетом разводнения (в рублях на 1 акцию) | E93: 4.81 | F93: -411.4 | G93: 136.2 | H93: 104.5 | I93: 138.7 | J93: 8.5 | K93: 4.4
D94: Прибыль на акцию: базовая и с учетом разводнения до прибыли после налогообложения, полученной от дочерних компаний, приобретенных исключительно в целях перепродажи (в рублях на 1 акцию) | I94: 137.3 | J94: 4.1 | K94: 6.3
D95: Проверка чистой прибыли | E95: =E89-SUM(E91:E92) -> 0.722 | F95: =F89-SUM(F91:F92) -> 0 | G95: =G89-SUM(G91:G92) -> 0.0005 | H95: =H89-SUM(H91:H92) -> 0 | I95: =I89-SUM(I91:I92) -> -0.001 | J95: =J89-SUM(J91:J92) -> 0 | K95: =K89-SUM(K91:K92) -> -9.7699626e-15
D99: Отчет о совокупном доходе | E99: За год, закончившийся 31.12'
D100: млрд руб. | E100: =E7 -> 2009 | F100: =F7 -> 2010 | G100: =G7 -> 2011 | H100: =H7 -> 2012 | I100: =I7 -> 2013 | J100: =J7 -> 2014 | K100: =K7 -> 2015
D101: Чистая прибыль за период | E101: =E89 -> 0.722 | F101: =F89 -> -69.742 | G101: =G89 -> 24.617 | H101: =H89 -> 28.319 | I101: =I89 -> 37.699 | J101: =J89 -> 2.4 | K101: =K89 -> 1.2
D102: Прочий совокупный доход/ (расход), подлежащий реклассификации в прибыли и убытк в последующих периодах:
D103: Нереализованная прибыль/ (непокрытый) убыток от переоценки финансовых активов, имеющихся в наличии для продажи, за вычетом налога | E103: =-0.008+0.001 -> -0.007 | F103: 0.052 | G103: 0.045 | H103: 2.236 | I103: 0.3 | J103: -5.7 | K103: 3.9
D104: Реклассификация ранее признанного результата от переоценки финансовых активов, имеющихся в наличии для продажи, в связи с их продажей, за вычетом налога | G104: 0 | H104: -0.763 | I104: -0.9 | J104: -0.1 | K104: 0
D105: Влияние пересчета валют, за вычетом налога | E105: -0.201 | F105: =0.043-0.011 -> 0.032 | G105: =-0.5505-0.009 -> -0.5595 | H105: 0.517 | I105: -0.001 | J105: -0.1 | K105: 0
D106: Доля в прочем совокупном доходе ассоциированных компаний и совместных предприятий | G106: 0 | H106: 0 | I106: 0 | J106: 0 | K106: 0.2
D107: Прочий совокупный доход, не подлежащий реклассификации в прибыли и убытки в последующих периодах:
D108: Признанный резерв переоценки основных средств | E108: =-1.835+0.367 -> -1.468 | G108: 0 | H108: 2.655 | I108: 0 | J108: 0 | K108: 0.9
D109: Итого прочие совокупный доход/ (расход) за период | E109: =SUM(E103:E108) -> -1.676 | F109: =SUM(F103:F108) -> 0.084 | G109: =SUM(G103:G108) -> -0.5145 | H109: =SUM(H103:H108) -> 4.645 | I109: =SUM(I103:I108) -> -0.601 | J109: =SUM(J103:J108) -> -5.9 | K109: =SUM(K103:K108) -> 5
D110: Совокупный доход/ (расход) за период, итого | E110: =E101+E109 -> -0.954 | F110: =F101+F109 -> -69.658 | G110: =G101+G109 -> 24.1025 | H110: =H101+H109 -> 32.964 | I110: =I101+I109 -> 37.098 | J110: =J101+J109 -> -3.5 | K110: =K101+K109 -> 6.2
...

Sheet Ф_808_2023-2017
A1: Номер строки | B1: Наименование инструмента (показателя) | C1: 2017 | D1: 2018 | E1: 2019 | F1: 2020 | G1: 2021 | H1: 2022 | I1: 2023 | J1: 2024
A2: Источники базового капитала | B2: Источники базового капитала
A3: 1 | B3: Уставный капитал и эмиссионный доход, всего, в том числе сформированный: | C3: 48011741 | D3: 48011741 | E3: 48011741 | F3: 48011741 | G3: 48011741 | H3: 48011741 | I3: 48011741 | J3: 48011741
A4: 1.1 | B4: обыкновенными акциями (долями) | C4: 48011741 | D4: 48011741 | E4: 48011741 | F4: 48011741 | G4: 48011741 | H4: 48011741 | I4: 48011741 | J4: 48011741
A5: 1.2 | B5: привилегированными акциями | C5: 0 | D5: 0 | E5: 0 | F5: 0 | G5: 0 | H5: 0 | I5: 0 | J5: 0
A6: 2 | B6: Нераспределенная прибыль (убыток): | C6: 8346702 | D6: 8743061 | E6: 17195208 | F6: 17152868 | G6: 16934996 | H6: 21228177 | I6: 23797022 | J6: 44867500
A7: 2.1 | B7: прошлых лет | C7: 411512 | D7: 588794 | E7: 6002640 | F7: 16107897 | G7: 13266615 | H7: 17355948 | I7: 18975773 | J7: 44867500
A8: 2.2 | B8: отчетного года | C8: 7935190 | D8: 8154267 | E8: 11192568 | F8: 1044971 | G8: 3668381 | H8: 3872229 | I8: 4821249 | J8: 0
A9: 3 | B9: Резервный фонд | C9: 64084 | D9: 109078 | E9: 207894 | F9: 520535 | G9: 738407 | H9: 1053596 | I9: 1131454 | J9: 1451972
A10: 4 | B10: Доли уставного капитала, подлежащие поэтапному исключению из расчета собственных средств (капитала) | C10: 0 | D10: 0
A11: 5 | B11: Инструменты базового капитала дочерних организаций, принадлежащие третьим сторонам | C11: 0 | D11: 95207
A12: 6 | B12: Источники базового капитала, итого (строка 1 +/– строка 2 + строка 3 – строка 4 + строка 5) | C12: 56422527 | D12: 56959087 | E12: 65414843 | F12: 65685144 | G12: 65685144 | H12: 70293514 | I12: 72940217 | J12: 94331213
A13: Показатели, уменьшающие источники базового капитала | B13: Показатели, уменьшающие источники базового капитала
A14: 7 | B14: Корректировка стоимости финансового инструмента | C14: 0 | D14: 0 | E14: 0 | F14: 0 | G14: 0 | H14: 0 | I14: 0 | J14: 0
A15: 8 | B15: Деловая репутация (гудвил) за вычетом отложенных налоговых обязательств | C15: 0 | D15: 0 | E15: 0 | F15: 0 | G15: 0 | H15: 0 | I15: 0 | J15: 0
A16: 9 | B16: Нематериальные активы (кроме деловой репутации и сумм прав по обслуживанию ипотечных кредитов) за вычетом отложенных налоговых обязательств | C16: 315083 | D16: 747255 | E16: 1783192 | F16: 3037328 | G16: 4409785 | H16: 6973458 | I16: 8737457 | J16: 10774027
A17: 10 | B17: Отложенные налоговые активы, зависящие от будущей прибыли | C17: 85194 | D17: 264330 | E17: 708714 | F17: 883074 | G17: 921846 | H17: 1997406 | I17: 0 | J17: 0
A18: 11 | B18: Резервы хеджирования денежных потоков | C18: 0 | D18: 0 | E18: 0 | F18: 0 | G18: 0 | H18: 0 | I18: 0 | J18: 0
A19: 12 | B19: Недосозданные резервы на возможные потери | C19: 0 | D19: 0 | E19: 0 | F19: 367065 | G19: 367065 | H19: 367065 | I19: 367065 | J19: 367065
A20: 13 | B20: Доход от сделок секьюритизации | C20: 0 | D20: 0
A21: 14 | B21: Доходы и расходы, связанные с изменением кредитного риска по обязательствам, оцениваемым по справедливой стоимости | C21: 0 | D21: 0
A22: 15 | B22: Активы пенсионного плана с установленными выплатами | C22: 0 | D22: 0
A23: 16 | B23: Вложения в собственные акции (доли) | C23: 0 | D23: 378281 | E23: 377330 | F23: 397695
A24: 17 | B24: Встречные вложения кредитной организации и финансовой организации в инструменты базового капитала | C24: 0 | D24: 0 | E24: 6180 | F24: 6180
A25: 18 | B25: Несущественные вложения в инструменты базового капитала финансовых организаций | C25: 0 | D25: 0 | E25: 0 | F25: 0
A26: 19 | B26: Существенные вложения в инструменты базового капитала финансовых организаций | C26: 0 | D26: 0 | E26: 0 | F26: 0
A27: 20 | B27: Права по обслуживанию ипотечных кредитов | C27: 0 | D27: 0
A28: 21 | B28: Отложенные налоговые активы, не зависящие от будущей прибыли | C28: 0 | D28: 0 | E28: 0 | F28: 0 | G28: 0 | H28: 0 | I28: 0 | J28: 0
A29: 22 | B29: Совокупная сумма существенных вложений и отложенных налоговых активов в части, превышающей 15 процентов от величины базового капитала, всего, в том числе: | C29: 0 | D29: 0 | E29: 0 | F29: 0
A30: 23 | B30: существенные вложения в инструменты базового капитала финансовых организаций | C30: 0 | D30: 0 | E30: 0 | F30: 0
A31: 24 | B31: права по обслуживанию ипотечных кредитов | C31: 0 | D31: 0
A32: 25 | B32: отложенные налоговые активы, не зависящие от будущей прибыли | C32: 0 | D32: 0 | F32: 0 | I32: 0 | J32: 0
A33: 26 | B33: Иные показатели, уменьшающие источники базового капитала, установленные Банком России | C33: 299849 | D33: 224198 | E33: 224198 | F33: 224198 | G33: 224198 | H33: 224198 | I33: 224198 | J33: 224198
A34: 27 | B34: Отрицательная величина добавочного капитала | C34: 183731 | D34: 0 | E34: 0 | F34: 0 | G34: 0 | H34: 0 | I34: 0 | J34: 0
A35: 28 | B35: Показатели, уменьшающие источники базового капитала, итого (сумма строк 7–22, 26 и 27) | C35: 883857 | D35: 1614064 | E35: 3099614 | F35: 4915540 | G35: 6339559 | H35: 9981379 | I35: 9746337 | J35: 11755919
A36: 29 | B36: Базовый капитал, итого (строка 6 – строка 28) | C36: 55538670 | D36: 55345023 | E36: 62315229 | F36: 60769604 | G36: 59345585 | H36: 60312135 | I36: 63193880 | J36: 82575294
A37: Источники добавочного капитала | B37: Источники добавочного капитала
A38: 30 | B38: Инструменты добавочного капитала и эмиссионный доход, всего, в том числе: | C38: 0 | D38: 0 | E38: 0 | F38: 0 | G38: 0 | H38: 0 | I38: 0 | J38: 0
A39: 31 | B39: классифицируемые как капитал | C39: 0 | D39: 0 | E39: 0 | F39: 0 | G39: 0 | H39: 0 | I39: 0 | J39: 0
A40: 32 | B40: классифицируемые как обязательства | C40: 0 | D40: 0 | E40: 0 | F40: 0 | G40: 0 | H40: 0 | I40: 0 | J40: 0
A41: 33 | B41: Инструменты добавочного капитала, подлежащие поэтапному исключению из расчета собственных средств (капитала) | C41: 0 | D41: 0 | E41: 0 | F41: 0 | G41: 0 | H41: 0 | I41: 0 | J41: 0
A42: 34 | B42: Инструменты добавочного капитала дочерних организаций, принадлежащие третьим сторонам, всего, в том числе: | C42: 0 | D42: 0
A43: 35 | B43: инструменты добавочного капитала дочерних организаций, подлежащие поэтапному исключению из расчета собственных средств (капитала) | C43: 0 | D43: 0
A44: 36 | B44: Источники добавочного капитала, итого (строка 30 + строка 33 + строка 34) | C44: 0 | D44: 0 | E44: 0 | F44: 0 | G44: 0 | H44: 0 | I44: 0 | J44: 0
A45: Показатели, уменьшающие источники добавочного капитала | B45: Показатели, уменьшающие источники добавочного капитала
A46: 37 | B46: Вложения в собственные инструменты добавочного капитала | C46: 0 | D46: 0 | E46: 0 | F46: 0
A47: 38 | B47: Встречные вложения кредитной организации и финансовой организации в инструменты добавочного капитала | C47: 0 | D47: 0 | E47: 0 | F47: 0
A48: 39 | B48: Несущественные вложения в инструменты добавочного капитала финансовых организаций | C48: 0 | D48: 0 | E48: 0 | F48: 0
A49: 40 | B49: Существенные вложения в инструменты добавочного капитала финансовых организаций | C49: 0 | D49: 0 | E49: 0 | F49: 0
A50: 41 | B50: Иные показатели, уменьшающие источники добавочного капитала, установленные Банком России | C50: 183731 | D50: 0 | E50: 0 | F50: 0 | G50: 0 | H50: 0 | I50: 0 | J50: 0
A51: 42 | B51: Отрицательная величина дополнительного капитала | C51: 0 | D51: 0 | E51: 0 | F51: 0 | G51: 0 | H51: 0 | I51: 0 | J51: 0
A52: 43 | B52: Показатели, уменьшающие источники добавочного капитала, итого (сумма строк 37–42) | C52: 183731 | D52: 0 | E52: 0 | F52: 0 | G52: 0 | H52: 0 | I52: 0 | J52: 0
A53: 44 | B53: Добавочный капитал, итого (строка 36 – строка 43) | C53: 0 | D53: 0 | E53: 0 | F53: 0 | G53: 0 | H53: 0 | I53: 0 | J53: 0
A54: 45 | B54: Основной капитал, итого (строка 29 + строка 44) | C54: 55538670 | D54: 55345023 | E54: 62315229 | F54: 60769604 | G54: 59345585 | H54: 60312135 | I54: 63193880 | J54: 82575294
A55: Источники дополнительного капитала | B55: Источники дополнительного капитала
A56: 46 | B56: Инструменты дополнительного капитала и эмиссионный доход | C56: 19234106 | D56: 20835352 | E56: 12837465 | F56: 11751655 | G56: 15745009 | H56: 14200777 | I56: 32863078 | J56: 18795461
A57: 47 | B57: Инструменты дополнительного капитала, подлежащие поэтапному исключению из расчета собственных средств (капитала) | C57: 3428384 | D57: 3932783 | E57: 3081458 | F57: 2515553 | G57: 1131762 | H57: 0 | I57: 0 | J57: 0
A58: 48 | B58: Инструменты дополнительного капитала дочерних организаций, принадлежащие третьим сторонам, всего, в том числе: | C58: 0 | D58: 113536
A59: 49 | B59: инструменты дополнительного капитала дочерних организаций, подлежащие поэтапному исключению из расчета собственных средств (капитала) | C59: 0 | D59: 0
A60: 50 | B60: Резервы на возможные потери | C60: 0 | D60: 0 | E60: 0 | F60: 0 | G60: 0 | H60: 0 | I60: 0 | J60: 0
A61: 51 | B61: Источники дополнительного капитала, итого (строка 46 + строка 47 + строка 48 + строка 50) | C61: 22662490 | D61: 24881671 | E61: 15918923 | F61: 14267208 | G61: 16876771 | H61: 14200777 | I61: 32863078 | J61: 18795461
A62: Показатели, уменьшающие источники дополнительного капитала | B62: Показатели, уменьшающие источники дополнительного капитала
A63: 52 | B63: Вложения в собственные инструменты дополнительного капитала | C63: 0 | D63: 0 | E63: 0 | F63: 0 | G63: 0 | H63: 0 | I63: 0 | J63: 0
A64: 53 | B64: Встречные вложения кредитной организации и финансовой организации в инструменты дополнительного капитала | C64: 0 | D64: 0 | E64: 0 | F64: 0 | G64: 0 | H64: 0 | I64: 0 | J64: 0
A65: 54 | B65: Несущественные вложения в инструменты дополнительного капитала и иные инструменты, обеспечивающие общую способность к поглощению убытков финансовых организаций | C65: 0 | D65: 0 | E65: 0 | F65: 0
A66: 54а | B66: вложения в иные инструменты, обеспечивающие общую способность к поглощению убытков финансовых организаций
A67: 55 | B67: Существенные вложения в инструменты дополнительного капитала и иные инструменты, обеспечивающие общую способность к поглощению убытков финансовых организаций | C67: 0 | D67: 0 | E67: 0 | F67: 0
A68: 56 | B68: Иные показатели, уменьшающие источники дополнительного капитала, установленные Банком России, всего, в том числе: | C68: 0 | D68: 0 | E68: 0 | F68: 0 | G68: 0 | H68: 0 | I68: 0 | J68: 0
A69: 56.1 | B69: просроченная дебиторская задолженность длительностью свыше 30 календарных дней | C69: 0 | D69: 0 | E69: 0 | F69: 0 | G69: 0 | H69: 0 | I69: 0 | J69: 0
A70: 56.2 | B70: превышение совокупной суммы кредитов, банковских гарантий и поручительств, предоставленных своим акционерам (участникам) и инсайдерам, над ее максимальным размером | C70: 0 | D70: 0 | E70: 0 | F70: 0 | G70: 0 | H70: 0 | I70: 0 | J70: 0
A71: 56.3 | B71: вложения в создание и приобретение основных средств и материальных запасов | C71: 0 | D71: 0 | E71: 0 | F71: 0 | G71: 0 | H71: 0 | I71: 0 | J71: 0
A72: 56.4 | B72: разница между действительной стоимостью доли, причитающейся вышедшим из общества участникам, и стоимостью, по которой доля была реализована другому участнику | C72: 0 | D72: 0 | E72: 0 | F72: 0 | G72: 0 | H72: 0 | I72: 0 | J72: 0
A73: 57 | B73: Показатели, уменьшающие источники дополнительного капитала, итого (сумма строк с 52 по 56) | C73: 0 | D73: 0 | E73: 0 | F73: 0 | G73: 0 | H73: 0 | I73: 0 | J73: 0
A74: 58 | B74: Дополнительный капитал, итого (строка 51 – строка 57) | C74: 22662490 | D74: 24881671 | E74: 15918923 | F74: 14267208 | G74: 16876771 | H74: 14200777 | I74: 32863078 | J74: 18795461
A75: 59 | B75: Собственные средства (капитал), итого (строка 45 + строка 58) | C75: 78201160 | D75: 80226694 | E75: 78234152 | F75: 75036812 | G75: 76222356 | H75: 74512912 | I75: 96056958 | J75: 101370755
A76: 60 | B76: Активы, взвешенные по уровню риска:
A77: 60.1 | B77: необходимые для определения достаточности базового капитала | C77: 548339488 | D77: 526114963 | E77: 518631101 | F77: 524301086 | G77: 633235213 | H77: 624879043 | I77: 684497906 | J77: 756291057
A78: 60.2 | B78: необходимые для определения достаточности основного капитала | C78: 548339488 | D78: 526114963 | E78: 518631101 | F78: 524301086 | G78: 633235213 | H78: 624879043 | I78: 684497906 | J78: 756291057
A79: 60.3 | B79: необходимые для определения достаточности собственных средств (капитала) | C79: 548309316 | D79: 526129031 | E79: 517567321 | F79: 524308466 | G79: 633242593 | H79: 626380967 | I79: 686526139 | J79: 758768180
A80: Показатели достаточности собственных средств (капитала) и надбавки к нормативам достаточности собственных средств (капитала), процент | B80: Показатели достаточности собственных средств (капитала) и надбавки к нормативам достаточности собственных средств (капитала), процент
A81: 61 | B81: Достаточность базового капитала (строка 29 : строка 60.1) | C81: 10 | D81: 11 | E81: 12 | F81: 12 | G81: 9 | H81: 10 | I81: 9 | J81: 11
A82: 62 | B82: Достаточность основного капитала (строка 45 : строка 60.2) | C82: 10 | D82: 11 | E82: 12 | F82: 12 | G82: 9 | H82: 10 | I82: 9 | J82: 11
A83: 63 | B83: Достаточность собственных средств (капитала) (строка 59 : строка 60.3) | C83: 14 | D83: 15 | E83: 15 | F83: 14 | G83: 12 | H83: 12 | I83: 14 | J83: 13
A84: 64 | B84: Надбавки к нормативу достаточности базового капитала, всего, в том числе: | C84: 1 | D84: 2
A85: 65 | B85: надбавка поддержания достаточности капитала | C85: 1 | D85: 2
A86: 66 | B86: антициклическая надбавка | C86: 0 | D86: 0
A87: 67 | B87: надбавка за системную значимость банков
A88: 68 | B88: Базовый капитал, доступный для направления на поддержание надбавок к нормативам достаточности собственных средств (капитала) | C88: 4 | D88: 5
A89: Нормативы достаточности собственных средств (капитала), процент | B89: Нормативы достаточности собственных средств (капитала), процент
A90: 69 | B90: Норматив достаточности базового капитала | C90: 5 | D90: 5 | E90: 5 | F90: 5 | G90: 5 | H90: 5 | I90: 5 | J90: 5
A91: 70 | B91: Норматив достаточности основного капитала | C91: 6 | D91: 6 | E91: 6 | F91: 6 | G91: 6 | H91: 6 | I91: 6 | J91: 6
A92: 71 | B92: Норматив достаточности собственных средств (капитала) | C92: 8 | D92: 8 | E92: 8 | F92: 8 | G92: 8 | H92: 8 | I92: 8 | J92: 8
A93: Показатели, не превышающие установленные пороги существенности и не принимаемые в уменьшение источников капитала | B93: Показатели, не превышающие установленные пороги существенности и не принимаемые в уменьшение источников капитала
A94: 72 | B94: Несущественные вложения в инструменты капитала и иные инструменты, обеспечивающие общую способность к поглощению убытков финансовых организаций | C94: 1611224 | D94: 1764830 | E94: 1349325 | F94: 2806507
A95: 73 | B95: Существенные вложения в инструменты базового капитала финансовых организаций | C95: 150000 | D95: 150000 | E95: 1384722 | F95: 1994393
A96: 74 | B96: Права по обслуживанию ипотечных кредитов | C96: 0 | D96: 0
A97: 75 | B97: Отложенные налоговые активы, не зависящие от будущей прибыли | C97: 101488 | D97: 0 | E97: 0 | F97: 0 | G97: 0 | H97: 0 | I97: -1579395 | J97: 0
A98: Ограничения на включения в расчет дополнительного капитала резервов на возможные потери | B98: Ограничения на включения в расчет дополнительного капитала резервов на возможные потери
A99: 76 | B99: Резервы на возможные потери, включаемые в расчет дополнительного капитала, в отношении позиций, для расчета кредитного риска по которым применяется стандартизированный подход | C99: 0 | D99: 0
A100: 77 | B100: Ограничения на включение в расчет дополнительного капитала сумм резервов на возможные потери при использовании стандартизированного подхода | C100: 0 | D100: 0
...

Sheet Ф_808_2016-2015
A1: Номер строки | B1: Наименование инструмента (показателя) | C1: 2015 | D1: 2016
A2: Источники базового капитала | B2: Источники базового капитала
A3: 1 | B3: Уставный капитал и эмиссионный доход, всего, в том числе, сформированный: | C3: 38011741 | D3: 38011741
A4: 1.1 | B4: обыкновенными акциями (долями) | C4: 38011741 | D4: 38011741
A5: 1.2 | B5: привилегированными акциями | C5: 0 | D5: 0
A6: 2 | B6: Нераспределенная прибыль (убыток): | C6: -3558085 | D6: 4715067
A7: 2.1 | B7: прошлых лет | C7: 5976703 | D7: 805695
A8: 2.2 | B8: отчетного года | C8: -9534788 | D8: 3909372
A9: 3 | B9: Резервный фонд | C9: 2401789 | D9: 0
A10: 4 | B10: Доли уставного капитала, подлежащие поэтапному исключению из расчета собственных средств (капитала)
A11: 5 | B11: Инструменты базового капитала дочерних организаций, принадлежащие третьим сторонам
A12: 6 | B12: Источники базового капитала, итого: (строка 1 +/– строка 2 + строка 3 - строка 4 + строка 5) | C12: 36855445 | D12: 42726808
A13: Показатели, уменьшающие источники базового капитала | B13: Показатели, уменьшающие источники базового капитала
A14: 7 | B14: Корректировка торгового портфеля
A15: 8 | B15: Деловая репутация (Гудвил) за вычетом отложенных налоговых обязательств | C15: 0 | D15: 0
A16: 9 | B16: Нематериальные активы (кроме деловой репутации и сумм прав по обслуживанию ипотечных кредитов) за вычетом отложенных налоговых обязательств | C16: 10518 | D16: 156300
A17: 10 | B17: Отложенные налоговые активы, зависящие от будущей прибыли | C17: 175672 | D17: 0
A18: 11 | B18: Резервы хеджирования денежных потоков
A19: 12 | B19: Недосозданные резервы на возможные потери | C19: 0 | D19: 0
A20: 13 | B20: Доход от сделок секьюритизации
A21: 14 | B21: Доходы и расходы, связанные с изменением кредитного риска по обязательствам, оцениваемым по справедливой стоимости
A22: 15 | B22: Активы пенсионного плана с установленными выплатами
A23: 16 | B23: Вложения в собственные акции (доли) | C23: 0 | D23: 0
A24: 17 | B24: Взаимное перекрестное владение акциями (долями)
A25: 18 | B25: Несущественные вложения в инструменты базового капитала финансовых организаций | C25: 0 | D25: 0
A26: 19 | B26: Существенные вложения в инструменты базового капитала финансовых организаций | C26: 0 | D26: 0
A27: 20 | B27: Права по обслуживанию ипотечных кредитов
A28: 21 | B28: Отложенные налоговые активы, не зависящие от будущей прибыли | C28: 0 | D28: 0
A29: 22 | B29: Совокупная сумма существенных вложений и отложенных налоговых активов в части, превышающей 15 процентов от величины базового капитала, всего, в том числе: | C29: 0 | D29: 0
A30: 23 | B30: существенные вложения в инструменты базового капитала финансовых организаций | C30: 0 | D30: 0
A31: 24 | B31: права по обслуживанию ипотечных кредитов
A32: 25 | B32: отложенные налоговые активы, не зависящие от будущей прибыли | C32: 0 | D32: 0
A33: 26 | B33: Иные показатели, уменьшающие источники базового капитала, установленные Банком России, всего, в том числе: | C33: 190094 | D33: 285141
A34: 26.1 | B34: показатели, подлежащие поэтапному исключению из расчета собственных средств (капитала) | C34: 0 | D34: 0
A35: 27 | B35: Отрицательная величина добавочного капитала | C35: 895002 | D35: 655430
A36: 28 | B36: Показатели, уменьшающие источники базового капитала, итого: (сумма строк с 7 по 22 и строк 26 и 27) | C36: 1271286 | D36: 1096871
A37: 29 | B37: Базовый капитал, итого: (строка 6 – строка 28) | C37: 35584159 | D37: 41629937
A38: Источники добавочного капитала | B38: Источники добавочного капитала
A39: 30 | B39: Инструменты добавочного капитала и эмиссионный доход, всего, в том числе: | C39: 0 | D39: 0
A40: 31 | B40: классифицируемые как капитал | C40: 0 | D40: 0
A41: 32 | B41: классифицируемые как обязательства | C41: 0 | D41: 0
A42: 33 | B42: Инструменты добавочного капитала, подлежащие поэтапному исключению из расчета собственных средств (капитала) | C42: 0 | D42: 0
A43: 34 | B43: Инструменты добавочного капитала дочерних организаций, принадлежащие третьим сторонам, всего, в том числе:
A44: 35 | B44: инструменты добавочного капитала дочерних организаций, подлежащие поэтапному исключению из расчета собственных средств (капитала)
A45: 36 | B45: Источники добавочного капитала, итого: (строка 30 + строка 33 + строка 34) | C45: 0 | D45: 0
A46: Показатели, уменьшающие источники добавочного капитала | B46: Показатели, уменьшающие источники добавочного капитала
A47: 37 | B47: Вложения в собственные инструменты добавочного капитала | C47: 0 | D47: 0
A48: 38 | B48: Взаимное перекрестное владение инструментами добавочного капитала
A49: 39 | B49: Несущественные вложения в инструменты добавочного капитала финансовых организаций
A50: 40 | B50: Существенные вложения в инструменты добавочного капитала финансовых организаций | C50: 0 | D50: 0
A51: 41 | B51: Иные показатели, уменьшающие источники добавочного капитала, установленные Банком России, всего, в том числе: | C51: 895002 | D51: 655430
A52: 41.1 | B52: Показатели, подлежащие поэтапному исключению из расчета собственных средств (капитала), всего, из них: | C52: 895002 | D52: 655430
A53: 41.1.1 | B53: нематериальные активы | C53: 15777 | D53: 104200
A54: 41.1.2 | B54: собственные акции (доли), приобретенные (выкупленные) у акционеров (участников) | C54: 0 | D54: 0
A55: 41.1.3 | B55: акции (доли) дочерних и зависимых финансовых организаций и кредитных организаций–резидентов | C55: 594084 | D55: 361136
A56: 41.1.4 | B56: источники собственных средств, для формирования которых использованы ненадлежащие активы | C56: 285141 | D56: 190094
A57: 41.1.5 | B57: отрицательная величина дополнительного капитала, сложившаяся в связи с корректировкой величины собственных средств (капитала) на сумму источников дополнительного капитала, сформированных с использованием инвесторами ненадлежащих активов | C57: 0 | D57: 0
A58: 42 | B58: Отрицательная величина дополнительного капитала | C58: 0 | D58: 0
A59: 43 | B59: Показатели, уменьшающие источники добавочного капитала, итого: (сумма строк с 37 по 42) | C59: 895002 | D59: 655430
A60: 44 | B60: Добавочный капитал, итого: (строка 36 – строка 43) | C60: 0 | D60: 0
A61: 45 | B61: Основной капитал, итого: (строка 29 + строка 44) | C61: 35584159 | D61: 41629937
A62: Источники дополнительного капитала | B62: Источники дополнительного капитала
A63: 46 | B63: Инструменты дополнительного капитала и эмиссионный доход | C63: 12115630 | D63: 18797897
A64: 47 | B64: Инструменты дополнительного капитала, подлежащие поэтапному исключению из расчета собственных средств (капитала) | C64: 11727539 | D64: 10052176
A65: 48 | B65: Инструменты дополнительного капитала дочерних организаций, принадлежащие третьим сторонам, всего, в том числе:
A66: 49 | B66: инструменты дополнительного капитала дочерних организаций, подлежащие поэтапному исключению из расчета собственных средств (капитала)
A67: 50 | B67: Резервы на возможные потери
A68: 51 | B68: Источники дополнительного капитала, итого: (строка 46 + строка 47 + строка 48 + строка 50) | C68: 23843169 | D68: 28850073
A69: Показатели, уменьшающие источники дополнительного капитала | B69: Показатели, уменьшающие источники дополнительного капитала
A70: 52 | B70: Вложения в собственные инструменты дополнительного капитала | C70: 0 | D70: 0
A71: 53 | B71: Взаимное перекрестное владение инструментами дополнительного капитала
A72: 54 | B72: Несущественные вложения в инструменты дополнительного капитала финансовых организаций | C72: 0 | D72: 0
A73: 55 | B73: Существенные вложения в инструменты дополнительного капитала финансовых организаций | C73: 58638 | D73: 45000
A74: 56 | B74: Иные показатели, уменьшающие источники дополнительного капитала, установленные Банком России, всего, в том числе: | C74: 87958 | D74: 74184
A75: 56.1 | B75: Показатели, подлежащие поэтапному исключению из расчета собственных средств (капитала), всего, из них: | C75: 87958 | D75: 74184
A76: 56.1.1 | B76: источники капитала, для формирования которых инвесторами использованы ненадлежащие активы | C76: 0 | D76: 0
A77: 56.1.2 | B77: просроченная дебиторская задолженность длительностью свыше 30 календарных дней | C77: 0 | D77: 0
A78: 56.1.3 | B78: субординированные кредиты, предоставленные кредитным организациям – резидентам | C78: 87958 | D78: 74184
A79: 56.1.4 | B79: превышение совокупной суммы кредитов, банковских гарантий и поручительств, предоставленных своим акционерам (участникам) и инсайдерам, над ее максимальным размером | C79: 0 | D79: 0
A80: 56.1.5 | B80: вложения в сооружение и приобретение основных средств и материальных запасов | C80: 0 | D80: 0
A81: 56.1.6 | B81: разница между действительной стоимостью доли, причитающейся вышедшим из общества участникам, и стоимостью, по которой доля была реализована другому участнику | C81: 0 | D81: 0
A82: 57 | B82: Показатели, уменьшающие источники дополнительного капитала, итого: (сумма строк с 52 по 56) | C82: 146596 | D82: 119184
A83: 58 | B83: Дополнительный капитал, итого: (строка 51 – строка 57) | C83: 23696573 | D83: 28730889
A84: 59 | B84: Собственные средства (капитал), итого: (строка 45 + строка 58) | C84: 59280732 | D84: 70360826
A85: 60 | B85: Активы, взвешенные по уровню риска:
A86: 60.1 | B86: подлежащие поэтапному исключению из расчета собственных средств (капитала) | C86: 263507 | D86: 0
A87: 60.2 | B87: необходимые для определения достаточности базового капитала | C87: 499019424 | D87: 538019710
A88: 60.3 | B88: необходимые для определения достаточности основного капитала | C88: 499019424 | D88: 538019710
A89: 60.4 | B89: необходимые для определения достаточности собственных средств (капитала) | C89: 498877303 | D89: 537904938
A90: Показатели достаточности собственных средств (капитала) и надбавки к нормативам достаточности собственных средств (капитала), процент | B90: Показатели достаточности собственных средств (капитала) и надбавки к нормативам достаточности собственных средств (капитала), процент
A91: 61 | B91: Достаточность базового капитала (строка 29/строка 60.2) | C91: 7 | D91: 8
A92: 62 | B92: Достаточность основного капитала (строка 45/строка 60.3) | C92: 7 | D92: 8
A93: 63 | B93: Достаточность собственных средств (капитала) (строка 59/строка 60.4) | C93: 12 | D93: 13
A94: 64 | B94: Надбавки к нормативам достаточности собственных средств (капитала), всего, в том числе:
A95: 65 | B95: надбавка поддержания достаточности капитала
A96: 66 | B96: антициклическая надбавка
A97: 67 | B97: надбавка за системную значимость банков
A98: 68 | B98: Базовый капитал, доступный для направления на поддержание надбавок к нормативам достаточности собственных средств (капитала)
A99: Нормативы достаточности собственных средств (капитала), процент | B99: Нормативы достаточности собственных средств (капитала), процент
A100: 69 | B100: Норматив достаточности базового капитала | C100: 5 | D100: 5
...

Sheet Ф_135_2017-2015
A1: Краткое наименование норматива | B1: 2017 | C1: 2016 | D1: 2015
A2: Н1.1 | B2: 0.10533 | C2: 0.0771 | D2: 0.0698
A3: Н1.2 | B3: 0.10533 | C3: 0.0771 | D3: 0.0698
A4: Н1.0 | B4: 0.14717 | C4: 0.1336 | D4: 0.1173
A5: Н1.3
A6: Н2 | B6: 2.42094 | C6: 1.7318 | D6: 0.5493
A7: Н3 | B7: 3.30786 | C7: 4.4735 | D7: 0.8269
A8: Н4 | B8: 0.32521 | C8: 0.4237 | D8: 0.8606
A9: Н7 | B9: 1.52423 | C9: 2.0471 | D9: 2.7521
A10: Н9.1 | B10: 0.34012 | C10: 0.1403 | D10: 0.1984
A11: Н10.1 | B11: 0.00216 | C11: 0.0043 | D11: 0.0059
A12: Н12 | B12: 0.14377 | C12: 0.2277 | D12: 0.1018
A13: Н15
A14: Н15.1
A15: Н16
A16: Н16.1
A17: Н16.2
A18: Н18

Sheet Ф_135_2024-2018
A1: Краткое наименование норматива | B1: 2024 | C1: 2023 | D1: 2021 | E1: 2020 | F1: 2019 | G1: 2018
A2: Н1.1 | B2: 0.10932 | C2: 0.09181 | D2: 0.09415 | E2: 0.11613 | F2: 0.11928 | G2: 0.10917
A3: Н1.2 | B3: 0.10932 | C3: 0.09181 | D3: 0.09415 | E3: 0.11613 | F3: 0.11928 | G3: 0.10917
A4: Н1.0 | B4: 0.13298 | C4: 0.14049 | D4: 0.12059 | E4: 0.14334 | F4: 0.15113 | G4: 0.15113
A5: Н1.3
A6: Н1.4 | D6: 0.07781 | E6: 0.08792 | F6: 0.0981 | G6: 0.10551
A7: Н2 | B7: 0.94739 | C7: 1.0833 | D7: 0.47719 | E7: 0.83566 | F7: 1.21316 | G7: 0.73041
A8: Н3 | B8: 1.58313 | C8: 1.42807 | D8: 2.19447 | E8: 0.33194 | F8: 6.48096 | G8: 2.10697
A9: Н4 | B9: 0.46558 | C9: 0.41274 | D9: 0.40717 | E9: 0.31678 | F9: 0.29083 | G9: 0.33024
A10: Н7 | D10: 2.71888 | E10: 2.08775 | F10: 1.96346 | G10: 1.68332
A11: Н12 | D11: 0.15696 | E11: 0.15731 | F11: 0.15225 | G11: 0.14754
A12: Н15
A13: Н15.1
A14: Н16
A15: Н16.1
A16: Н16.2
A17: Н18 | D17: 0 | E17: 0 | F17: 0
A18: Н29

Sheet Ф_123_2021
A1: Номер строки | B1: Наименование показателя | C1: 2021
A2: 000 | B2: Собственные средства (капитал), итого, в том числе: | C2: 76372718
A3: 100 | B3: Источники базового капитала: | C3: 65318079
A4: 100.1 | B4: Уставный капитал кредитной организации: | C4: 48011741
A5: 100.1.1 | B5: сформированный обыкновенными акциями | C5: 48011741
A6: 100.1.2 | B6: сформированный привилегированными акциями, в том числе: | C6: 0
A7: 100.1.2.1 | B7: выпущенными до 1 марта 2013 года | C7: 0
A8: 100.1.3 | B8: сформированный долями | C8: 0
A9: 100.2 | B9: Эмиссионный доход: | C9: 0
A10: 100.2.1 | B10: кредитной организации в организационно-правовой форме акционерного общества, всего, в том числе: | C10: 0
A11: 100.2.1.1 | B11: сформированный при размещении обыкновенных акций | C11: 0
A12: 100.2.1.2 | B12: сформированный при размещении привилегированных акций, в том числе: | C12: 0
A13: 100.2.1.2.1 | B13: выпущенных до 1 марта 2013 года | C13: 0
... A195: 203 | B195: Дополнительный капитал, итого | C195: 16743739

Sheet Ф_123_2020
A1: Номер строки | B1: Наименование показателя | C1: 2020
A2: 000 | B2: Собственные средства (капитал), итого, в том числе: | C2: 75168165
A3: 100 | B3: Источники базового капитала: | C3: 66788831
A4: 100.1 | B4: Уставный капитал кредитной организации: | C4: 48011741
A5: 100.1.1 | B5: сформированный обыкновенными акциями | C5: 48011741
A6: 100.1.2 | B6: сформированный привилегированными акциями, в том числе: | C6: 0
A7: 100.1.2.1 | B7: выпущенными до 1 марта 2013 года | C7: 0
A8: 100.1.3 | B8: сформированный долями | C8: 0
A9: 100.2 | B9: Эмиссионный доход: | C9: 0
A10: 100.2.1 | B10: кредитной организации в организационно-правовой форме акционерного общества, всего, в том числе: | C10: 0
A11: 100.2.1.1 | B11: сформированный при размещении обыкновенных акций | C11: 0
A12: 100.2.1.2 | B12: сформированный при размещении привилегированных акций, в том числе: | C12: 0
A13: 100.2.1.2.1 | B13: выпущенных до 1 марта 2013 года | C13: 0
... A164: 203 | B164: Дополнительный капитал, итого | C164: 14267208

Sheet Ф_123_2019
A1: Номер строки | B1: Наименование показателя | C1: 2019
A2: 000 | B2: Собственные средства (капитал), итого, в том числе: | C2: 78209997
A3: 100 | B3: Источники базового капитала: | C3: 65414843
A4: 100.1 | B4: Уставный капитал кредитной организации: | C4: 48011741
A5: 100.1.1 | B5: сформированный обыкновенными акциями | C5: 48011741
A6: 100.1.2 | B6: сформированный привилегированными акциями, в том числе: | C6: 0
A7: 100.1.2.1 | B7: выпущенными до 1 марта 2013 года | C7: 0
A8: 100.1.3 | B8: сформированный долями | C8: 0
A9: 100.2 | B9: Эмиссионный доход: | C9: 0
A10: 100.2.1 | B10: кредитной организации в организационно-правовой форме акционерного общества, всего, в том числе: | C10: 0
A11: 100.2.1.1 | B11: сформированный при размещении обыкновенных акций | C11: 0
A12: 100.2.1.2 | B12: сформированный при размещении привилегированных акций, в том числе: | C12: 0
A13: 100.2.1.2.1 | B13: выпущенных до 1 марта 2013 года | C13: 0
... A164: 203 | B164: Дополнительный капитал, итого | C164: 16353400

Sheet Ф_123_2018
A1: Номер строки | B1: Наименование показателя | C1: 2018
A2: 000 | B2: Собственные средства (капитал), итого, в том числе: | C2: 79008228
A3: 100 | B3: Источники базового капитала: | C3: 58419021
A4: 100.1 | B4: Уставный капитал кредитной организации: | C4: 48011741
A5: 100.1.1 | B5: сформированный обыкновенными акциями | C5: 48011741
A6: 100.1.2 | B6: сформированный привилегированными акциями | C6: 0
A7: 100.1.3 | B7: сформированный долями | C7: 0
A8: 100.2 | B8: Эмиссионный доход: | C8: 0
A9: 100.2.1 | B9: кредитной организации в организационно-правовой форме акционерного общества, всего, в том числе: | C9: 0
A10: 100.2.1.1 | B10: сформированный при размещении обыкновенных акций | C10: 0
A11: 100.2.1.2 | B11: сформированный при размещении привилегированных акций | C11: 0
A12: 100.2.2 | B12: кредитной организации в организационно-правовой форме общества с ограниченной ответственностью | C12: 0
A13: 100.3 | B13: Часть резервного фонда кредитной организации, сформированная за счет прибыли предшествующих лет | C13: 72364
... A101: 104.6 | B101: Средства, поступившие в оплату акций кредитной организации, включаемых в состав добавочного капитала, в случае, если основное или дочернее общество кредитной организации или любое дочернее общество основного общества кредитной организации предоставило владельцу акций (долей) обязательство, связанное с владением акциями (долями) кредитной организации | C101: 0
A102: 104.7 | B102: Показатели, определенные в соответствии с пунктом 2 приложения к Положению Банка России № 395-П, всего, в том числе:
A103: 104.7.1 | B103: нематериальные активы
A104: 104.7.2 | B104: собственные акции (доли) акционеров (участников), приобретенные (выкупленные) кредитной организацией у акционеров (участников)
A105: 104.7.3 | B105: вложения кредитной организации в акции (доли) дочерних и зависимых финансовых организаций и уставный капитал кредитных организаций - резидентов
A106: 104.7.4 | B106: уставный капитал (его часть) и иные источники собственных средств (эмиссионный доход, прибыль, резервный фонд) (их часть), для формирования которых инвесторами (акционерами, участниками и другими лицами, участвующими в формировании источников собственных средств кредитной организации) использованы ненадлежащие активы
A107: 104.7.5 | B107: отрицательная величина дополнительного капитала
A108: 105 | B108: Добавочный капитал, итого | C108: 0
A109: 106 | B109: Основной капитал, итого | C109: 57073901
A110: 200 | B110: Источники дополнительного капитала: | C110: 21953077
A111: 200.1 | B111: Уставный капитал кредитной организации в организационно-правовой форме акционерного общества, сформированный в результате выпуска и размещения привилегированных акций, всего, в том числе: | C111: 0
A112: 200.1.1 | B112: уставный капитал кредитной организации в организационно-правовой форме акционерного общества, сформированный в результате выпуска и размещения привилегированных акций, проведенных до 1 марта 2013 года | C112: 0
A113: 200.1.2 | B113: уставный капитал кредитной организации в организационно-правовой форме акционерного общества, сформированный в результате выпуска и размещения привилегированных акций, проведенных после 1 марта 2013 года | C113: 0
A114: 200.2 | B114: Часть уставного капитала кредитной организации, сформированного за счет капитализации прироста стоимости основных средств при переоценке до выбытия основных средств | C114: 3655
A115: 200.3 | B115: Эмиссионный доход кредитной организации в организационно-правовой форме акционерного общества | C115: 0
A116: 200.4 | B116: Резервный фонд кредитной организации в части, сформированной за счет отчислений из прибыли текущего года | C116: 0
A117: 200.5 | B117: Прибыль текущего года (ее часть), не подтвержденная аудиторской организацией, всего, в том числе: | C117: 5904976
A118: 200.5.1 | B118: величина резерва (резервов), фактически недосозданного кредитной организацией по сравнению с величиной, требуемой в соответствии с нормативными актами Банка России, всего, в том числе в соответствии: | C118: 0
A119: 200.5.1.1 | B119: с Положением Банка России № 590-П | C119: 0
... A156: 201.6 | B156: Промежуточный итог | C156: 79008228
A157: 201.7 | B157: Показатели, определенные в соответствии с пунктами 3-5 приложения к Положению Банка России № 395-П, всего, в том числе:
A158: 201.7.1 | B158: источники (часть источников) дополнительного капитала (уставного капитала, нераспределенной прибыли, резервного фонда, субординированного кредита), для формирования которых инвесторами использованы ненадлежащие активы
A159: 201.7.2 | B159: просроченная дебиторская задолженность длительностью свыше 30 календарных дней, учитываемая на балансовых счетах
A160: 201.7.3 | B160: субординированные кредиты (депозиты, займы, облигационные займы), в том числе субординированные займы с дополнительными условиями, предоставленные кредитным организациям - резидентам
A161: 201.7.4 | B161: величина превышения совокупной суммы кредитов, банковских гарантий и поручительств, предоставленных кредитной организацией участникам (акционерам) и инсайдерам, над ее максимальным размером, предусмотренным федеральными законами и нормативными актами Банка России
A162: 201.7.5 | B162: вложения, превышающие сумму источников основного и дополнительного капитала, в приобретение основных средств (в том числе земли), сооружение (строительство) и создание (изготовление) основных средств, в недвижимость, временно неиспользуемую в основной деятельности, в сооружение (строительство) объектов недвижимости, временно неиспользуемой в основной деятельности, долгосрочные активы, предназначенные для продажи, а также запасы (за исключением изданий)
A163: 201.7.5.1 | B163: справочно: совокупная сумма вложений в активы, указанные в подпункте 5.2 пункта 5 приложения к Положению Банка России № 395-П
A164: 201.7.6 | B164: разница между действительной стоимостью доли, причитающейся вышедшим из общества участникам, и стоимостью, по которой доля была реализована другому участнику
A165: 202 | B165: Показатели, определенные в соответствии с пунктом 4 Положения Банка России № 395-П: | C165: 0
A166: 202.1 | B166: Просроченная дебиторская задолженность длительностью свыше 30 календарных дней | C166: 0
A167: 202.2 | B167: Величина превышения совокупной суммы кредитов, банковских гарантий и поручительств, предоставленных кредитной организацией своим участникам (акционерам) и инсайдерам, над ее максимальным размером, предусмотренным федеральными законами и нормативными актами Банка России | C167: 0
A168: 202.3 | B168: Вложения, превышающие сумму источников основного и дополнительного капитала, всего, в том числе: | C168: 0
A169: 202.3.1 | B169: в приобретение (аренду) основных средств (в том числе земли), сооружение (строительство) и создание (изготовление) основных средств, в недвижимость, временно неиспользуемую в основной деятельности, в сооружение (строительство) объектов недвижимости, временно неиспользуемой в основной деятельности, долгосрочные активы, предназначенные для продажи, а также запасы (за исключением изданий) | C169: 0
A170: 202.3.2 | B170: отчужденные при осуществлении операций, совершаемых на возвратной основе без прекращения признания | C170: 0
A171: 202.3.3 | B171: находящиеся под управлением управляющих компаний | C171: 0
A172: 202.3.4 | B172: справочно: совокупная сумма вложений в активы, указанные в подпункте 4.2.2 пункта 4 Положения Банка России № 395-П | C172: 11620551
A173: 202.4 | B173: Разница между действительной стоимостью доли, причитающейся вышедшим из общества участникам, и стоимостью, по которой доля была реализована другому участнику | C173: 0
A174: 203 | B174: Дополнительный капитал, итого | C174: 21934327

Sheet Ф_123_2017
A1: Номер строки | B1: Наименование показателя | C1: 2017
A2: 000 | B2: Собственные средства (капитал), итого, в том числе: | C2: 78930785
A3: 100 | B3: Источники базового капитала: | C3: 57403326
A4: 100.1 | B4: Уставный капитал кредитной организации: | C4: 48011741
A5: 100.1.1 | B5: сформированный обыкновенными акциями | C5: 48011741
A6: 100.1.2 | B6: сформированный привилегированными акциями | C6: 0
A7: 100.1.3 | B7: сформированный долями | C7: 0
A8: 100.2 | B8: Эмиссионный доход: | C8: 0
A9: 100.2.1 | B9: кредитной организации в организационно-правовой форме акционерного общества, всего, в том числе: | C9: 0
A10: 100.2.1.1 | B10: сформированный при размещении обыкновенных акций | C10: 0
A11: 100.2.1.2 | B11: сформированный при размещении привилегированных акций | C11: 0
A12: 100.2.2 | B12: кредитной организации в организационно-правовой форме общества с ограниченной ответственностью | C12: 0
A13: 100.3 | B13: Часть резервного фонда кредитной организации, сформированная за счет прибыли предшествующих лет | C13: 32534
... A174: 203 | B174: Дополнительный капитал, итого | C174: 22431435

Sheet Ф_123_2016
A1: Номер строки | B1: Наименование показателя | C1: 2016
A2: 000 | B2: Собственные средства (капитал), итого, в том числе: | C2: 71645291
A3: 100 | B3: Источники базового капитала: | C3: 42726808
A4: 100.1 | B4: Уставный капитал кредитной организации: | C4: 38011741
A5: 100.1.1 | B5: сформированный обыкновенными акциями | C5: 38011741
A6: 100.1.2 | B6: сформированный привилегированными акциями | C6: 0
A7: 100.1.3 | B7: сформированный долями | C7: 0
A8: 100.2 | B8: Эмиссионный доход: | C8: 0
A9: 100.2.1 | B9: кредитной организации в организационно-правовой форме акционерного общества, всего, в том числе: | C9: 0
A10: 100.2.1.1 | B10: сформированный при размещении обыкновенных акций | C10: 0
A11: 100.2.1.2 | B11: сформированный при размещении привилегированных акций | C11: 0
A12: 100.2.2 | B12: кредитной организации в организационно-правовой форме общества с ограниченной ответственностью | C12: 0
A13: 100.3 | B13: Часть резервного фонда кредитной организации, сформированная за счет прибыли предшествующих лет | C13: 0
... A174: 203 | B174: Дополнительный капитал, итого | C174: 30278861

Sheet Ф_123_2015
A1: Номер строки | B1: Наименование показателя | C1: 2015
A2: 000 | B2: Собственные средства (капитал), итого, в том числе: | C2: 58559338
A3: 100 | B3: Источники базового капитала:
A4: 100.1 | B4: Уставный капитал кредитной организации: | C4: 38011741
A5: 100.1.1 | B5: сформированный обыкновенными акциями | C5: 38011741
A6: 100.1.2 | B6: сформированный привилегированными акциями | C6: 0
A7: 100.1.3 | B7: сформированный долями | C7: 0
A8: 100.2 | B8: Эмиссионный доход: | C8: 0
A9: 100.2.1 | B9: кредитной организации в организационно-правовой форме акционерного общества, всего, в том числе: | C9: 0
A10: 100.2.1.1 | B10: сформированный при размещении обыкновенных акций | C10: 0
A11: 100.2.1.2 | B11: сформированный при размещении привилегированных акций | C11: 0
A12: 100.2.2 | B12: кредитной организации в организационно-правовой форме общества с ограниченной ответственностью | C12: 0
A13: 100.3 | B13: Часть резервного фонда кредитной организации, сформированная за счет прибыли предшествующих лет | C13: 2401789
A14: 100.4 | B14: Часть резервного фонда кредитной организации, сформированная за счет прибыли текущего года | C14: 0
A15: 100.5 | B15: Прибыль текущего года в части, подтвержденной аудиторской организацией, всего, в том числе: | C15: 0
... A35: 100.7 | B35: Сумма источников базового капитала, итого | C35: 46390233
A36: 101 | B36: Показатели, уменьшающие сумму источников базового капитала:
A37: 101.1 | B37: Нематериальные активы | C37: 10518
A38: 101.2 | B38: Сумма налога на прибыль, подлежащая возмещению в будущих отчетных периодах в отношении перенесенных на будущее убытков, учитываемых при расчете налога на прибыль | C38: 175672
A39: 101.3 | B39: Сумма налога на прибыль, подлежащая возмещению в будущих отчетных периодах в отношении вычитаемых временных разниц | C39: 0
A40: 101.4 | B40: Вложения в собственные обыкновенные акции и привилегированные акции, всего, в том числе: | C40: 0
A41: 101.4.1 | B41: косвенные (через третьих лиц) вложения за счет денежных средств (в том числе за счет ссуды) и (или) иного имущества, предоставленного самой кредитной организацией, и (или) имущества, предоставленного третьими лицами, в случае если кредитная организация прямо или косвенно (через третьих лиц) приняла на себя риски, возникшие в связи с предоставлением указанного имущества | C41: 0
A42: 101.4.2 | B42: вложения в паи паевых инвестиционных фондов | C42: 0
A43: 101.4.3 | B43: иные вложения в источники собственных средств (капитала) | C43: 0
A44: 101.5 | B44: Вложения в доли участников, а также перешедшие к кредитной организации доли участников, всего, в том числе: | C44: 0
A45: 101.5.1 | B45: перешедшие к кредитной организации доли участников, подавших заявление о выходе из состава участников кредитной организации в организационно-правовой форме общества с ограниченной (или дополнительной) ответственностью в соответствии со статьей 26 Федерального закона N 14-ФЗ | C45: 0
A46: 101.5.2 | B46: вложения в доли участников | C46: 0
A47: 101.5.3 | B47: вложения в паи паевых инвестиционных фондов | C47: 0
A48: 101.6 | B48: Доли участников, приобретенные третьими лицами | C48: 0
... A77: 101.14 | B77: Сумма показателей, уменьшающих сумму источников базового капитала, итого | C77: 11527468
A78: 101.14.3 | B78: покрытия возможных потерь в результате ухудшения финансового положения центрального контрагента вследствие уменьшения его доходов или увеличения расходов, не связанных с неисполнением обязательств участниками клиринга
A79: 102 | B79: Базовый капитал, итого | C79: 34862765
A80: 103 | B80: Источники добавочного капитала:
A81: 103.1 | B81: Уставный капитал кредитной организации в организационно-правовой форме акционерного общества, сформированный в результате выпуска и размещения привилегированных акций, всего, в том числе: | C81: 0
A82: 103.1.1 | B82: привилегированные акции, выпущенные в соответствии с Федеральным законом N 181-ФЗ | C82: 0
A83: 103.2 | B83: Эмиссионный доход | C83: 0
A84: 103.3 | B84: Субординированный заем с дополнительными условиями | C84: 0
A85: 103.4 | B85: Субординированный кредит (депозит, заем, облигационный заем) без ограничения срока привлечения, всего, в том числе: | C85: 0
A86: 103.4.1 | B86: субординированный кредит (депозит, заем, облигационный заем), привлеченный в соответствии с правом иностранного государства | C86: 0
A87: 103.4.2 | B87: субординированный кредит (депозит, заем), привлеченный не менее чем на 50 лет | C87: 0
A88: 103.5 | B88: Сумма источников добавочного капитала, итого | C88: 0
A89: 104 | B89: Показатели, уменьшающие сумму источников добавочного капитала:
A90: 104.1 | B90: Вложения в собственные привилегированные акции, всего, в том числе: | C90: 0
A91: 104.1.1 | B91: косвенные (через третьих лиц) вложения за счет денежных средств (в том числе за счет ссуды) и (или) иного имущества, предоставленного самой кредитной организацией, и (или) имущества, предоставленного третьими лицами, в случае если кредитная организация прямо или косвенно (через третьих лиц) приняла на себя риски, возникшие в связи с предоставлением указанного имущества | C91: 0
A92: 104.1.2 | B92: вложения в паи паевых инвестиционных фондов | C92: 0
A93: 104.1.3 | B93: иные вложения в источники собственных средств (капитала) | C93: 0
A94: 104.2 | B94: Вложения кредитной организации в акции финансовых организаций, всего, в том числе: | C94: 0
A95: 104.2.1 | B95: несущественные вложения кредитной организации в акции финансовых организаций | C95: 0
A96: 104.2.2 | B96: существенные вложения кредитной организации в акции финансовых организаций | C96: 0
A97: 104.3 | B97: Субординированные кредиты (депозиты, займы, облигационные займы), предоставленные финансовым организациям - резидентам, а также финансовым организациям - нерезидентам, всего, в том числе: | C97: 0
A98: 104.3.1 | B98: несущественные субординированные кредиты (депозиты, займы, облигационные займы), всего, в том числе: | C98: 0
A99: 104.3.1.1 | B99: предоставленные финансовым организациям - нерезидентам | C99: 0
A100: 104.3.2 | B100: существенные субординированные кредиты (депозиты, займы, облигационные займы), всего, в том числе: | C100: 0
A101: 104.3.2.1 | B101: предоставленные финансовым организациям - нерезидентам | C101: 0
... A113: 106 | B113: Основной капитал, итого | C113: 34862765
A114: 200 | B114: Источники дополнительного капитала:
A115: 200.1 | B115: Уставный капитал кредитной организации в организационно-правовой форме акционерного общества, сформированный в результате выпуска и размещения привилегированных акций, всего, в том числе: | C115: 0
A116: 200.1.1 | B116: уставный капитал кредитной организации в организационно-правовой форме акционерного общества, сформированный в результате выпуска и размещения привилегированных акций, проведенных до 1 марта 2013 года | C116: 0
A117: 200.1.2 | B117: уставный капитал кредитной организации в организационно-правовой форме акционерного общества, сформированный в результате выпуска и размещения привилегированных акций, проведенных после 1 марта 2013 года | C117: 0
A118: 200.2 | B118: Часть уставного капитала кредитной организации, сформированного за счет капитализации прироста стоимости имущества при переоценке до выбытия имущества | C118: 3655
A119: 200.3 | B119: Эмиссионный доход кредитной организации в организационно-правовой форме акционерного общества | C119: 0
A120: 200.4 | B120: Резервный фонд кредитной организации в части, сформированной за счет отчислений из прибыли текущего года | C120: 0
A121: 200.5 | B121: Прибыль текущего года (ее часть), не подтвержденная аудиторской организацией, всего, в том числе: | C121: 0
A122: 200.5.1 | B122: финансовый результат от операций с ПФИ: | C122: 0
A123: 200.5.1.1 | B123: реализованный | C123: 0
A124: 200.5.1.2 | B124: нереализованный | C124: 0
A125: 200.5.2 | B125: величина резерва (резервов), фактически недосозданного кредитной организацией по сравнению с величиной, требуемой в соответствии с нормативными актами Банка России, всего, в том числе в соответствии: | C125: 0
A126: 200.5.2.1 | B126: с Положением Банка России N 254-П | C126: 0
... A145: 200.9 | B145: Сумма источников дополнительного капитала, итого | C145: 23843169
A146: 201 | B146: Показатели, уменьшающие сумму источников дополнительного капитала:
A147: 201.1 | B147: Вложения в собственные привилегированные акции, всего, в том числе: | C147: 0
A148: 201.1.1 | B148: косвенные (через третьих лиц) вложения за счет денежных средств (имущества), предоставленного самой кредитной организацией, и (или) имущества, предоставленного другими лицами, в случае, если кредитная организация прямо или косвенно (через третьих лиц) приняла на себя риски, возникшие в связи с предоставлением указанного имущества | C148: 0
A149: 201.1.2 | B149: вложения в паи паевых инвестиционных фондов | C149: 0
A150: 201.1.3 | B150: иные вложения в источники собственных средств (капитала) | C150: 0
A151: 201.2 | B151: Вложения кредитной организации в акции финансовых организаций, всего, в том числе: | C151: 0
A152: 201.2.1 | B152: несущественные вложения кредитной организации в акции финансовых организаций | C152: 0
A153: 201.2.2 | B153: существенные вложения кредитной организации в акции финансовых организаций | C153: 0
A154: 201.3 | B154: Субординированные кредиты (депозиты, займы, облигационные займы), в том числе субординированные займы с дополнительными условиями, предоставленные финансовым организациям - резидентам, а также финансовым организациям - нерезидентам, всего,в том числе: | C154: 58638
A155: 201.3.1 | B155: несущественные субординированные кредиты (депозиты, займы, облигационные займы), всего, в том числе: | C155: 0
A156: 201.3.1.1 | B156: предоставленные финансовым организациям - нерезидентам | C156: 0
A157: 201.3.2 | B157: существенные субординированные кредиты (депозиты, займы, облигационные займы), всего, в том числе: | C157: 58638
A158: 201.3.2.1 | B158: предоставленные финансовым организациям - нерезидентам | C158: 0
... A169: 201.8 | B169: Сумма показателей, уменьшающих сумму источников дополнительного капитала, итого | C169: 146596
A170: 202 | B170: Показатели, определенные в соответствии с пунктом 4 Положения Банка России N 395-П:
A171: 202.1 | B171: Просроченная дебиторская задолженность длительностью свыше 30 календарных дней | C171: 0
A172: 202.2 | B172: Величина превышения совокупной суммы кредитов, банковских гарантий и поручительств, предоставленных кредитной организацией своим участникам (акционерам) и инсайдерам, над ее максимальным размером, предусмотренным федеральными законами и нормативными актами Банка России | C172: 0
A173: 202.3 | B173: Превышающие сумму источников основного и дополнительного капитала вложения, в том числе: | C173: 0
A174: 202.3.1 | B174: в сооружение (строительство), создание (изготовление) и приобретение (аренду) основных средств, стоимость основных средств, а также материальных запасов | C174: 0
A175: 202.3.2 | B175: в паи паевых инвестиционных фондов недвижимости | C175: 0
A176: 202.3.3 | B176: в активы, переданные в доверительное управление | C176: 0
A177: 202.4 | B177: Разница между действительной стоимостью доли, причитающейся вышедшим из общества участникам, и стоимостью, по которой доля была реализована другому участнику | C177: 0
A178: 202.5 | B178: Сумма показателей, определенных в соответствии с пунктом 4 Положения Банка России N 395-П, итого | C178: 0
A179: 203 | B179: Дополнительный капитал, итого | C179: 23696573

Sheet Ф_807_2020-2015
A1: Номер строки | B1: Наименование статьи | C1: 2015 | D1: 2016 | E1: 2017 | F1: 2018 | G1: 2019 | H1: 2020
A2: 1 | B2: Процентные доходы, всего, в том числе: | C2: 41046894 | D2: 39406966 | E2: 32277374 | F2: 32696102 | G2: 34890129 | H2: 35064279
A3: 1.1 | B3: от размещения средств в кредитных организациях | C3: 446840 | D3: 1429268 | E3: 2290198 | F3: 5236226 | G3: 8626417 | H3: 4687320
A4: 1.2 | B4: от ссуд, предоставленных клиентам, не являющимся кредитными организациями | C4: 32143133 | D4: 31803404 | E4: 23222286 | F4: 20227846 | G4: 18769588 | H4: 19162845
A5: 1.3 | B5: от оказания услуг по финансовой аренде (лизингу) | C5: 0 | D5: 0
A6: 1.4 | B6: от вложений в ценные бумаги | C6: 8456921 | D6: 6174294 | E6: 6764890 | F6: 7232030 | G6: 7494124 | H6: 11214114
A7: 2 | B7: Процентные расходы, всего, в том числе: | C7: 40681507 | D7: 28438041 | E7: 23507935 | F7: 21830036 | G7: 23983878 | H7: 21867589
A8: 2.1 | B8: по привлеченным средствам кредитных организаций | C8: 4235828 | D8: 1713221 | E8: 352116 | F8: 537340 | G8: 1127506 | H8: 501761
A9: 2.2 | B9: по привлеченным средствам клиентов, не являющихся кредитными организациями | C9: 27953338 | D9: 22371151 | E9: 21251521 | F9: 21008637 | G9: 22801814 | H9: 21304551
A10: 2.3 | B10: по выпущенным ценным бумагам | C10: 8492341 | D10: 4353669 | E10: 1904298 | F10: 284059 | G10: 54558 | H10: 61277
A11: 3 | B11: Чистые процентные доходы (отрицательная процентная маржа) | C11: 365387 | D11: 10968925 | E11: 8769439 | F11: 10866066 | G11: 10906251 | H11: 13196690
A12: 4 | B12: Изменение резерва на возможные потери и оценочного резерва под ожидаемые кредитные убытки по ссудам, ссудной и приравненной к ней задолженности, средствам, размещенным на корреспондентских счетах, а также начисленным процентным доходам, всего, в том числе: | C12: -5496591 | D12: -4442136 | E12: -7370259 | F12: -13131603 | G12: -189684 | H12: -15941611
A13: 4.1 | B13: изменение резерва на возможные потери и оценочного резерва под ожидаемые кредитные убытки по начисленным процентным доходам | C13: -151378 | D13: -356879 | E13: -1256600 | F13: -829479 | G13: -1290151 | H13: -1979090
A14: 5 | B14: Чистые процентные доходы (отрицательная процентная маржа) после создания резерва на возможные потери | C14: -5131204 | D14: 6526789 | E14: 1399180 | F14: -2265537 | G14: 10716567 | H14: -2744921
A15: 6 | B15: Чистые доходы от операций с финансовыми активами, оцениваемыми по справедливой стоимости через прибыль или убыток | C15: 3540738 | D15: -690978 | E15: -1688868 | F15: -921174 | G15: 6616841 | H15: -27294511
A16: 7 | B16: Чистые доходы от операций с финансовыми обязательствами, оцениваемыми по справедливой стоимости через прибыль или убыток | C16: -714496 | D16: -124714 | F16: -470461 | G16: -1378185 | H16: -8797
A17: 8 | B17: Чистые доходы от операций с ценными бумагами, оцениваемыми по справедливой стоимости через прочий совокупный доход | C17: 4209108 | D17: 5120056 | E17: 16433696 | F17: 15638105 | G17: 707685 | H17: 381225
A18: 8а | B18: Чистые доходы от операций с ценными бумагами, имеющимися в наличии для продажи
A19: 9 | B19: Чистые доходы от операций с ценными бумагами, оцениваемым по амортизированной стоимости | C19: 48466 | D19: 11422 | E19: -10316 | F19: -18390 | G19: 873078 | H19: 389668
A20: 10 | B20: Чистые доходы от операций с иностранной валютой | C20: 1020185 | D20: -38430 | E20: -236776 | F20: 73534 | G20: 393398 | H20: 7212275
A21: 11 | B21: Чистые доходы от переоценки иностранной валюты | C21: -7419393 | D21: 2603288 | E21: 2015778 | F21: 1619574 | G21: -4663411 | H21: 23020743
A22: 9а | B22: Чистые доходы от операций с ценными бумагами, удерживаемыми до погашения
A23: 12 | B23: Чистые доходы от операций с драгоценными металлами | C23: 69064 | D23: -265726 | E23: 144770 | F23: 382401 | G23: 51630 | H23: 209689
A24: 13 | B24: Доходы от участия в капитале других юридических лиц | C24: 238935 | D24: 1318441 | E24: 3359363 | F24: 1648614 | G24: 2590154 | H24: 1262634
A25: 14 | B25: Комиссионные доходы | C25: 2703650 | D25: 3665904 | E25: 4469501 | F25: 5580882 | G25: 6994739 | H25: 7918155
A26: 15 | B26: Комиссионные расходы | C26: 661724 | D26: 988175 | E26: 1354409 | F26: 1739783 | G26: 2329429 | H26: 3039552
A27: 16 | B27: Изменение резерва на возможные потери и оценочного резерва под ожидаемые кредитные убытки по ценным бумагам, оцениваемым по справедливой стоимости через прочий совокупный доход | C27: -362636 | D27: -152074 | E27: 24923 | F27: -500274 | G27: -380298 | H27: -18325
A28: 17 | B28: Изменение резерва на возможные потери и оценочного резерва под ожидаемые кредитные убытки по ценным бумагам, оцениваемым по амортизированной стоимости | C28: -401003 | D28: 65337 | E28: -115708 | F28: -62725 | G28: -224156 | H28: 79958
A29: 18 | B29: Изменение резерва по прочим потерям | C29: 4753065 | D29: -4811143 | E29: 538506 | F29: 189472 | G29: -642104 | H29: -1067598
A30: 19 | B30: Прочие операционные доходы | C30: 16016407 | D30: 3173766 | E30: 1347032 | F30: 1578875 | G30: 3430955 | H30: 17993070
A31: 20 | B31: Чистые доходы (расходы) | C31: 17909162 | D31: 15413763 | E31: 26326672 | F31: 20733113 | G31: 22757464 | H31: 24293713
A32: 16а | B32: Изменение резерва на возможные потери по ценным бумагам, имеющимся в наличии для продажи
A33: 21 | B33: Операционные расходы | C33: 26707082 | D33: 14559974 | E33: 25075105 | F33: 16853565 | G33: 15033435 | H33: 17938236
A34: 22 | B34: Прибыль (убыток) до налогообложения | C34: -8797920 | D34: 853789 | E34: 1251567 | F34: 3879548 | G34: 7724029 | H34: 6355477
A35: 23 | B35: Возмещение (расход) по налогам | C35: 363183 | D35: 203107 | E35: 454977 | F35: 1168933 | G35: 1471208 | H35: 1998039
A36: 17а | B36: Изменение резерва на возможные потери по ценным бумагам, удерживаемым до погашения
A37: 24 | B37: Прибыль (убыток) от продолжающейся деятельности | C37: -9161103 | D37: 866108 | E37: 881913 | F37: 2727813 | G37: 6247687 | H37: 4367673
A38: 25 | B38: Прибыль (убыток) от прекращенной деятельности | C38: 0 | D38: -215426 | E38: -85323 | F38: -17198 | G38: 5134 | H38: -10235
A39: 26 | B39: Прибыль (убыток) за отчетный период | C39: -9161103 | D39: 650682 | E39: 796590 | F39: 2710615 | G39: 6252821 | H39: 4357438

Sheet Ф_807_2023-2021
A1: Номер строки | B1: Наименование статьи | C1: 2021 | D1: 2022 | E1: 2023 | F1: 2024
A2: 1 | B2: Процентные доходы, всего, в том числе: | C2: 34478939 | D2: 52116860 | E2: 70353320 | F2: 119578613
A3: 1.1 | B3: от размещения средств в кредитных организациях | C3: 3466338 | D3: 9372191 | E3: 20637092 | F3: 35677313
A4: 1.2 | B4: от ссуд, предоставленных клиентам, не являющимся кредитными организациями | C4: 19636002 | D4: 31379804 | E4: 40192349 | F4: 61806668
A5: 1.3 | B5: от вложений в ценные бумаги | C5: 11376599 | D5: 11364865 | E5: 9523879 | F5: 22094632
A6: 2 | B6: Процентные расходы, всего, в том числе: | C6: 20186165 | D6: 37110655 | E6: 39533603 | F6: 75149106
A7: 2.1 | B7: по привлеченным средствам кредитных организаций | C7: 1002505 | D7: 2519571 | E7: 3072135 | F7: 15254448
A8: 2.2 | B8: по привлеченным средствам клиентов, не являющихся кредитными организациями | C8: 19165164 | D8: 34590034 | E8: 36453818 | F8: 59891245
A9: 2.3 | B9: по выпущенным ценным бумагам | C9: 18496 | D9: 1050 | E9: 7650 | F9: 3413
A10: 3 | B10: Чистые процентные доходы (отрицательная процентная маржа) | C10: 14292774 | D10: 15006205 | E10: 30819717 | F10: 44429507
A11: 4 | B11: Изменение резерва на возможные потери и оценочного резерва под ожидаемые кредитные убытки по ссудам, ссудной и приравненной к ней задолженности, средствам, размещенным на корреспондентских счетах, а также начисленным процентным доходам, всего, в том числе: | C11: -417331 | D11: -2156923 | E11: -9125230 | F11: -2780409
A12: 4.1 | B12: изменение резерва на возможные потери и оценочного резерва под ожидаемые кредитные убытки по начисленным процентным доходам | C12: -325360 | D12: -367969 | E12: -1045029 | F12: -610699
A13: 5 | B13: Чистые процентные доходы (отрицательная процентная маржа) после создания резерва на возможные потери | C13: 13875443 | D13: 12849282 | E13: 21694487 | F13: 41649098
A14: 6 | B14: Чистые доходы от операций с финансовыми активами, оцениваемыми по справедливой стоимости через прибыль или убыток | C14: 6595963 | D14: 1143110 | E14: -3475928 | F14: -2846032
A15: 7 | B15: Чистые доходы от операций с финансовыми обязательствами, оцениваемыми по справедливой стоимости через прибыль или убыток | E15: -157340 | F15: -801779
A16: 8 | B16: Чистые доходы от операций с ценными бумагами, оцениваемыми по справедливой стоимости через прочий совокупный доход | C16: -734489 | D16: -158605 | E16: -745630 | F16: -1802559
A17: 9 | B17: Чистые доходы от операций с ценными бумагами, оцениваемым по амортизированной стоимости | C17: 17404 | D17: 74361 | E17: -761082 | F17: 3548645
A18: 10 | B18: Чистые доходы от операций с иностранной валютой
A19: 11 | B19: Чистые доходы от переоценки иностранной валюты
A20: 12 | B20: Чистые доходы от операций с драгоценными металлами | C20: -40143 | D20: -225665 | E20: 609291 | F20: 1146075
A21: 13 | B21: Доходы от участия в капитале других юридических лиц
A22: 14 | B22: Комиссионные доходы | C22: 8833704 | D22: 9326419 | E22: 11177948 | F22: 11764283
A23: 15 | B23: Комиссионные расходы | C23: 2293031 | D23: 2430764 | E23: 3423457 | F23: 4550902
A24: 16 | B24: Изменение резерва на возможные потери и оценочного резерва под ожидаемые кредитные убытки по ценным бумагам, оцениваемым по справедливой стоимости через прочий совокупный доход | C24: -3547 | D24: -450470 | E24: -316889 | F24: -756964
A25: 17 | B25: Изменение резерва на возможные потери и оценочного резерва под ожидаемые кредитные убытки по ценным бумагам, оцениваемым по амортизированной стоимости | C25: -129113 | D25: 152689 | E25: -3761576 | F25: -121754
A26: 18 | B26: Изменение резерва по прочим потерям | C26: -575651 | D26: -5820426 | E26: -17531841 | F26: -9954768
A27: 19 | B27: Прочие операционные доходы | C27: 5741051 | D27: 7143324 | E27: 10015694 | F27: 877988
A28: 20 | B28: Чистые доходы (расходы) | C28: 28996613 | D28: 30578406 | E28: 36237410 | F28: 48060940
A29: 21 | B29: Операционные расходы | C29: 21594560 | D29: 28587486 | E29: 26956296 | F29: 28723624
A30: 22 | B30: Прибыль (убыток) до налогообложения | C30: 7402053 | D30: 1990920 | E30: 9281114 | F30: 19337316
A31: 23 | B31: Возмещение (расход) по налогу на прибыль | C31: 1098274 | D31: 433772 | E31: 2870756 | F31: 3935762
A32: 24 | B32: Прибыль (убыток) от продолжающейся деятельности | C32: 6123774 | D32: 1456653 | E32: 6310896 | F32: 15315232
A33: 25 | B33: Прибыль (убыток) от прекращенной деятельности | C33: 180005 | D33: 100495 | E33: 99462 | F33: 86322
A34: 26 | B34: Прибыль (убыток) за отчетный период | C34: 6303779 | D34: 1557148 | E34: 6410358 | F34: 15401554
A50: =Ф_807_2023_2021[[#Headers],[Номер строки]] -> Номер строки | B50: =Ф_807_2023_2021[[#Headers],[Наименование статьи]] -> Наименование статьи | C50: =Ф_807_2023_2021[[#Headers],[2021]] -> 2021 | D50: =Ф_807_2023_2021[[#Headers],[2022]] -> 2022 | E50: =Ф_807_2023_2021[[#Headers],[2023]] -> 2023 | F50: =Ф_807_2023_2021[[#Headers],[2024]] -> 2024
A51: КОРРЕКТИРОВКА на нераскрываемые статьи отчета о ФР | C51: ='Ф_807_2023-2021'!C34-('Ф_807_2023-2021'!C13+'Ф_807_2023-2021'!C14+'Ф_807_2023-2021'!C15+'Ф_807_2023-2021'!C16+'Ф_807_2023-2021'!C17+'Ф_807_2023-2021'!C18+'Ф_807_2023-2021'!C19+'Ф_807_2023-2021'!C20+'Ф_807_2023-2021'!C21+'Ф_807_2023-2021'!C22-'Ф_807_2023-2021'!C23+'Ф_807_2023-2021'!C24+'Ф_807_2023-2021'!C25+'Ф_807_2023-2021'!C26+'Ф_807_2023-2021'!C27-'Ф_807_2023-2021'!C29-'Ф_807_2023-2021'!C31) -> -2290978 | D51: ='Ф_807_2023-2021'!D34-('Ф_807_2023-2021'!D13+'Ф_807_2023-2021'!D14+'Ф_807_2023-2021'!D15+'Ф_807_2023-2021'!D16+'Ф_807_2023-2021'!D17+'Ф_807_2023-2021'!D18+'Ф_807_2023-2021'!D19+'Ф_807_2023-2021'!D20+'Ф_807_2023-2021'!D21+'Ф_807_2023-2021'!D22-'Ф_807_2023-2021'!D23+'Ф_807_2023-2021'!D24+'Ф_807_2023-2021'!D25+'Ф_807_2023-2021'!D26+'Ф_807_2023-2021'!D27-'Ф_807_2023-2021'!D29-'Ф_807_2023-2021'!D31) -> 8975151 | E51: ='Ф_807_2023-2021'!E34-('Ф_807_2023-2021'!E13+'Ф_807_2023-2021'!E14+'Ф_807_2023-2021'!E15+'Ф_807_2023-2021'!E16+'Ф_807_2023-2021'!E17+'Ф_807_2023-2021'!E18+'Ф_807_2023-2021'!E19+'Ф_807_2023-2021'!E20+'Ф_807_2023-2021'!E21+'Ф_807_2023-2021'!E22-'Ф_807_2023-2021'!E23+'Ф_807_2023-2021'!E24+'Ф_807_2023-2021'!E25+'Ф_807_2023-2021'!E26+'Ф_807_2023-2021'!E27-'Ф_807_2023-2021'!E29-'Ф_807_2023-2021'!E31) -> 22913733 | F51: ='Ф_807_2023-2021'!F34-('Ф_807_2023-2021'!F13+'Ф_807_2023-2021'!F14+'Ф_807_2023-2021'!F15+'Ф_807_2023-2021'!F16+'Ф_807_2023-2021'!F17+'Ф_807_2023-2021'!F18+'Ф_807_2023-2021'!F19+'Ф_807_2023-2021'!F20+'Ф_807_2023-2021'!F21+'Ф_807_2023-2021'!F22-'Ф_807_2023-2021'!F23+'Ф_807_2023-2021'!F24+'Ф_807_2023-2021'!F25+'Ф_807_2023-2021'!F26+'Ф_807_2023-2021'!F27-'Ф_807_2023-2021'!F29-'Ф_807_2023-2021'!F31) -> 9909609

Sheet Ф_806_2018-2015
A1: Номер строки | B1: Наименование статьи | C1: 2015 | D1: 2016 | E1: 2017 | F1: 2018
A2: I. Активы | B2: I. Активы
A3: 1 | B3: Денежные средства | C3: 9515293 | D3: 10866168 | E3: 10371248 | F3: 9651096
A4: 2 | B4: Средства кредитных организаций в Центральном банке Российской Федерации | C4: 12223752 | D4: 12836368 | E4: 11954847 | F4: 12086758
A5: 2.1 | B5: Обязательные резервы | C5: 3675782 | D5: 4266434 | E5: 3836490 | F5: 2848617
A6: 3 | B6: Средства в кредитных организациях | C6: 7422375 | D6: 3625500 | E6: 2812293 | F6: 2884465
A7: 4 | B7: Финансовые активы, оцениваемые по справедливой стоимости через прибыль или убыток | C7: 1356097 | D7: 774422 | E7: 1061566 | F7: 151584
A8: 5 | B8: Чистая ссудная задолженность | C8: 270529573 | D8: 246715767 | E8: 224707711 | F8: 315918432
A9: 6 | B9: Чистые вложения в ценные бумаги и другие финансовые активы, имеющиеся в наличии для продажи | C9: 70845144 | D9: 112519879 | E9: 146559139 | F9: 88072946
A10: 6.1 | B10: Инвестиции в дочерние и зависимые организации | C10: 11418235 | D10: 1609029 | E10: 1614782 | F10: 1749596
A11: 7 | B11: Чистые вложения в ценные бумаги, удерживаемые до погашения | C11: 21104298 | D11: 19041393 | E11: 9250660 | F11: 37930296
A12: 8 | B12: Требование по текущему налогу на прибыль | C12: 214 | D12: 0 | F12: 920
A13: 9 | B13: Отложенный налоговый актив | C13: 591545 | D13: 0
A14: 10 | B14: Основные средства, нематериальные активы и материальные запасы | C14: 4712070 | D14: 3712388 | E14: 3890826 | F14: 4381648
A15: 11 | B15: Долгосрочные активы, предназначенные для продажи | D15: 536707 | E15: 357580 | F15: 1309806
A16: 12 | B16: Прочие активы | C16: 74372688 | D16: 31719394 | E16: 25418511 | F16: 25939543
A17: 13 | B17: Всего активов | C17: 472673049 | D17: 442347986 | E17: 436384381 | F17: 498327494
A18: II. Пассивы | B18: II. Пассивы
A19: 14 | B19: Кредиты, депозиты и прочие средства Центрального банка Российской Федерации | C19: 5540000 | D19: 0 | F19: 742061
A20: 15 | B20: Средства кредитных организаций | C20: 24872626 | D20: 9090401 | E20: 12780993 | F20: 1340666
A21: 16 | B21: Средства клиентов, не являющихся кредитными организациями | C21: 318982420 | D21: 321096467 | E21: 346024092 | F21: 402943978
A22: 16.1 | B22: Вклады (средства) физических лиц, в том числе индивидуальных предпринимателей | C22: 99624268 | D22: 107992639 | E22: 110028833 | F22: 114448382
A23: 17 | B23: Финансовые обязательства, оцениваемые по справедливой стоимости через прибыль или убыток | C23: 2222826 | D23: 0 | E23: 70481 | F23: 15833674
A24: 18 | B24: Выпущенные долговые обязательства | C24: 74379633 | D24: 50154203 | E24: 3455571 | F24: 1275982
A25: 19 | B25: Обязательство по текущему налогу на прибыль | C25: 0 | D25: 0
A26: 20 | B26: Отложенное налоговое обязательство | C26: 0 | D26: 1067049 | E26: 689686 | F26: 489478
A27: 21 | B27: Прочие обязательства | C27: 6495627 | D27: 5481430 | E27: 5494893 | F27: 6729587
A28: 22 | B28: Резервы на возможные потери по условным обязательствам кредитного характера, прочим возможным потерям и операциям с резидентами офшорных зон | C28: 1029083 | D28: 5588092 | E28: 3992419 | F28: 3492658
A29: 23 | B29: Всего обязательств | C29: 433522215 | D29: 392477642 | E29: 372508135 | F29: 432848084
A30: III. Источники собственных средств | B30: III. Источники собственных средств
A31: 24 | B31: Средства акционеров (участников) | C31: 38015396 | D31: 38015396 | E31: 48015396 | F31: 48015396
A32: 25 | B32: Собственные акции (доли), выкупленные у акционеров (участников) | C32: 0 | D32: 0
A33: 26 | B33: Эмиссионный доход | C33: 0 | D33: 0
A34: 27 | B34: Резервный фонд | C34: 2401789 | D34: 0 | E34: 32534 | F34: 72364
A35: 28 | B35: Переоценка по справедливой стоимости ценных бумаг, имеющихся в наличии для продажи, уменьшенная на отложенное налоговое обязательство (увеличенная на отложенный налоговый актив) | C35: -129118 | D35: 6183303 | E35: 9392614 | F35: 8285386
A36: 29 | B36: Переоценка основных средств и нематериальных активов, уменьшенная на отложенное налоговое обязательство | C36: 4475 | D36: 4413 | E36: 4386 | F36: 4163
A37: 30 | B37: Переоценка обязательств (требований) по выплате долгосрочных вознаграждений | C37: 0 | D37: 0
A38: 31 | B38: Переоценка инструментов хеджирования | C38: 0 | D38: 0
A39: 32 | B39: Денежные средства безвозмездного финансирования (вклады в имущество) | C39: 0 | D39: 4210837 | E39: 4210837 | F39: 4210837
A40: 33 | B40: Нераспределенная прибыль (непокрытые убытки) прошлых лет | C40: 8019395 | D40: 805713 | E40: 1423889 | F40: 2180649
A41: 34 | B41: Неиспользованная прибыль (убыток) за отчетный период | C41: -9161103 | D41: 650682 | E41: 796590 | F41: 2710615
A42: 35 | B42: Всего источников собственных средств | C42: 39150834 | D42: 49870344 | E42: 63876246 | F42: 65479410
A43: IV. Внебалансовые обязательства | B43: IV. Внебалансовые обязательства
A44: 36 | B44: Безотзывные обязательства кредитной организации | C44: 84356242 | D44: 105551441 | E44: 168695869 | F44: 250882222
A45: 37 | B45: Выданные кредитной организацией гарантии и поручительства | C45: 21026711 | D45: 28053711 | E45: 36693585 | F45: 38193257
A46: 38 | B46: Условные обязательства некредитного характера | C46: 0 | D46: 0
A62: =Ф_806_2018_2015[[#Headers],[Номер строки]] -> Номер строки | B62: =Ф_806_2018_2015[[#Headers],[Наименование статьи]] -> Наименование статьи | C62: =Ф_806_2018_2015[[#Headers],[2015]] -> 2015 | D62: =Ф_806_2018_2015[[#Headers],[2016]] -> 2016 | E62: =Ф_806_2018_2015[[#Headers],[2017]] -> 2017 | F62: =Ф_806_2018_2015[[#Headers],[2018]] -> 2018
A63: КОРРЕКТИРОВКА на нераскрываемые статьи активов | C63: ='Ф_806_2018-2015'!C17-'Ф_806_2018-2015'!C3-'Ф_806_2018-2015'!C4-'Ф_806_2018-2015'!C6-'Ф_806_2018-2015'!C7-'Ф_806_2018-2015'!C8-'Ф_806_2018-2015'!C9-'Ф_806_2018-2015'!C11-'Ф_806_2018-2015'!C12-'Ф_806_2018-2015'!C13-'Ф_806_2018-2015'!C14-'Ф_806_2018-2015'!C15-'Ф_806_2018-2015'!C16 -> 0 | D63: ='Ф_806_2018-2015'!D17-'Ф_806_2018-2015'!D3-'Ф_806_2018-2015'!D4-'Ф_806_2018-2015'!D6-'Ф_806_2018-2015'!D7-'Ф_806_2018-2015'!D8-'Ф_806_2018-2015'!D9-'Ф_806_2018-2015'!D11-'Ф_806_2018-2015'!D12-'Ф_806_2018-2015'!D13-'Ф_806_2018-2015'!D14-'Ф_806_2018-2015'!D15-'Ф_806_2018-2015'!D16 -> 0 | E63: ='Ф_806_2018-2015'!E17-'Ф_806_2018-2015'!E3-'Ф_806_2018-2015'!E4-'Ф_806_2018-2015'!E6-'Ф_806_2018-2015'!E7-'Ф_806_2018-2015'!E8-'Ф_806_2018-2015'!E9-'Ф_806_2018-2015'!E11-'Ф_806_2018-2015'!E12-'Ф_806_2018-2015'!E13-'Ф_806_2018-2015'!E14-'Ф_806_2018-2015'!E15-'Ф_806_2018-2015'!E16 -> 0 | F63: ='Ф_806_2018-2015'!F17-'Ф_806_2018-2015'!F3-'Ф_806_2018-2015'!F4-'Ф_806_2018-2015'!F6-'Ф_806_2018-2015'!F7-'Ф_806_2018-2015'!F8-'Ф_806_2018-2015'!F9-'Ф_806_2018-2015'!F11-'Ф_806_2018-2015'!F12-'Ф_806_2018-2015'!F13-'Ф_806_2018-2015'!F14-'Ф_806_2018-2015'!F15-'Ф_806_2018-2015'!F16 -> 0
A64: КОРРЕКТИРОВКА на нераскрываемые статьи обязательств | C64: ='Ф_806_2018-2015'!C29-SUM('Ф_806_2018-2015'!C19:C28)+'Ф_806_2018-2015'!C22 -> 0 | D64: ='Ф_806_2018-2015'!D29-SUM('Ф_806_2018-2015'!D19:D28)+'Ф_806_2018-2015'!D22 -> 0 | E64: ='Ф_806_2018-2015'!E29-SUM('Ф_806_2018-2015'!E19:E28)+'Ф_806_2018-2015'!E22 -> 0 | F64: ='Ф_806_2018-2015'!F29-SUM('Ф_806_2018-2015'!F19:F28)+'Ф_806_2018-2015'!F22 -> 0
A65: КОРРЕКТИРОВКА на нераскрываемые статьи собственных средств | C65: =C42-(C31-C32+SUM(C33:C41)) -> 0 | D65: ='Ф_806_2018-2015'!D42-(D31-D32+SUM(D33:D41)) -> 0 | E65: ='Ф_806_2018-2015'!E42-(E31-E32+SUM(E33:E41)) -> 0 | F65: ='Ф_806_2018-2015'!F42-(F31-F32+SUM(F33:F41)) -> 0

Sheet Ф_806_2023-2019
A1: Номер строки | B1: Наименование статьи | C1: 2019 | D1: 2020 | E1: 2021 | F1: 2022 | G1: 2023
A2: I. Активы | B2: I. Активы
A3: 1 | B3: Денежные средства | C3: 8786054 | D3: 14699337 | E3: 13125643 | F3: 12124725 | G3: 29701298
A4: 2 | B4: Средства кредитной организации в Центральном банке Российской Федерации | C4: 18630222 | D4: 17545793 | E4: 16963663 | F4: 17255953 | G4: 41660710
A5: 2.1 | B5: Обязательные резервы | C5: 3360185 | D5: 3454685 | E5: 3878169 | F5: 927450 | G5: 2047374
A6: 3 | B6: Средства в кредитных организациях | C6: 5271415 | D6: 6715428 | E6: 6830454 | F6: 83365775 | G6: 12298870
A7: 4 | B7: Финансовые активы, оцениваемые по справедливой стоимости через прибыль или убыток | C7: 3165995 | D7: 3261718 | E7: 3310084 | F7: 1081829 | G7: 847302
A8: 5 | B8: Чистая ссудная задолженность, оцениваемая по амортизированной стоимости | C8: 322491423 | D8: 334777604 | E8: 382942668 | F8: 474062674 | G8: 527651671
A9: 6 | B9: Чистые вложения в финансовые активы, оцениваемые по справедливой стоимости через прочий совокупный доход | C9: 78267457 | D9: 77441935 | E9: 70842146 | F9: 30563075 | G9: 64334445
A10: 7 | B10: Чистые вложения в ценные бумаги и иные финансовые активы, оцениваемые по амортизированной стоимости (кроме ссудной задолженности) | C10: 92865288 | D10: 105029800 | E10: 121775858 | F10: 115991855 | G10: 108480427
A11: 8 | B11: Инвестиции в дочерние и зависимые организации | C11: 1867112 | D11: 1786060
A12: 9 | B12: Требование по текущему налогу на прибыль | C12: 19509 | D12: 85088 | G12: 135112
A13: 10 | B13: Отложенный налоговый актив | C13: 708714 | D13: 1988000 | E13: 2695422 | F13: 2458409 | G13: 789697
A14: 11 | B14: Основные средства, активы в форме права пользования и нематериальные активы | C14: 5453352 | D14: 9019962 | E14: 10001922 | F14: 14379514 | G14: 16468963
A15: 12 | B15: Долгосрочные активы, предназначенные для продажи | C15: 1401161 | D15: 1138795 | E15: 492276 | F15: 755624 | G15: 506598
A16: 13 | B16: Прочие активы | C16: 22216978 | D16: 20536023
A17: 14 | B17: Всего активов | C17: 561144680 | D17: 594025543 | E17: 653574443 | F17: 811266749 | G17: 837684837
A18: II. Пассивы | B18: II. Пассивы
A19: 15 | B19: Кредиты, депозиты и прочие средства Центрального банка Российской Федерации | C19: 1523408 | D19: 6207334 | E19: 1743193 | F19: 2763779 | G19: 10717397
A20: 16 | B20: Средства клиентов, оцениваемые по амортизированной стоимости | C20: 481331669 | D20: 505595436 | E20: 564680606 | F20: 716258469 | G20: 717776447
A21: 16.1 | B21: средства кредитных организаций | C21: 4849737 | D21: 3912068 | E21: 2653423 | F21: 9780212 | G21: 56180218
A22: 16.2 | B22: средства клиентов, не являющихся кредитными организациями | C22: 476481932 | D22: 501683368 | E22: 562027183 | F22: 706478257 | G22: 661596229
A23: 16.2.1 | B23: вклады (средства) физических лиц, в том числе индивидуальных предпринимателей | C23: 124289828 | D23: 127642669 | E23: 119057672 | F23: 152421895 | G23: 152962532
A24: 17 | B24: Финансовые обязательства, оцениваемые по справедливой стоимости через прибыль или убыток | C24: 594868 | D24: 3034631 | E24: 1356231 | F24: 1453922 | G24: 7500034
A25: 17.1 | B25: вклады (средства) физических лиц, в том числе индивидуальных предпринимателей
A26: 18 | B26: Выпущенные долговые ценные бумаги | C26: 1393560 | D26: 185218 | E26: 229063 | F26: 1100576 | G26: 58896
A27: 18.1 | B27: оцениваемые по справедливой стоимости через прибыль или убыток
A28: 18.2 | B28: оцениваемые по амортизированной стоимости | C28: 1393560 | D28: 185218 | E28: 229063 | F28: 1100576 | G28: 58896
A29: 19 | B29: Обязательства по текущему налогу на прибыль
A30: 20 | B30: Отложенные налоговые обязательства | C30: 810242 | D30: 1104926 | E30: 1773576 | G30: 1579395
A31: 21 | B31: Прочие обязательства | C31: 1888793 | D31: 4073070
A32: 22 | B32: Резервы на возможные потери по условным обязательствам кредитного характера, прочим возможным потерям и операциям с резидентами офшорных зон | C32: 438661 | D32: 1097501
A33: 23 | B33: Всего обязательств | C33: 487981201 | D33: 521298116 | E33: 575377126 | F33: 734618478 | G33: 745046430
A34: III. Источники собственных средств | B34: III. Источники собственных средств
A35: 24 | B35: Средства акционеров (участников) | C35: 48015396 | D35: 48015396 | E35: 48015396 | F35: 48015396 | G35: 48015396
A36: 25 | B36: Собственные акции (доли), выкупленные у акционеров (участников)
A37: 26 | B37: Эмиссионный доход
A38: 27 | B38: Резервный фонд | C38: 207894 | D38: 520535 | E38: 738407 | F38: 1053596 | G38: 1131454
A39: 28 | B39: Переоценка по справедливой стоимости финансовых активов, оцениваемых по справедливой стоимости через прочий совокупный доход, уменьшенная на отложенное налоговое обязательство (увеличенная на отложенный налоговый актив) | C39: 6354127 | D39: 1646306 | E39: 793290 | F39: -3789500 | G39: 5595206
A40: 29 | B40: Переоценка основных средств, активов в форме права пользования и нематериальных активов, уменьшенная на отложенное налоговое обязательство | C40: 4163 | D40: 3725 | E40: 3725 | F40: 1498269 | G40: 1619662
A41: 30 | B41: Переоценка обязательств (требований) по выплате долгосрочных вознаграждений
A42: 31 | B42: Переоценка инструментов хеджирования
A43: 32 | B43: Денежные средства безвозмездного финансирования (вклады в имущество) | C43: 4210837 | D43: 4210837 | E43: 4210837 | F43: 4210837 | G43: 4210837
A44: 33 | B44: Изменение справедливой стоимости финансового обязательства, обусловленное изменением кредитного риска
A45: 34 | B45: Оценочные резервы под ожидаемые кредитные убытки | C45: 120902 | D45: 35233 | E45: 54360 | F45: 36258 | G45: 92027
A46: 35 | B46: Неиспользованная прибыль (убыток) | C46: 14250160 | D46: 18295395 | E46: 24381302 | F46: 25623415 | G46: 31973825
A47: 36 | B47: Всего источников собственных средств | C47: 73163479 | D47: 72727427 | E47: 78197317 | F47: 76648271 | G47: 92638407
A48: IV. Внебалансовые обязательства | B48: IV. Внебалансовые обязательства
A49: 37 | B49: Безотзывные обязательства кредитной организации | C49: 312913654 | D49: 515255497 | E49: 584732323 | F49: 589820020 | G49: 696809435
A50: 38 | B50: Выданные кредитной организацией гарантии и поручительства | C50: 67738342 | D50: 79537401 | E50: 120409768 | F50: 165422734 | G50: 180142323
A51: 39 | B51: Условные обязательства некредитного характера
A52: 4а | B52: Производные финансовые инструменты для целей хеджирования
A53: 17а | B53: Производные финансовые инструменты для целей хеджирования
A62: =Ф_806_2023_2019[[#Headers],[Номер строки]] -> Номер строки | B62: =Ф_806_2023_2019[[#Headers],[Наименование статьи]] -> Наименование статьи | C62: =Ф_806_2023_2019[[#Headers],[2019]] -> 2019 | D62: =Ф_806_2023_2019[[#Headers],[2020]] -> 2020 | E62: =Ф_806_2023_2019[[#Headers],[2021]] -> 2021 | F62: =Ф_806_2023_2019[[#Headers],[2022]] -> 2022 | G62: =Ф_806_2023_2019[[#Headers],[2023]] -> 2023
A63: КОРРЕКТИРОВКА на нераскрываемые статьи активов | C63: ='Ф_806_2023-2019'!C17-SUM('Ф_806_2023-2019'!C3:C16)+'Ф_806_2023-2019'!C5 -> 0 | D63: ='Ф_806_2023-2019'!D17-SUM('Ф_806_2023-2019'!D3:D16)+'Ф_806_2023-2019'!D5 -> 0 | E63: ='Ф_806_2023-2019'!E17-SUM('Ф_806_2023-2019'!E3:E16)+'Ф_806_2023-2019'!E5 -> 24594307 | F63: ='Ф_806_2023-2019'!F17-SUM('Ф_806_2023-2019'!F3:F16)+'Ф_806_2023-2019'!F5 -> 59227316 | G63: ='Ф_806_2023-2019'!G17-SUM('Ф_806_2023-2019'!G3:G16)+'Ф_806_2023-2019'!G5 -> 34809744
A64: КОРРЕКТИРОВКА на нераскрываемые статьи обязательств | C64: ='Ф_806_2023-2019'!C33-SUM('Ф_806_2023-2019'!C19:C20,'Ф_806_2023-2019'!C24,'Ф_806_2023-2019'!C26,'Ф_806_2023-2019'!C29:C32) -> 0 | D64: ='Ф_806_2023-2019'!D33-SUM('Ф_806_2023-2019'!D19:D20,'Ф_806_2023-2019'!D24,'Ф_806_2023-2019'!D26,'Ф_806_2023-2019'!D29:D32) -> 0 | E64: ='Ф_806_2023-2019'!E33-SUM('Ф_806_2023-2019'!E19:E20,'Ф_806_2023-2019'!E24,'Ф_806_2023-2019'!E26,'Ф_806_2023-2019'!E29:E32) -> 5594457 | F64: ='Ф_806_2023-2019'!F33-SUM('Ф_806_2023-2019'!F19:F20,'Ф_806_2023-2019'!F24,'Ф_806_2023-2019'!F26,'Ф_806_2023-2019'!F29:F32) -> 13041732 | G64: ='Ф_806_2023-2019'!G33-SUM('Ф_806_2023-2019'!G19:G20,'Ф_806_2023-2019'!G24,'Ф_806_2023-2019'!G26,'Ф_806_2023-2019'!G29:G32) -> 7414261
A65: КОРРЕКТИРОВКА на нераскрываемые статьи собственных средств | C65: =C47-(C35-C36+SUM(C37:C46)) -> 0 | D65: =D47-(D35-D36+SUM(D37:D46)) -> 0 | E65: =E47-(E35-E36+SUM(E37:E46)) -> 0 | F65: =F47-(F35-F36+SUM(F37:F46)) -> 0 | G65: =G47-(G35-G36+SUM(G37:G46)) -> 0

Sheet Ф_806_2024
A1: Номер строки | B1: Наименование статьи | C1: 2024 | D1: 2023
A2: I. Активы | B2: I. Активы
A3: 1 | B3: Денежные средства | C3: 20326092 | D3: 29701298
A4: 2 | B4: Средства кредитной организации в Центральном банке Российской Федерации | C4: 41078760 | D4: 41660710
A5: 2.1 | B5: обязательные резервы | C5: 2875662 | D5: 2047374
A6: 3 | B6: Средства в кредитных организациях | C6: 2803131 | D6: 12298870
A7: 4 | B7: Финансовые активы, оцениваемые по справедливой стоимости через прибыль или убыток | C7: 1148295 | D7: 847302
A8: 4а | B8: Производные финансовые инструменты для целей хеджирования
A9: 5 | B9: Чистая ссудная задолженность, оцениваемая по амортизированной стоимости | C9: 546142705 | D9: 527651671
A10: 6 | B10: Чистые вложения в финансовые активы, оцениваемые по справедливой стоимости через прочий совокупный доход | C10: 78910803 | D10: 64334445
A11: 7 | B11: Чистые вложения в ценные бумаги и иные финансовые активы, оцениваемые по амортизированной стоимости (кроме ссудной задолженности) | C11: 177249140 | D11: 108480427
A12: 8 | B12: Инвестиции в дочерние и зависимые организации
A13: 9 | B13: Требование по текущему налогу на прибыль | D13: 135112
A14: 10 | B14: Отложенный налоговый актив | D14: 789697
A15: 11 | B15: Основные средства, активы в форме права пользования и нематериальные активы | C15: 20647817 | D15: 16468963
A16: 12 | B16: Долгосрочные активы, предназначенные для продажи | C16: 463446 | D16: 506598
A17: 13 | B17: Прочие активы
A18: 14 | B18: Всего активов | C18: 931506637 | D18: 837684837
A19: II. Пассивы | B19: II. Пассивы
A20: 15 | B20: Кредиты, депозиты и прочие средства Центрального банка Российской Федерации | C20: 3443821 | D20: 10717397
A21: 16 | B21: Средства клиентов, оцениваемые по амортизированной стоимости | C21: 788548611 | D21: 717776447
A22: 16.1 | B22: средства кредитных организаций | C22: 123148633 | D22: 56180218
A23: 16.2 | B23: средства клиентов, не являющихся кредитными организациями | C23: 665399978 | D23: 661596229
A24: 16.2.1 | B24: вклады (средства) физических лиц, в том числе индивидуальных предпринимателей | C24: 148946994 | D24: 152962532
A25: 17 | B25: Финансовые обязательства, оцениваемые по справедливой стоимости через прибыль или убыток | C25: 7754218 | D25: 7500034
A26: 17.1 | B26: вклады (средства) физических лиц, в том числе индивидуальных предпринимателей
A27: 17а | B27: Производные финансовые инструменты для целей хеджирования
A28: 18 | B28: Выпущенные долговые ценные бумаги | C28: 77939 | D28: 58896
A29: 18.1 | B29: оцениваемые по справедливой стоимости через прибыль или убыток
A30: 18.2 | B30: оцениваемые по амортизированной стоимости | C30: 77939 | D30: 58896
A31: 19 | B31: Привлеченные субординированные кредиты (депозиты, займы) и выпущенные субординированные облигационные займы, классифицированные в качестве обязательств
A32: 20 | B32: Обязательства по текущему налогу на прибыль
A33: 21 | B33: Отложенные налоговые обязательства | C33: 1845878 | D33: 1579395
A34: 22 | B34: Прочие обязательства
A35: 23 | B35: Резервы на возможные потери по условным обязательствам кредитного характера, прочим возможным потерям и операциям с резидентами офшорных зон
A36: 24 | B36: Всего обязательств | C36: 826407677 | D36: 745046430
A37: III. Источники собственных средств | B37: III. Источники собственных средств
A38: 25 | B38: Средства акционеров (участников) | C38: 48015396 | D38: 48015396
A39: 26 | B39: Собственные акции (доли), выкупленные у акционеров (участников)
A40: 27 | B40: Эмиссионный доход
A41: 28 | B41: Резервный фонд | C41: 1451972 | D41: 1131454
A42: 29 | B42: Переоценка финансовых активов, оцениваемых по справедливой стоимости через прочий совокупный доход, уменьшенная на отложенное налоговое обязательство (увеличенная на отложенный налоговый актив) | C42: 2017491 | D42: 5595206
A43: 30 | B43: Переоценка основных средств, активов в форме права пользования и нематериальных активов, уменьшенная на отложенное налоговое обязательство | C43: 1855101 | D43: 1619662
A44: 31 | B44: Переоценка обязательств (требований) по выплате долгосрочных вознаграждений
A45: 32 | B45: Переоценка инструментов хеджирования
A46: 33 | B46: Денежные средства безвозмездного финансирования (вклады в имущество) | C46: 4210837 | D46: 4210837
A47: 34 | B47: Изменение справедливой стоимости финансового обязательства, обусловленное изменением кредитного риска
A48: 35 | B48: Привлеченные субординированные кредиты (депозиты, займы) и выпущенные субординированные облигационные займы, классифицированные в качестве долевых инструментов
A49: 36 | B49: Оценочные резервы под ожидаемые кредитные убытки | C49: 474163 | D49: 92027
A50: 37 | B50: Неиспользованная прибыль (убыток) | C50: 47074000 | D50: 31973825
A51: 38 | B51: Всего источников собственных средств | C51: 105098960 | D51: 92638407
A52: IV. Внебалансовые обязательства | B52: IV. Внебалансовые обязательства
A53: 39 | B53: Безотзывные обязательства кредитной организации | C53: 704624144 | D53: 696809435
A54: 40 | B54: Выданные кредитной организацией гарантии и поручительства | C54: 167663603 | D54: 180142323
A55: 41 | B55: Условные обязательства некредитного характера
A62: =Ф_806_2024[[#Headers],[Номер строки]] -> Номер строки | B62: =Ф_806_2024[[#Headers],[Наименование статьи]] -> Наименование статьи | C62: =Ф_806_2024[[#Headers],[2024]] -> 2024 | D62: =Ф_806_2024[[#Headers],[2023]] -> 2023
A63: КОРРЕКТИРОВКА на нераскрываемые статьи активов | C63: =C18-SUM(C3:C17)+C5+C8 -> 42736448 | D63: =D18-SUM(D3:D17)+D5+D8 -> 34809744
A64: КОРРЕКТИРОВКА на нераскрываемые статьи обязательств | C64: =C36-SUM(C20:C21,C25,C28,C31:C35) -> 24737210 | D64: =D36-SUM(D20:D21,D25,D28,D31:D35) -> 7414261
A65: КОРРЕКТИРОВКА на нераскрываемые статьи собственных средств | C65: =C51-(C38-C39+SUM(C40:C50)) -> 0 | D65: =D51-(D38-D39+SUM(D40:D50)) -> 0

Sheet Ф_814_2020-2015
A1: Номер строки | B1: Наименование статьи | C1: 2015 | D1: 2016 | E1: 2017 | F1: 2018 | G1: 2019 | H1: 2020
A2: 1 | B2: Чистые денежные средства, полученные от (использованные в) операционной деятельности
A3: 1.1 | B3: Денежные средства, полученные от (использованные в) операционной деятельности до изменений в операционных активах и обязательствах, всего, в том числе: | C3: -5507380 | D3: -4934070 | E3: -11392522 | F3: 2620320 | G3: 4067002 | H3: -3527895
A4: 1.1.1 | B4: проценты полученные | C4: 37568362 | D4: 36871823 | E4: 32865045 | F4: 34367799 | G4: 30116929 | H4: 31838074
A5: 1.1.2 | B5: проценты уплаченные | C5: -51945424 | D5: -29893095 | E5: -23570761 | F5: -20719498 | G5: -25908706 | H5: -22321117
A6: 1.1.3 | B6: комиссии полученные | C6: 2703650 | D6: 3665904 | E6: 4469501 | F6: 5580882 | G6: 6994739 | H6: 7918155
A7: 1.1.4 | B7: комиссии уплаченные | C7: -661724 | D7: -988175 | E7: -1354409 | F7: -1739783 | G7: -2329429 | H7: -3039552
A8: 1.1.5 | B8: доходы за вычетом расходов по операциям с финансовыми активами, оцениваемыми по справедливой стоимости через прибыль или убыток, через прочий совокупный доход | C8: 3210611 | D8: -2026815 | E8: -3422893 | F8: -1032209 | G8: 4128925 | H8: -25579382
A9: 1.1.6 | B9: доходы за вычетом расходов по операциям с ценными бумагами, оцениваемыми по амортизированной стоимости | C9: 0 | D9: 0
A10: 1.1.7 | B10: доходы за вычетом расходов по операциям с иностранной валютой | C10: 1020185 | D10: -38436 | E10: -236776 | F10: 73534 | G10: 393398 | H10: 7212275
A11: 1.1.8 | B11: прочие операционные доходы | C11: 24291149 | D11: 4193611 | E11: 4698564 | F11: 3394665 | G11: 5990438 | H11: 19336530
A12: 1.1.9 | B12: операционные расходы | C12: -21297511 | D12: -13958181 | E12: -24594632 | F12: -16355506 | G12: -14308228 | H12: -16024073
A13: 1.1.10 | B13: расход (возмещение) по налогам | C13: -396678 | D13: -2760706 | E13: -246161 | F13: -949564 | G13: -1011064 | H13: -2868804
A14: 1.2 | B14: Прирост (снижение) чистых денежных средств от операционных активов и обязательств, всего, в том числе: | C14: 4719587 | D14: 37080569 | E14: 5837256 | F14: -55625902 | G14: 53028089 | H14: -4628816
A15: 1.2.1 | B15: чистый прирост (снижение) по обязательным резервам на счетах в Банке России | C15: -662615 | D15: -590652 | E15: 429944 | F15: 987873 | G15: -511568 | H15: -94500
A16: 1.2.2 | B16: чистый прирост (снижение) по финансовым активам, оцениваемым по справедливой стоимости через прибыль или убыток | C16: 10237909 | D16: 1773884 | E16: 1442296 | F16: 1029920 | G16: -1903670 | H16: -1819649
A17: 1.2.3 | B17: чистый прирост (снижение) по ссудной задолженности | C17: -5999822 | D17: 15893067 | E17: 15617690 | F17: -101730120 | G17: -9878767 | H17: -18509409
A18: 1.2.4 | B18: чистый прирост (снижение) по прочим активам | C18: 8371889 | D18: 37242369 | E18: 2767966 | F18: -2656127 | G18: -1107820 | H18: 3081369
A19: 1.2.5 | B19: чистый прирост (снижение) по кредитам, депозитам и прочим средствам Банка России | C19: -28015197 | D19: -5540000 | F19: 742061 | G19: 781347 | H19: 4683926
A20: 1.2.6 | B20: чистый прирост (снижение) по средствам других кредитных организаций | C20: 10966904 | D20: -15099937 | E20: 3655541 | F20: -12243266 | G20: 3470757 | H20: -1019209
A21: 1.2.7 | B21: чистый прирост (снижение) по средствам клиентов, не являющихся кредитными организациями | C21: 24342752 | D21: 18741920 | E21: 28233574 | F21: 45598382 | G21: 74450522 | H21: 14956843
A22: 1.2.8 | B22: чистый прирост (снижение) по финансовым обязательствам, оцениваемым по справедливой стоимости через прибыль или убыток | C22: -8941751 | D22: -2222826 | E22: 70481 | F22: 15292732 | G22: -15238806 | H22: 2439763
A23: 1.2.9 | B23: чистый прирост (снижение) по выпущенным долговым обязательствам | C23: 1677594 | D23: -22057227 | E23: -46487936 | F23: -2180730 | G23: 4714 | H23: -1222723
A24: 1.2.10 | B24: чистый прирост (снижение) по прочим обязательствам | C24: -7258076 | D24: 8939971 | E24: 107699 | F24: -466627 | G24: 2961380 | H24: -7125227
A25: 1.3 | B25: Итого (сумма строк 1.1 и 1.2) | C25: -787793 | D25: 32146499 | E25: -5555266 | F25: -53005582 | G25: 57095091 | H25: -8156710
A26: 2 | B26: Чистые денежные средства, полученные от (использованные в) инвестиционной деятельности
A27: 2.1 | B27: Приобретение финансовых активов, оцениваемых по справедливой стоимости через прочий совокупный доход | C27: -128731841 | D27: -136050814 | E27: -288479227 | F27: -110242183 | G27: -95288936 | H27: -42945092
A28: 2.2 | B28: Выручка от реализации и погашения финансовых активов, оцениваемых по справедливой стоимости через прочий совокупный доход | C28: 114125512 | D28: 102695959 | E28: 277047762 | F28: 162991729 | G28: 99151063 | H28: 40401469
A29: 2.3 | B29: Приобретение ценных бумаг, оцениваемых по амортизированной стоимости | C29: -3535064 | D29: 1372613 | E29: 2689691 | F29: -669730 | G29: -95912545 | H29: -30575649
A30: 2.4 | B30: Выручка от погашения ценных бумаг, оцениваемых по амортизированной стоимости | C30: 54206 | D30: 2923031 | E30: 1603493 | F30: 1854959 | G30: 43876921 | H30: 31190381
A31: 2.5 | B31: Приобретение основных средств, нематериальных активов и материальных запасов | C31: -446438 | D31: -159965 | E31: -485161 | F31: -825096 | G31: -1766021 | H31: -2336352
A32: 2.6 | B32: Выручка от реализации основных средств, нематериальных активов и материальных запасов | C32: 111318 | D32: 21161 | E32: 383889 | F32: 426564 | G32: 252553 | H32: 344143
A33: 2.7 | B33: Дивиденды полученные | C33: -37371 | D33: 503 | E33: 93482 | F33: 8 | G33: 86
A34: 2.8 | B34: Итого (сумма строк с 2.1 по 2.7) | C34: -18459678 | D34: -29197512 | E34: -7146071 | F34: 53536251 | G34: -49686878 | H34: -3921100
A35: 3 | B35: Чистые денежные средства, полученные от (использованные в) финансовой деятельности
A36: 3.1 | B36: Взносы акционеров (участников) в уставный капитал | C36: 9800000 | D36: 4210837 | E36: 10000000
A37: 3.2 | B37: Приобретение собственных акций (долей), выкупленных у акционеров (участников) | C37: 0 | D37: 0
A38: 3.3 | B38: Продажа собственных акций (долей), выкупленных у акционеров (участников) | C38: 0 | D38: 0
A39: 3.4 | B39: Выплаченные дивиденды | C39: 0 | D39: 0
A40: 3.5 | B40: Итого (сумма строк с 3.1 по 3.4) | C40: 9800000 | D40: 4210837 | E40: 10000000
A41: 4 | B41: Влияние изменений курсов иностранных валют, установленных Банком России, на денежные средства и их эквиваленты | C41: 8040061 | D41: -9540574 | E41: 940149 | F41: -73879 | G41: 37545 | H41: 18363042
A42: 5 | B42: Прирост (использование) денежных средств и их эквивалентов | C42: -1407410 | D42: -2380750 | E42: -1761187 | F42: 456790 | G42: 7445758 | H42: 6285232
A43: 5.1 | B43: Денежные средства и их эквиваленты на начало отчетного года | C43: 26849761 | D43: 25442351 | E43: 23061601 | F43: 21300414 | G43: 21757204 | H43: 29202962
A44: 5.2 | B44: Денежные средства и их эквиваленты на конец отчетного периода | C44: 25442351 | D44: 23061601 | E44: 21300414 | F44: 21757204 | G44: 29202962 | H44: 35488194

Sheet Банк. система_ввод
E7: =МСФО_ввод!D7 -> млрд руб. | G7: На 31.12'
G8: 2010 | H8: 2011 | I8: 2012 | J8: 2013 | K8: 2014 | L8: 2015 | M8: 2016 | N8: 2017 | O8: 2018 | P8: 2019 | Q8: 2020 | R8: 2021 | S8: 2022 | T8: 2023 | U8: 2024 | V8: 2025
D12: Собственный капитал по всей совокупности российских банков
D13: млрд руб. | G13: На 31.12'
G14: =G8 -> 2010 | H14: =H8 -> 2011 | I14: =I8 -> 2012 | J14: =J8 -> 2013 | K14: =K8 -> 2014 | L14: =L8 -> 2015 | M14: =M8 -> 2016 | N14: =N8 -> 2017 | ... V14: =V8 -> 2025
C15: 1. | D15: Основной капитал (I уровня) | G15: =0.114*G21 -> 2526.7302 | H15: =0.093*H21 -> 3325.7358 | I15: =0.085*I21 -> 3794.4595 | J15: =SUM(J16:J17) -> 4838 | K15: =K16+K17 -> 5718.4 | L15: =L16+L17 -> 6002.5 | M15: =M16+M17 -> 6586.7 | N15: =N16+N17 -> 6622.8 | O15: =O16+O17 -> 7499.7 | P15: =P16+P17 -> 8224.5 | Q15: =Q16+Q17 -> 8890.7929 | R15: =R16+R17 -> 9933.1985 | ... V15: =V16+V17 -> 17262.788
D16: - | E16: Базовый капитал | J16: 4812 | K16: 5638.3 | L16: 5857.8 | M16: 6408.2 | N16: 6417.9 | O16: 7012.3 | P16: 7643.2 | Q16: 8043.1993 | R16: 8739.7856 | S16: 9798.4799 | T16: 12660.925 | U16: 14138.606 | V16: 16078.15
D17: - | E17: Добавочный капитал | J17: 26 | K17: 80.1 | L17: 144.7 | M17: 178.5 | N17: 204.9 | O17: 487.4 | P17: 581.3 | Q17: 847.59362 | R17: 1193.4129 | S17: 1145.6615 | T17: 1248.7658 | U17: 1344.3361 | V17: 1184.6381
C18: 2. | D18: Дополнительный капитал (II уровня) | G18: =G19-G15 -> 2205.5698 | H18: =H19-H15 -> 1916.3642 | I18: =I19-I15 -> 2318.4405 | J18: =J19-J15 -> 2226.3 | K18: 2210 | L18: 3006.1 | M18: 2800.4 | N18: 2774.6 | O18: 2769.6 | P18: 2756.6 | Q18: 2522.3503 | R18: 2671.855 | S18: 2404.0756 | T18: 3232.761 | U18: 3431.0444 | V18: 3467.7549
D19: Собственный (регуляторный) капитал, итого | G19: 4732.3 | H19: 5242.1 | I19: 6112.9 | J19: 7064.3 | K19: =K15+K18 -> 7928.4 | L19: =L15+L18 -> 9008.6 | M19: =M15+M18 -> 9387.1 | N19: =N15+N18 -> 9397.4 | O19: =O15+O18 -> 10269.3 | P19: =P15+P18 -> 10981.1 | Q19: =Q15+Q18 -> 11413.143 | R19: =R15+R18 -> 12605.054 | ... V19: =V15+V18 -> 20730.543
D20: Активы, всего | G20: 31480.513 | H20: 39139.628 | I20: 46860.262 | J20: 54382.128 | K20: 73423.809 | L20: 77474.262 | M20: 74092.991 | N20: 77961.134 | O20: 86231.98 | P20: 88796.188 | Q20: 104023.03 | R20: 120536.63 | S20: 134818.45 | T20: 167830.41 | U20: 199255.74 | V20: 210874.52
D21: Активы, взвешенные по риску, всего | G21: 22164.3 | H21: 35760.6 | I21: 44640.7 | J21: 52473.9 | K21: 63456.9 | L21: 70914.5 | M21: 71810.2 | N21: 77884.2 | O21: 84510.1 | P21: 89055.478 | Q21: 90915.544 | R21: 102106.12 | S21: 104188.88 | T21: 127965.39 | U21: 149963.44 | V21: 156050.77
E22: то же в % к активам | G22: =G21/G20 -> 0.70406413 | H22: =H21/H20 -> 0.91366736 | I22: =I21/I20 -> 0.95263446 | J22: =J21/J20 -> 0.96491076 | K22: =K21/K20 -> 0.86425509 | L22: =L21/L20 -> 0.91532979 | M22: =M21/M20 -> 0.96919019 | N22: =N21/N20 -> 0.99901318 | ... V22: =V21/V20 -> 0.7400172
G24: На 31.12'
D25: Структура Активов, взвешенных по риску (знаменатель в формуле Н1) | G25: =G8 -> 2010 | H25: =H8 -> 2011 | I25: =I8 -> 2012 | J25: =J8 -> 2013 | K25: =K8 -> 2014 | L25: =L8 -> 2015 | M25: =M8 -> 2016 | N25: =N8 -> 2017 | ... V25: =V8 -> 2025
D26: Активы, взвешенные по риску (RWA) | J26: =J21 -> 52473.9 | K26: =K21 -> 63456.9 | L26: =L21 -> 70914.5 | M26: =M21 -> 71810.2 | N26: =N21 -> 77884.2 | O26: =O21 -> 84510.1 | P26: =P21 -> 89055.478 | Q26: =Q21 -> 90915.544 | ... V26: =V21 -> 156050.77
E27: Кредитный риск по балансовым активам (Аi) | J27: 29502.1 | K27: 35225.2 | L27: 40081.2 | M27: 35299.7 | N27: 33381.9 | O27: 32952.1 | P27: 36131.2
E28: Операции с повышенным коэффициентом (ПК и ПКв) | J28: 9078.3 | K28: 9592.6 | L28: 11168.6 | M28: 15127.5 | N28: 17234.5 | O28: 8465.5 | P28: 7462.3
E29: Величина кредитного риска с учетом надбавок, рассчитанная на основе ПВР для целей включения в норматив достаточности капитала (КРП и код 8770) | O29: 16308.2 | P29: 19102.2
E30: Операционный риск (ОР) с k=12,5 | J30: 3558.1 | K30: 5264.7 | L30: 6732.5 | M30: 7486.4 | N30: 8369.8 | O30: 8137.4 | P30: 8191
E31: Рыночный риск (РР) | J31: 3101.5 | K31: 2734.6 | L31: 3859.4 | M31: 4012.4 | N31: 3916.1 | O31: 3737.8 | P31: 3873.6
E32: Кредитный риск по условным обязательствам кредитного характера (КРВ) | J32: 3971.4 | K32: 4802 | L32: 4198.1 | M32: 4152.6 | N32: 4589.8 | O32: 3897.7 | P32: 4500.7
E33: Требования к связанным лицам (код 8957) | J33: 2087.6 | K33: 1700.4 | L33: 1919.5 | M33: 2297 | N33: 3056.6 | O33: 2546.1 | P33: 0
E34: Показатель, предусматривающий применение повышенных требований по покрытию капиталом соответствующего уровня отдельных активов банка в соответствии с международными подходами к повышению устойчивости банковского сектора (БК) | J34: 17.3 | K34: 329.6 | L34: 653.2 | M34: 1667.5 | N34: 5139.8 | O34: 5021.4 | P34: 3006.4
E35: Прочие элементы | J35: =J26-SUM(J27:J34) -> 1157.6 | K35: =K26-SUM(K27:K34) -> 3807.8 | L35: =L26-SUM(L27:L34) -> 2302 | M35: =M26-SUM(M27:M34) -> 1767.1 | N35: =N26-SUM(N27:N34) -> 2195.7 | O35: =O26-SUM(O27:O34) -> 3443.9 | P35: =P26-SUM(P27:P34) -> 6788.0784
G37: На 31.12'
D38: Структура Активов, взвешенных по риску (знаменатель в формуле Н1) | J38: =J8 -> 2013 | K38: =K8 -> 2014 | L38: =L8 -> 2015 | M38: =M8 -> 2016 | N38: =N8 -> 2017 | O38: =O8 -> 2018 | P38: =P8 -> 2019 | Q38: =Q8 -> 2020 | ... V38: =V8 -> 2025 | AA38: =J38 -> 2013 | AB38: =K38 -> 2014 | AC38: =L38 -> 2015 | AD38: =M38 -> 2016 | AE38: =N38 -> 2017 | AF38: =O38 -> 2018 | AG38: =P38 -> 2019 | AH38: =Q38 -> 2020 | ... AK38: =T38 -> 2023
D39: Активы, взвешенные по риску (RWA) | J39: =J21 -> 52473.9 | K39: =K21 -> 63456.9 | L39: =L21 -> 70914.5 | M39: =M21 -> 71810.2 | N39: =N21 -> 77884.2 | O39: =O21 -> 84510.1 | P39: =P21 -> 89055.478 | Q39: =Q21 -> 90915.544 | ... V39: =V21 -> 156050.77 | AA39: =J39 -> 52473.9 | AB39: =K39 -> 63456.9 | AC39: =L39 -> 70914.5 | AD39: =M39 -> 71810.2 | AE39: =N39 -> 77884.2 | AF39: =O39 -> 84510.1 | AG39: =P39 -> 89055.478 | AH39: =Q39 -> 90915.544
D40: 1. Кредитные риски всего, из них | J40: =J39-J46-J47 -> 45814.3 | K40: =K39-K46-K47 -> 55457.6 | L40: =L39-L46-L47 -> 60322.6 | M40: =M39-M46-M47 -> 60311.4 | N40: =N39-N46-N47 -> 65598.3 | O40: =O39-O46-O47 -> 72634.9 | P40: 73984.454 | Q40: 72810.423 | R40: 83160.435 | S40: 83646.437 | T40: 105522.36 | U40: 125139.11 | V40: 128547.79 | AA40: =J40/J$39 -> 0.87308738 | AB40: =K40/K$39 -> 0.87394121 | AC40: =L40/L$39 -> 0.85063844 | AD40: =M40/M$39 -> 0.83987233 | AE40: =N40/N$39 -> 0.84225427 | AF40: =O40/O$39 -> 0.85948188 | AG40: =P40/P$39 -> 0.83076814 | AH40: =Q40/Q$39 -> 0.80085781
E41: 1.1. Кредитный риск (стандартный подход) | P41: 50246.666 | Q41: 11523.466 | R41: 8356.5855 | S41: 7129.8653 | AG41: =P41/P$39 -> 0.56421757 | AH41: =Q41/Q$39 -> 0.12674913
E42: 1.2. Кредитный риск (финализированный подход) | Q42: 38622.069 | R42: 44836.372 | S42: 44759.578 | AG42: =P42/P$39 -> 0 | AH42: =Q42/Q$39 -> 0.4248126
E43: 1.3. Кредитный риск на основе внутренних рейтингов (ПВР) | P43: 18591.613 | Q43: 17017.241 | R43: 20966.915 | S43: 30651.694 | AG43: =P43/P$39 -> 0.20876439 | AH43: =Q43/Q$39 -> 0.18717636
E44: 1.4. Макропруденциальные надбавки | P44: 5146.1762 | Q44: 5647.6475 | R44: 9000.5624 | S44: 1105.299 | AG44: =P44/P$39 -> 0.057786183 | AH44: =Q44/Q$39 -> 0.062119713
D45: 2. Повышенный риск по вложениям в акции (доли) и отложенные налоговые активы | P45: 3006.4243 | Q45: 4308.5566 | R45: 5041.4107 | S45: 5629.878 | T45: 5953.1849 | U45: 7382.4912 | V45: 10265.096 | AG45: =P45/P$39 -> 0.033759005 | AH45: =Q45/Q$39 -> 0.047390758
D46: 3. Операционный риск | J46: =J30 -> 3558.1 | K46: =K30 -> 5264.7 | L46: =L30 -> 6732.5 | M46: =M30 -> 7486.4 | N46: =N30 -> 8369.8 | O46: =O30 -> 8137.4 | P46: 8191.0073 | Q46: 8977.6327 | R46: 8609.2041 | S46: 10304.265 | T46: 11190.373 | U46: 12445.14 | V46: 13140.214 | AA46: =J46/J$39 -> 0.067807043 | AB46: =K46/K$39 -> 0.082964973 | AC46: =L46/L$39 -> 0.094938271 | AD46: =M46/M$39 -> 0.1042526 | AE46: =N46/N$39 -> 0.10746467 | AF46: =O46/O$39 -> 0.096289083 | AG46: =P46/P$39 -> 0.091976456 | AH46: =Q46/Q$39 -> 0.09874695
D47: 4. Рыночный риск | J47: =J31 -> 3101.5 | K47: =K31 -> 2734.6 | L47: =L31 -> 3859.4 | M47: =M31 -> 4012.4 | N47: =N31 -> 3916.1 | O47: =O31 -> 3737.8 | P47: 3873.5923 | Q47: 4818.9316 | R47: 5295.0705 | S47: 4608.2956 | T47: 5299.4794 | U47: 4996.6974 | V47: 4097.6722 | AA47: =J47/J$39 -> 0.059105574 | AB47: =K47/K$39 -> 0.043093816 | AC47: =L47/L$39 -> 0.054423284 | AD47: =M47/M$39 -> 0.055875071 | AE47: =N47/N$39 -> 0.050281058 | AF47: =O47/O$39 -> 0.044229033 | AG47: =P47/P$39 -> 0.043496395 | AH47: =Q47/Q$39 -> 0.053004485
G50: На 31.12'
D51: Норматив достаточности | G51: =G8 -> 2010 | H51: =H8 -> 2011 | I51: =I8 -> 2012 | J51: =J8 -> 2013 | K51: =K8 -> 2014 | L51: =L8 -> 2015 | M51: =M8 -> 2016 | N51: =N8 -> 2017 | ... V51: =V8 -> 2025
D52: - | E52: базового капитала Н1.1 (норматив - не ниже 4,5%) | G52: н/п | H52: н/п | I52: н/п | J52: 0.088 | K52: 0.089 | L52: 0.082 | M52: 0.089 | N52: 0.082 | O52: 0.083 | P52: 0.086 | Q52: 0.08738376 | R52: 0.08448176 | S52: 0.0927651 | T52: 0.097456671 | U52: 0.093472819 | V52: 0.102571
D53: - | E53: основного капитала Н1.2 (норматив - не ниже 6,0%) | G53: н/п | H53: н/п | I53: н/п | J53: 0.088 | K53: 0.09 | L53: 0.085 | M53: 0.092 | N53: 0.085 | O53: 0.089 | P53: 0.093 | Q53: 0.097 | R53: 0.09647721 | S53: 0.10409966 | T53: 0.10749771 | U53: 0.10258157 | V53: 0.11021252
D54: - | E54: собственного капитала Н1.0 (норматив - не ниже 8%) | G54: 0.181 | H54: 0.147 | I54: 0.137 | J54: 0.129 | K54: 0.125 | L54: 0.127 | M54: 0.131 | N54: 0.121 | O54: 0.122 | P54: 0.123 | Q54: 0.125 | R54: 0.12259456 | S54: 0.12703286 | T54: 0.13271609 | U54: 0.12471956 | V54: 0.13185038
G56: На 31.12'
G57: =G8 -> 2010 | H57: =H8 -> 2011 | I57: =I8 -> 2012 | J57: =J8 -> 2013 | K57: =K8 -> 2014 | L57: =L8 -> 2015 | M57: =M8 -> 2016 | N57: =N8 -> 2017 | ... V57: =V8 -> 2025
D58: Собственный (регуляторный) капитал (брутто) | G58: =G19 -> 4732.3 | H58: =H19 -> 5242.1 | I58: =I19 -> 6112.9 | J58: =J19 -> 7064.3 | K58: =K19 -> 7928.4 | L58: =L19 -> 9008.6 | M58: =M19 -> 9387.1 | N58: =N19 -> 9397.4 | ... V58: =V19 -> 20730.543
C59: - | D59: Иммобилизованные активы
E60: внеоборотные активы и запасы | G60: -864.6 | H60: -973.8 | I60: -1090.5 | J60: -1147.5 | K60: -1222.3 | L60: -1277.6 | M60: -1486.6 | N60: -1512.9 | O60: -1625.9 | P60: -1677 | Q60: -1961.6202 | R60: =-1843.278487 -> -1843.2785 | S60: -3185.7091 | T60: -3470.1267 | U60: -4116.5652 | V60: -4882.9338
E61: участие в капитале | G61: -493.09006 | H61: -667.24211 | I61: -900.24375 | J61: -942.5782 | K61: -1704.0548 | L61: -2144.2346 | M61: -2207.8587 | N61: -2466.9694 | O61: -2184.8454 | P61: -2160.4879 | Q61: -2398.1143 | R61: -2726.9711 | S61: -3107.5395 | T61: -3576.8396 | U61: -3868.4568 | V61: -4323.3017
C62: 0.6 | E62: просроченная задолженность (с k=0,6) | G62: -621.52457 | H62: -679.80826 | I62: -754.4406 | J62: -838.80315 | K62: -1186.8201 | L62: -1952.285 | M62: -1850.5626 | N62: -1708.1736 | O62: -1594.8933 | P62: -1750.0665 | Q62: -2039.0639 | R62: -1866.925 | S62: -1979.6076 | T62: -1977.0231 | U62: -2176.794 | V62: -2633.1501
C63: = | D63: Собственный капитал (нетто) | G63: =SUM(G58:G62) -> 2753.0854 | H63: =SUM(H58:H62) -> 2921.2496 | I63: =SUM(I58:I62) -> 3367.7156 | J63: =SUM(J58:J62) -> 4135.4187 | K63: =SUM(K58:K62) -> 3815.2251 | L63: =SUM(L58:L62) -> 3634.4803 | M63: =SUM(M58:M62) -> 3842.0787 | N63: =SUM(N58:N62) -> 3709.3571 | ... V63: =SUM(V58:V62) -> 8891.1574
D65: Доля собственного капитала на покрытие иммобилизации (<50%) | G65: =1-G63/G58 -> 0.41823524 | H65: =1-H63/H58 -> 0.44273294 | I65: =1-I63/I58 -> 0.44908053 | J65: =1-J63/J58 -> 0.41460319 | K65: =1-K63/K58 -> 0.51879004 | L65: =1-L63/L58 -> 0.59655437 | M65: =1-M63/M58 -> 0.59070653 | N65: =1-N63/N58 -> 0.60527837 | ... V65: =1-V63/V58 -> 0.57110832
D67: Для расчетов
G68: На 31.12'
E69: млрд руб. | G69: =G8 -> 2010 | H69: =H8 -> 2011 | I69: =I8 -> 2012 | J69: =J8 -> 2013 | K69: =K8 -> 2014 | L69: =L8 -> 2015 | M69: =M8 -> 2016 | N69: =N8 -> 2017 | ... V69: =V8 -> 2025
D70: Итого активов | G70: =G20 -> 31480.513 | H70: =H20 -> 39139.628 | I70: =I20 -> 46860.262 | J70: =J20 -> 54382.128 | K70: =K20 -> 73423.809 | L70: =L20 -> 77474.262 | M70: =M20 -> 74092.991 | N70: =N20 -> 77961.134 | ... U70: =U20 -> 199255.74 | V70: 210874.52
D71: Собственный (бухгалтерский) капитал | G71: 4339.1466 | H71: 4963.0292 | I71: 5911.0052 | J71: 6629.2126 | K71: 6921.8997 | L71: 7551.7439 | M71: 8611.3962 | N71: 8962.9303 | O71: 9306.1348 | P71: 10009.2 | Q71: 10680.898 | R71: 11979.264 | S71: 13431.078 | T71: 15550.211 | U71: 17543.742 | V71: 20251.205
D72: Активы, которые генерируют процентный доход (брутто) | G72: 27549.769 | H72: 34039.115 | I72: 40118.637 | J72: 47591.037 | K72: 61253.229 | L72: 67889.141 | M72: 65950.827 | N72: 70548.318 | O72: 78015.674 | P72: 80722.221 | Q72: 94664.525 | R72: 109813.73 | S72: 119485.51 | T72: 130222.34 | U72: 162665.12 | V72: 189681.36
D73: Пассивы, по которым уплачиваются проценты | G73: 22544.694 | H73: 26159.278 | I73: 32908.735 | J73: 39233.155 | K73: 45816.518 | L73: 61172.812 | M73: 65625.736 | N73: 62175.645 | O73: 65922.947 | P73: 73459.5 | Q73: 75104.67 | R73: 104975.62 | S73: 116752.55 | T73: 143180.11 | U73: 169711.34 | V73: 179595.1
D74: Работающие активы | G74: 26839.727 | H74: 33622.369 | I74: 39873.064 | J74: 47066.939 | K74: 62349.356 | L74: 67037.934 | M74: 64687.122 | N74: 68657.053 | O74: 75969.133 | P74: 77748.775 | Q74: 91650.776 | R74: 106659.03 | S74: 119955.55 | T74: 148395.17 | U74: 175357.36 | V74: 182135.76
D75: Среднегодовая численность сотрудников, чел. | K75: 950000 | L75: 950000 | M75: 838000 | N75: =M75*0.97 -> 812860 | O75: =N75*0.97 -> 788474.2 | P75: =O75*0.97 -> 764819.97 | Q75: =P75*0.97 -> 741875.37 | R75: =Q75 -> 741875.37 | S75: =R75 -> 741875.37 | T75: =S75*1.05 -> 778969.14 | U75: =T75*1.05 -> 817917.6 | V75: =U75 -> 817917.6
A76: Банк России | D76: Cтоимость риска (CoR) по кредитам ЮЛ, % | P76: 0.01 | Q76: 0.011 | R76: -0.001 | S76: 0.015 | T76: 0.007 | U76: 0.003 | V76: 0.01
D77: Cтоимость риска (CoR) по кредитам ФЛ, % | P77: 0.014 | Q77: 0.0265 | R77: 0.015 | S77: 0.024 | T77: 0.017 | U77: 0.023 | V77: 0.029
D78: Гарантии и поручительства | R78: 7688.3417 | S78: 8235.5816 | T78: 10045.779 | U78: 11042 | V78: 14103.877
D85: Курс доллара США (ЦБ РФ) на дату
G86: На 31.12'
G87: =G8 -> 2010 | H87: =H8 -> 2011 | I87: =I8 -> 2012 | J87: =J8 -> 2013 | K87: =K8 -> 2014 | L87: =L8 -> 2015 | M87: =M8 -> 2016 | N87: =N8 -> 2017 | ... V87: =V8 -> 2025
D88: Курс доллара США (ЦБ РФ) на дату | G88: 30.3505 | H88: 31.8729 | I88: 30.4215 | J88: 32.6587 | K88: 56.2584 | L88: 72.8827 | M88: 60.6569 | N88: 57.6002 | O88: 69.4706 | P88: 61.9057 | Q88: 73.8757 | R88: 75.1315 | S88: 70.3002 | T88: 90.404 | U88: 101.6797 | V88: 78.2267
D91: Структура доходов и расходов кредитных организаций в России (по данным ЦБ РФ)
F93: млрд руб. | G93: На 31.12'
A94: 1 | G94: =G8 -> 2010 | H94: =H8 -> 2011 | I94: =I8 -> 2012 | J94: =J8 -> 2013 | K94: =K8 -> 2014 | L94: =L8 -> 2015 | M94: =M8 -> 2016 | N94: =N8 -> 2017 | ... V94: =V8 -> 2025
A95: 2 | B95: Стабильные источники прибыли от банковской деятельности
A96: 3 | B96: 1 | C96: Процентные доходы | J96: 3962.6 | K96: 4776.5 | L96: 5783.8 | M96: =6484.8+0.1 -> 6484.9 | N96: =5781.1+0.8 -> 5781.9 | O96: =O97+O98+O104 -> 6179.0557 | P96: =P97+P98+P104 -> 6728.0227 | Q96: =Q97+Q98+Q104 -> 6422.7852 | R96: =R97+R98+R104 -> 7217.4086 | S96: =S97+S98+S104 -> 10512.365 | T96: =T97+T98+T104 -> 13520.017 | U96: =U97+U98+U104 -> 23633.132 | V96: =V97+V98+V104 -> 29468.445 | W96: =W97+W98+W104 -> 0
A97: 4 | C97: 1.1 | D97: От размещения средств в кредитных организациях | O97: 608.27688 | P97: 619.35034 | Q97: 436.44097 | R97: 518.26001 | S97: 1174.7174 | T97: 1619.8676 | U97: 3494.2595 | V97: 4008.2515
A98: 5 | C98: 1.2 | D98: От ссуд, предоставленных клиентам, не являющимся кредитными организациями | O98: 4844.695 | P98: =SUM(P99:P102) -> 5339.0922 | Q98: =SUM(Q99:Q102) -> 5248.3829 | R98: =SUM(R99:R102) -> 5731.1742 | S98: =SUM(S99:S102) -> 8040.035 | T98: =SUM(T99:T102) -> 10183.387 | U98: =SUM(U99:U102) -> 17425.324 | V98: =SUM(V99:V102) -> 21636.204 | W98: =SUM(W99:W102) -> 0
A99: 6 | D99: По корпоративным кредитам | P99: 3050.5432 | Q99: 2817.1401 | R99: 3077.7284 | S99: 4846.6389 | T99: 6247.625 | U99: 11463.05 | V99: 14833.04
A100: 7 | D100: По розничным кредитам | P100: 2215.335 | Q100: 2369.5609 | R100: 2604.4797 | S100: 3141.2936 | T100: 3831.9925 | U100: 5930.983 | V100: 6733.5081
A101: 8 | D101: По кредитам, выданным государственным структурам | P101: 53.320436 | Q101: 46.195239 | R101: 35.722071 | S101: 18.947604 | T101: 15.853417 | U101: 26.342716 | V101: 61.589576
A102: 9 | D102: Прочее | P102: 19.893512 | Q102: 15.486677 | R102: 13.244042 | S102: 33.154844 | T102: 87.915839 | U102: 4.947649 | V102: 8.066859
A103: 10 | C103: 1.3 | D103: От оказания услуг по финансовой аренде (лизингу)
A104: 11 | C104: 1.4 | D104: От вложений в ценные бумаги | O104: 726.08379 | P104: 769.5801 | Q104: 737.96132 | R104: 967.97439 | S104: 1297.6124 | T104: 1716.7626 | U104: 2713.5494 | V104: 3823.9892
A105: 12 | B105: 2 | C105: Процентные расходы | J105: -1987.6 | K105: -2565.5 | L105: -4162.4 | M105: -3831.8 | N105: -3189 | O105: =O106+O107+O112 -> -2989.4939 | P105: =P106+P107+P112 -> -3393.6431 | Q105: =Q106+Q107+Q112 -> -2809.1548 | R105: =R106+R107+R112 -> -3136.2911 | S105: =S106+S107+S112 -> -6315.82 | T105: =T106+T107+T112 -> -7518.9389 | U105: =U106+U107+U112 -> -16974.75 | V105: =V106+V107+V112 -> -21697.185 | W105: =W106+W107+W112 -> 0
A106: 13 | C106: 2.1 | D106: По привлеченным средствам кредитных организаций | O106: -545.02933 | P106: -532.3096 | Q106: -420.65906 | R106: -505.85506 | S106: -1122.599 | T106: -1641.8719 | U106: -3406.9834 | V106: -3469.8282
A107: 14 | C107: 2.2 | D107: По привлеченным средствам клиентов, не являющихся кредитными организациями | O107: -2296.7636 | P107: =SUM(P108:P111) -> -2714.4729 | Q107: =SUM(Q108:Q111) -> -2225.5055 | R107: =SUM(R108:R111) -> -2449.1839 | S107: =SUM(S108:S111) -> -4999.0081 | T107: =SUM(T108:T111) -> -5676.9608 | U107: =SUM(U108:U111) -> -13267.465 | V107: =SUM(V108:V111) -> -17871.475 | W107: =SUM(W108:W111) -> 0
A108: 15 | D108: По средствам от корпоративных клиентов | P108: -1124.7062 | Q108: -949.80695 | R108: -1141.8172 | S108: -2213.6863 | T108: -2875.6829 | U108: -6247.9228 | V108: -7635.5827
A109: 16 | D109: По средствам от физических лиц | P109: -1259.0358 | Q109: -1061.2029 | R109: -905.23868 | S109: -2090.7653 | T109: -2021.1435 | U109: -5172.9187 | V109: -8372.8704
A110: 17 | D110: По средствам от государственных структур | P110: -327.31585 | Q110: -211.87061 | R110: -399.97986 | S110: -691.67708 | T110: -779.93192 | U110: -1833.568 | V110: -1835.6296
A111: 18 | D111: Прочее | P111: -3.415137 | Q111: -2.62503 | R111: -2.148117 | S111: -2.879361 | T111: -0.202471 | U111: -13.055191 | V111: -27.392259
A112: 19 | C112: 2.3 | D112: По выпущенным долговым обязательствам | O112: -147.70097 | P112: -146.8606 | Q112: -162.99029 | R112: -181.25211 | S112: -194.21291 | T112: -200.10617 | U112: -300.30246 | V112: -355.88171
A113: 20 | C113: Чистые процентные доходы | J113: =J96+J105 -> 1975 | K113: =K96+K105 -> 2211 | L113: =L96+L105 -> 1621.4 | M113: =M96+M105 -> 2653.1 | N113: =N96+N105 -> 2592.9 | O113: =O96+O105 -> 3189.5617 | P113: =P96+P105 -> 3334.3795 | Q113: =Q96+Q105 -> 3613.6304 | ... V113: =V96+V105 -> 7771.2598
A114: 21 | B114: 3 | C114: Комиссионные доходы | J114: 806.4 | K114: 906.6 | L114: 974.7 | M114: 1132.8 | N114: 1180.6 | O114: 1396.8644 | P114: =SUM(P115:P120) -> 1616.3607 | Q114: =SUM(Q115:Q120) -> 1775.5892 | R114: =SUM(R115:R120) -> 2180.1526 | S114: =SUM(S115:S120) -> 2218.3437 | T114: =SUM(T115:T120) -> 2623.6674 | U114: =SUM(U115:U120) -> 3048.576 | V114: =SUM(V115:V120) -> 3331.2069
A115: 22 | D115: От расчетного и кассового обслуживания | P115: 626.79265 | Q115: 667.41277 | R115: 825.26458 | S115: 855.54454 | T115: 1020.113 | U115: 1175.2962 | V115: 1240.6633
A116: 23 | D116: От осуществления переводов денежных средств | P116: 427.65523 | Q116: 465.1812 | R116: 575.32478 | S116: 626.18397 | T116: 749.21484 | U116: 939.01342 | V116: 1055.5101
A117: 24 | D117: От открытия и ведения банковских счетов | P117: 118.05369 | Q117: 124.8584 | R117: 122.45219 | S117: 161.23954 | T117: 172.32718 | U117: 180.02869 | V117: 179.66883
A118: 25 | D118: От посреднических услуг по брокерским договорам | P118: 145.62435 | Q118: 186.76803 | R118: 245.00167 | S118: 175.07455 | T118: 183.79508 | U118: 203.65016 | V118: 252.86067
A119: 26 | D119: От банковских гарантий и поручительств | P119: 75.327003 | Q119: 97.994758 | R119: 120.17035 | S119: 146.72481 | T119: 195.00727 | U119: 233.98513 | V119: 240.39332
